Workbook
Name AliBEVBattCap: #REF!
Name AliBEVBattCap: #REF!
Name AliBEVBattCap: #REF!
Name AliBEVBattCap: #REF!
Name AliBEVBattCap: #REF!
Name AliBEVBattCap: #REF!
Name AliBEVBattCap: #REF!
Name AliBEVBattCap: #REF!
Name AliBEVBattCap: #REF!
Name AliBEVBattCap: #REF!
Name AliBEVBattCap: #REF!
Name AliBEVBattCap: #REF!
Name AliBEVBattCap: #REF!
Name AliBEVBattCap: #REF!
Name AliBEVBattCap: #REF!
Name AliBEVBattCap: #REF!
Name AliBEVBattCap: #REF!
Name AliBEVBattCap: #REF!
Name AliBEVBattCap: #REF!
Name AliBEVBattCap: #REF!
Name AliBEVBattCap: #REF!
Name AliBEVBattCap: #REF!
Name AliBkWhpYear: #REF!
Name AliBkWhpYear: #REF!
Name AliBkWhpYear: #REF!
Name AliBkWhpYear: #REF!
Name AliBkWhpYear: #REF!
Name AliBkWhpYear: #REF!
Name AliBkWhpYear: #REF!
Name AliBkWhpYear: #REF!
Name AliBkWhpYear: #REF!
Name AliBkWhpYear: #REF!
Name AliBkWhpYear: #REF!
Name AliBkWhpYear: #REF!
Name AliBkWhpYear: #REF!
Name AliBkWhpYear: #REF!
Name AliBkWhpYear: #REF!
Name AliBkWhpYear: #REF!
Name AliBkWhpYear: #REF!
Name AliBkWhpYear: #REF!
Name AliBkWhpYear: #REF!
Name AliBkWhpYear: #REF!
Name AliBkWhpYear: #REF!
Name AliBkWhpYear: #REF!
Name AliBOppChargeFact: #REF!
Name AliBOppChargeFact: #REF!
Name AliBOppChargeFact: #REF!
Name AliBOppChargeFact: #REF!
Name AliBOppChargeFact: #REF!
Name AliBOppChargeFact: #REF!
Name AliBOppChargeFact: #REF!
Name AliBOppChargeFact: #REF!
Name AliBOppChargeFact: #REF!
Name AliBOppChargeFact: #REF!
Name AliBOppChargeFact: #REF!
Name AliBOppChargeFact: #REF!
Name AliBOppChargeFact: #REF!
Name AliBOppChargeFact: #REF!
Name AliBOppChargeFact: #REF!
Name AliBOppChargeFact: #REF!

Sheet Parameters Fixed
D3: 19T Rigid Market L | E3: 28T Rigid Market L | F3: 48T Rigid Market L | G3: 19T Rigid Parcel | H3: 28T Rigid Parcel | I3: 15T Rigid Perishble | J3: 28T Tip C&M | K3: 35T Tip C&M | L3: 48T Rigid Cement | M3: 55T TT Cement | N3: 55T TT Cement | O3: 28T Rigid POL Tnkr | P3: 28T Rigid NonPOL | Q3: 40T TT LPG
A4: 1 | B4: Fuel/Energy Efficienchy (kmpl, km.kg & kWh/km | C4: Diesel | D4: 5.2 | E4: 4.5 | F4: 2.9 | G4: 5 | H4: 4.5 | I4: 6 | J4: 3.8 | K4: 3 | L4: 2.9 | M4: 2.6 | N4: 2.6 | O4: 4.7 | P4: 4.7 | Q4: 3.6
C5: CNG | D5: 5.4 | E5: 4.8 | F5: 3.1 | G5: 5.4 | H5: 4.8 | I5: 6.3 | J5: 4 | K5: 3.2 | L5: 3.1 | M5: 2.8 | N5: 2.7 | O5: 4.9 | P5: 4.9 | Q5: 3.8
C6: LNG | D6: =(D4+D5)/2 -> 5.3 | E6: =(E4+E5)/2 -> 4.65 | F6: =(F4+F5)/2 -> 3 | G6: =(G4+G5)/2 -> 5.2 | H6: =(H4+H5)/2 -> 4.65 | I6: =(I4+I5)/2 -> 6.15 | J6: =(J4+J5)/2 -> 3.9 | K6: =(K4+K5)/2 -> 3.1 | ... Q6: =(Q4+Q5)/2 -> 3.7
C7: H2 ICE | D7: =D4*3 -> 15.6 | E7: =E4*3 -> 13.5 | F7: =F4*3 -> 8.7 | G7: =G4*3 -> 15 | H7: =H4*3 -> 13.5 | I7: =I4*3 -> 18 | J7: =J4*3 -> 11.4 | K7: =K4*3 -> 9 | ... Q7: =Q4*3 -> 10.8
C8: BET | D8: 0.95 | E8: 1.2 | F8: 1.35 | G8: 0.9 | H8: 1.15 | I8: 0.85 | J8: 1.3 | K8: 1.4 | L8: 1.4 | M8: 1.45 | N8: 1.4 | O8: 1.05 | P8: 1.05 | Q8: 1.25
C9: H2 FCET | D9: =D4*4 -> 20.8 | E9: =E4*4 -> 18 | F9: =F4*4 -> 11.6 | G9: =G4*4 -> 20 | H9: =H4*4 -> 18 | I9: =I4*4 -> 24 | J9: =J4*4 -> 15.2 | K9: =K4*4 -> 12 | ... Q9: =Q4*4 -> 14.4
A10: 2 | B10: Weights (kgs.) | C10: GVW | D10: 18500 | E10: 28000 | F10: 47500 | G10: 18500 | H10: 28000 | I10: 16000 | J10: 28000 | K10: 35000 | L10: 47500 | M10: 55000 | N10: 55000 | O10: 28000 | P10: 28000 | Q10: 39500
C11: ULW (ICE Trucks) | D11: 8000 | E11: 9000 | F11: 12500 | G11: 8000 | H11: 9500 | I11: 6500 | J11: 13500 | K11: 15000 | L11: 12500 | M11: 15500 | N11: 15000 | O11: 9500 | P11: 9500 | Q11: 19000
A12: 3 | B12: Maintenance Cost per km (incl. Tyres, suspension/body repairs, Battery & Fuel Cell Replacements (average for 10 years of operation) - Rs./km. in 2025 | C12: Diesel | D12: 2.8 | E12: 4.2 | F12: 7.7 | G12: 2.8 | H12: 4.2 | I12: 3.1 | J12: 8.6 | K12: 10.9 | L12: 7.7 | M12: 6.5 | N12: 8.3 | O12: 3.5 | P12: 3.5 | Q12: 4.3
C13: CNG/LNG/H2 ICE | D13: 3.3 | E13: 4.7 | F13: 8.2 | G13: 3.3 | H13: 4.7 | I13: 3.6 | J13: 9.1 | K13: 11.4 | L13: 8.2 | M13: 7 | N13: 8.8 | O13: 4 | P13: 4 | Q13: 4.8
C14: BET | D14: 3.2223832 | E14: 4.0777952 | F14: 5.071053 | G14: 3.4223832 | H14: 3.822979 | I14: 2.9981448 | J14: 5.1684913 | K14: 5.6727918 | L14: 4.9389099 | M14: 4.5635747 | N14: 4.9840216 | O14: 3.9351253 | P14: 3.9549666 | Q14: 4.6373487
C15: H2 FCET | D15: 3.8648341 | E15: 4.12 | F15: 5.4782857 | G15: 4.0966667 | H15: 3.9366667 | I15: 3.605 | J15: 6.1212 | K15: 6.238 | L15: 5.4421429 | M15: 5.447619 | N15: 5.6785714 | O15: 4.7702 | P15: 4.3702 | Q15: 5.6425
A16: 4 | B16: Maintenance Cost per km (incl. Tyres, suspension/body repairs, Battery & Fuel Cell Replacements (average for 10 years of operation) - Rs./km. in 2055 | C16: Diesel | D16: 9.081513 | E16: 13.62227 | F16: 24.974161 | G16: 9.081513 | H16: 13.62227 | I16: 10.054532 | J16: 27.893219 | K16: 35.353033 | L16: 24.974161 | M16: 21.082084 | N16: 26.920199 | O16: 11.351891 | P16: 11.351891 | Q16: 13.946609
C17: CNG/LNG/H2 ICE | D17: 10.703212 | E17: 15.243968 | F17: 26.59586 | G17: 10.703212 | H17: 15.243968 | I17: 11.676231 | J17: 29.514917 | K17: 36.974732 | L17: 26.59586 | M17: 22.703783 | N17: 28.541898 | O17: 12.97359 | P17: 12.97359 | Q17: 15.568308
C18: BET | D18: 8.828151 | E18: 13.407945 | F18: 24.893202 | G18: 8.9650097 | H18: 13.233576 | I18: 9.6477253 | J18: 21.596309 | K18: 28.854898 | L18: 24.802777 | M18: 21.473333 | N18: 27.599158 | O18: 11.313097 | P18: 11.326674 | Q18: 14.661499
C19: H2 FCET | D19: 9.2677762 | E19: 13.436826 | F19: 25.171868 | G19: 9.4264178 | H19: 13.311372 | I19: 10.062993 | J19: 22.248242 | K19: 29.241666 | L19: 25.147136 | M19: 22.078279 | N19: 28.074434 | O19: 11.884533 | P19: 11.610816 | Q19: 15.349318
A20: 5 | B20: Adblue Consumption/ litre of Diesel Consumed | D20: 0.05
A21: 6 | B21: Battery Life (full charging cycles) | D21: 3000
B22: Fuel Cell Life (hrs. of operation) | D22: 25000
A23: 7 | B23: Battery Energy Density (kg./kWh) | D23: 8 | E23: Used for calculation of Payload reduction
B24: Fuel Cell Power Density (kg./kW) | D24: 4
A25: 8 | B25: Funding | C25: Interest Rate | D25: 0.12
C26: Tenure (years) | D26: 7
A27: 9 | B27: Insurance Rate (% of Vehicle Price) | D27: 0.02
A28: 10 | B28: CNG Cylinders in Vehicle | C28: Capacity (ltrs.) | D28: 480 | E28: 960
C29: CNG Density (kg./ltr.) | D29: 0.2
C30: Capacity (kgs.) | D30: =D28*D29 -> 96 | E30: =E28*D29 -> 192
C31: Cost (Rs.) | D31: 150000 | E31: 250000
A32: 11 | B32: LNG Cylinders in Vehicle | C32: Capacity (ltrs.) | D32: 450 | E32: 990
C33: LNG Density (kg./ltr.) | D33: 0.35
C34: Capacity (kgs.) | D34: =D32*D33 -> 157.5 | E34: =E32*D33 -> 346.5
A35: 12 | B35: H2 Cylinders in Vehicle (350 bar pressure) | C35: Capacity (ltrs.) | D35: 1200 | E35: 2400
C36: H2 Density (kg./cu.M) | D36: 23.5
C37: Capacity (kgs.) | D37: =D35*D36/1000 -> 28.2 | E37: =E35*D36/1000 -> 56.4
D38: Diesel | E38: CNG | F38: LNG | G38: BET | H38: H2 ICE | I38: H2 FCET
A39: 13 | B39: TAT / gradeability / Productivity | C39: Relative Weightage | D39: 1 | E39: 0.95 | F39: 0.95 | G39: 1.15 | H39: 0.95 | I39: 1.15
A40: 14 | B40: Range & filling time | D40: 1 | E40: 1.05 | F40: 1.1 | G40: 1.2 | H40: 1 | I40: 1
A41: 15 | B41: Product & Eco-system Readiness (Year) | C41: Model | D41: Product Pilot | J41: Start of Supply (All Geography) | P41: Maturity (Products & Eco-system) | V41: Inflection Point (10% share)
D42: Diesel | E42: CNG | F42: LNG | G42: BET | H42: H2 ICE | I42: H2 FCET | J42: Diesel | K42: CNG | L42: LNG | M42: BET | N42: H2 ICE | O42: H2 FCET | P42: Diesel | Q42: CNG | R42: LNG | S42: BET | T42: H2 ICE | U42: H2 FCET | V42: BET | W42: H2 ICE | X42: H2 FCET
C43: 15T Rigid | D43: 2025 | E43: 2025 | F43: 2027 | G43: 2026 | H43: 2028 | I43: 2030 | J43: 2025 | K43: 2027 | M43: 2027 | N43: 2036 | O43: 2040 | P43: 2025 | Q43: 2030 | R43: 2033 | S43: 2035 | T43: 2042 | U43: 2045 | V43: 2038 | W43: 2050 | X43: 2050
C44: 19T Rigid | H44: 2027 | I44: 2028 | K44: 2027 | M44: 2027
C45: 28T Rigid | H45: 2028 | I45: 2029 | K45: 2027 | M45: 2028
C46: 35T Rigid | H46: 2028 | I46: 2029 | K46: 2028 | M46: 2028
C47: 48T Rigid | H47: 2028 | I47: 2029 | K47: 2028 | M47: 2028
C48: 28T Tipper | H48: 2028 | I48: 2029 | K48: 2027 | M48: 2028
C49: 35T Tipper | H49: 2028 | I49: 2029 | K49: 2028 | M49: 2028
C50: 40T Tractor | H50: 2028 | I50: 2029 | L50: 2028 | M50: 2028
C51: 55T Tractor | H51: 2027 | I51: 2029 | L51: 2028 | M51: 2027

Sheet Parameters Varying
A2: Sl. No. | B2: Parameter | D2: Base Value 2025 | E2: Value 2055 | F2: Trend | L2: CAGR | M2: Remarks
F3: 2026-30 | G3: 2031-35 | H3: 2036-40 | I3: 2041-45 | J3: 2046-56 | K3: 2050-55
A4: 1 | B4: Diesel Price per litre | D4: ='Changing with year'!C3 -> 88.926296 | E4: ='Changing with year'!AG3 -> 175.80862 | F4: (Annual values as per WRI Estimates) | L4: =_xlfn.RRI(30,D4,E4) -> 0.022979661
A5: 2 | B5: Adblue Price | D5: ='Changing with year'!C4 -> 55 | E5: ='Changing with year'!AG4 -> 115.36622 | F5: ='Changing with year'!AH4 -> 0.025 | G5: ='Changing with year'!AI4 -> 0.025 | H5: ='Changing with year'!AI4 -> 0.025 | I5: ='Changing with year'!AJ4 -> 0.025 | J5: ='Changing with year'!AJ4 -> 0.025 | K5: ='Changing with year'!AK4 -> 0.025
A6: 3 | B6: CNG Price per kg | D6: ='Changing with year'!C5 -> 87 | E6: ='Changing with year'!AG5 -> 215.62574 | F6: ='Changing with year'!AH5 -> 0.03 | G6: ='Changing with year'!AI5 -> 0.03 | H6: ='Changing with year'!AI5 -> 0.03 | I6: ='Changing with year'!AJ5 -> 0.03 | J6: ='Changing with year'!AJ5 -> 0.03 | K6: ='Changing with year'!AK5 -> 0.03
A7: 4 | B7: LNG Price per kg | D7: ='Changing with year'!C6 -> 83 | E7: ='Changing with year'!AG6 -> 202.66463 | F7: ='Changing with year'!AH6 -> 0.03 | G7: ='Changing with year'!AI6 -> 0.03 | H7: ='Changing with year'!AI6 -> 0.03 | I7: ='Changing with year'!AJ6 -> 0.03 | J7: ='Changing with year'!AJ6 -> 0.03 | K7: ='Changing with year'!AK6 -> 0.03
A8: 5 | B8: Electricity incl CAAS (Rs./kWh) | C8: Electricity incl DC | D8: ='Changing with year'!#REF! -> #REF! | E8: ='Changing with year'!#REF! -> #REF! | F8: ='Changing with year'!#REF! -> #REF! | G8: ='Changing with year'!#REF! -> #REF! | H8: ='Changing with year'!#REF! -> #REF! | I8: ='Changing with year'!#REF! -> #REF! | J8: ='Changing with year'!#REF! -> #REF! | K8: ='Changing with year'!#REF! -> #REF! | L8: =_xlfn.RRI(30,D8,E8) -> #REF!
C9: Real Estate | D9: ='Changing with year'!#REF! -> #REF! | E9: ='Changing with year'!#REF! -> #REF! | F9: ='Changing with year'!#REF! -> #REF! | G9: ='Changing with year'!#REF! -> #REF! | H9: ='Changing with year'!#REF! -> #REF! | I9: ='Changing with year'!#REF! -> #REF! | J9: ='Changing with year'!#REF! -> #REF! | K9: ='Changing with year'!#REF! -> #REF! | L9: =_xlfn.RRI(30,D9,E9) -> #REF!
C10: Charging Infra | D10: ='Changing with year'!#REF! -> #REF! | E10: ='Changing with year'!#REF! -> #REF! | F10: ='Changing with year'!#REF! -> #REF! | G10: ='Changing with year'!#REF! -> #REF! | H10: ='Changing with year'!#REF! -> #REF! | I10: ='Changing with year'!#REF! -> #REF! | J10: ='Changing with year'!#REF! -> #REF! | K10: ='Changing with year'!#REF! -> #REF! | L10: =_xlfn.RRI(30,D10,E10) -> #REF!
C11: Total | D11: ='Changing with year'!C18 -> 11.929848 | E11: ='Changing with year'!AG18 -> 10.603822 | L11: =_xlfn.RRI(30,D11,E11) -> -0.0039199295
A12: 6 | B12: Green H2 Prodn cost/kg | C12: Energy Cost | D12: ='Changing with year'!#REF! -> #REF! | E12: ='Changing with year'!#REF! -> #REF! | F12: ='Changing with year'!#REF! -> #REF! | G12: ='Changing with year'!#REF! -> #REF! | H12: ='Changing with year'!#REF! -> #REF! | I12: ='Changing with year'!#REF! -> #REF! | J12: ='Changing with year'!#REF! -> #REF! | K12: ='Changing with year'!#REF! -> #REF! | L12: =_xlfn.RRI(30,D12,E12) -> #REF!
C13: Capex (USD1.25) | D13: ='Changing with year'!C9 -> 115 | E13: ='Changing with year'!AG9 -> 30.417458 | F13: ='Changing with year'!AH9 -> -0.03 | G13: ='Changing with year'!AI9 -> -0.04 | H13: ='Changing with year'!AI9 -> -0.04 | I13: ='Changing with year'!AJ9 -> -0.05 | J13: ='Changing with year'!AJ9 -> -0.05 | K13: ='Changing with year'!AK9 -> -0.05 | L13: =_xlfn.RRI(30,D13,E13) -> -0.043362276
C14: Opex & Margin | D14: ='Changing with year'!C10 -> 140 | E14: ='Changing with year'!AG10 -> 33.348541 | F14: ='Changing with year'!AH10 -> -0.03 | G14: ='Changing with year'!AI10 -> -0.05 | H14: ='Changing with year'!AI10 -> -0.05 | I14: ='Changing with year'!AJ10 -> -0.05 | J14: ='Changing with year'!AJ10 -> -0.05 | K14: ='Changing with year'!AK10 -> -0.05 | L14: =_xlfn.RRI(30,D14,E14) -> -0.046695536
C15: Total | D15: ='Changing with year'!C11 -> 546.5 | E15: ='Changing with year'!AG11 -> 270.53188 | F15: ='Changing with year'!AH11 -> 0 | G15: ='Changing with year'!AI11 -> 0 | H15: ='Changing with year'!AI11 -> 0 | I15: ='Changing with year'!AJ11 -> 0 | J15: ='Changing with year'!AJ11 -> 0 | K15: ='Changing with year'!AK11 -> 0 | L15: =_xlfn.RRI(30,D15,E15) -> -0.023165606
A16: 7 | B16: Grey H2 Prodn Cost/kg | D16: ='Changing with year'!C12 -> 250 | E16: ='Changing with year'!AG12 -> 452.8404 | F16: ='Changing with year'!AH12 -> 0.02 | G16: ='Changing with year'!AI12 -> 0.02 | H16: ='Changing with year'!AI12 -> 0.02 | I16: ='Changing with year'!AJ12 -> 0.02 | J16: ='Changing with year'!AJ12 -> 0.02 | K16: ='Changing with year'!AK12 -> 0.02
A17: 8 | B17: H2 Compression, storage & transmission cost/kg | D17: ='Changing with year'!C14 -> 175 | E17: ='Changing with year'!AG14 -> 70.138953 | F17: ='Changing with year'!AH14 -> -0.04 | G17: ='Changing with year'!AI14 -> -0.03 | H17: ='Changing with year'!AI14 -> -0.03 | I17: ='Changing with year'!AJ14 -> -0.03 | J17: ='Changing with year'!AJ14 -> -0.03 | K17: ='Changing with year'!AK14 -> -0.02 | L17: =_xlfn.RRI(30,D17,E17) -> -0.030017183
A18: 9 | B18: Battery cost per kwh | D18: ='Changing with year'!C19 -> 9900 | E18: ='Changing with year'!AG19 -> 6773.6276 | F18: ='Changing with year'!AH19 -> -0.015 | G18: ='Changing with year'!AI19 -> -0.025 | H18: ='Changing with year'!AI19 -> -0.025 | I18: ='Changing with year'!AJ19 -> -0.01 | J18: ='Changing with year'!AJ19 -> -0.01 | K18: ='Changing with year'!AK19 -> 0.01 | L18: =_xlfn.RRI(30,D18,E18) -> -0.012570258
A19: 10 | B19: Fuel Cell cost per kW | D19: ='Changing with year'!C20 -> 36000 | E19: ='Changing with year'!AG20 -> 19577 | F19: ='Changing with year'!AH20 -> -0.03 | G19: ='Changing with year'!AI20 -> -0.03 | H19: ='Changing with year'!AI20 -> -0.03 | I19: ='Changing with year'!AJ20 -> -0.02 | J19: ='Changing with year'!AJ20 -> -0.02 | K19: ='Changing with year'!AK20 -> 0.01 | L19: =_xlfn.RRI(30,D19,E19) -> -0.020100684
A20: 11 | B20: LNG Tank cost/kg of LNG | D20: ='Changing with year'!C21 -> 3050 | E20: ='Changing with year'!AG21 -> 4110.9392 | F20: ='Changing with year'!AH21 -> 0.01 | G20: ='Changing with year'!AI21 -> 0.01 | H20: ='Changing with year'!AI21 -> 0.01 | I20: ='Changing with year'!AJ21 -> 0.01 | J20: ='Changing with year'!AJ21 -> 0.01 | K20: ='Changing with year'!AK21 -> 0.01
A21: 12 | B21: LNG Valves & Piping cost/vehicle | D21: ='Changing with year'!C22 -> 100000 | E21: ='Changing with year'!AG22 -> 134784.89 | F21: ='Changing with year'!AH22 -> 0.01 | G21: ='Changing with year'!AI22 -> 0.01 | H21: ='Changing with year'!AI22 -> 0.01 | I21: ='Changing with year'!AJ22 -> 0.01 | J21: ='Changing with year'!AJ22 -> 0.01 | K21: ='Changing with year'!AK22 -> 0.01
A22: 13 | B22: H2 Tank cost/kg of H2 | D22: ='Changing with year'!C23 -> 56000 | E22: ='Changing with year'!AG23 -> 33445.6 | F22: ='Changing with year'!AH23 -> -0.05 | G22: ='Changing with year'!AI23 -> -0.04 | H22: ='Changing with year'!AI23 -> -0.04 | I22: ='Changing with year'!AJ23 -> 0.01 | J22: ='Changing with year'!AJ23 -> 0.01 | K22: ='Changing with year'!AK23 -> 0.01 | L22: =_xlfn.RRI(30,D22,E22) -> -0.017034296
A23: 14 | B23: Cost of Engine & Transmission (Diesel) | C23: 15T Rigid | D23: ='Changing with year'!C26 -> 525000 | E23: ='Changing with year'!AG26 -> 950964.83 | F23: ='Changing with year'!AH26 -> 0.02 | G23: ='Changing with year'!AI26 -> 0.02 | H23: ='Changing with year'!AI26 -> 0.02 | I23: ='Changing with year'!AJ26 -> 0.02 | J23: ='Changing with year'!AJ26 -> 0.02 | K23: ='Changing with year'!AK26 -> 0.02 | M23: Other Model costs in hidden rows
C24: 19T Rigid | D24: ='Changing with year'!C27 -> 625000 | E24: ='Changing with year'!AG27 -> 1132101 | F24: ='Changing with year'!AH27 -> 0.02 | G24: ='Changing with year'!AI27 -> 0.02 | H24: ='Changing with year'!AI27 -> 0.02 | I24: ='Changing with year'!AJ27 -> 0.02 | J24: ='Changing with year'!AJ27 -> 0.02 | K24: ='Changing with year'!AK27 -> 0.02
C25: 28T/35T Rigid | D25: ='Changing with year'!C28 -> 650000 | E25: ='Changing with year'!AG28 -> 1177385 | F25: ='Changing with year'!AH28 -> 0.02 | G25: ='Changing with year'!AI28 -> 0.02 | H25: ='Changing with year'!AI28 -> 0.02 | I25: ='Changing with year'!AJ28 -> 0.02 | J25: ='Changing with year'!AJ28 -> 0.02 | K25: ='Changing with year'!AK28 -> 0.02
C26: 48T Rigid | D26: ='Changing with year'!C30 -> 750000 | E26: ='Changing with year'!AG30 -> 1358521.2 | F26: ='Changing with year'!AH30 -> 0.02 | G26: ='Changing with year'!AI30 -> 0.02 | H26: ='Changing with year'!AI30 -> 0.02 | I26: ='Changing with year'!AJ30 -> 0.02 | J26: ='Changing with year'!AJ30 -> 0.02 | K26: ='Changing with year'!AK30 -> 0.02
C27: 28T Tipper | D27: ='Changing with year'!C31 -> 650000 | E27: ='Changing with year'!AG31 -> 1177385 | F27: ='Changing with year'!AH31 -> 0.02 | G27: ='Changing with year'!AI31 -> 0.02 | H27: ='Changing with year'!AI31 -> 0.02 | I27: ='Changing with year'!AJ31 -> 0.02 | J27: ='Changing with year'!AJ31 -> 0.02 | K27: ='Changing with year'!AK31 -> 0.02
C28: 35T Tipper | D28: ='Changing with year'!C32 -> 750000 | E28: ='Changing with year'!AG32 -> 1358521.2 | F28: ='Changing with year'!AH32 -> 0.02 | G28: ='Changing with year'!AI32 -> 0.02 | H28: ='Changing with year'!AI32 -> 0.02 | I28: ='Changing with year'!AJ32 -> 0.02 | J28: ='Changing with year'!AJ32 -> 0.02 | K28: ='Changing with year'!AK32 -> 0.02
C29: 40T Tractor | D29: ='Changing with year'!C33 -> 650000 | E29: ='Changing with year'!AG33 -> 1177385 | F29: ='Changing with year'!AH33 -> 0.02 | G29: ='Changing with year'!AI33 -> 0.02 | H29: ='Changing with year'!AI33 -> 0.02 | I29: ='Changing with year'!AJ33 -> 0.02 | J29: ='Changing with year'!AJ33 -> 0.02 | K29: ='Changing with year'!AK33 -> 0.02
C30: 55T Tractor | D30: ='Changing with year'!C34 -> 750000 | E30: ='Changing with year'!AG34 -> 1358521.2 | F30: ='Changing with year'!AH34 -> 0.02 | G30: ='Changing with year'!AI34 -> 0.02 | H30: ='Changing with year'!AI34 -> 0.02 | I30: ='Changing with year'!AJ34 -> 0.02 | J30: ='Changing with year'!AJ34 -> 0.02 | K30: ='Changing with year'!AK34 -> 0.02
A31: 15 | B31: Cost of e-Powertrain | C31: 15T/19T/28T Rigid & 40T TT | D31: ='Changing with year'!C37 -> 1400000 | E31: ='Changing with year'!AG37 -> 1198551.6 | F31: ='Changing with year'!AH37 -> -0.04 | G31: ='Changing with year'!AI37 -> -0.01 | H31: ='Changing with year'!AI37 -> -0.01 | I31: ='Changing with year'!AJ37 -> 0.01 | J31: ='Changing with year'!AJ37 -> 0.01 | K31: ='[1]Changing with year'!AK30 -> 0.01 | L31: =_xlfn.RRI(30,D31,E31) -> -0.0051652264
C32: 35T/48T Rigid, 28T/35T Tip & 55T TT | D32: ='Changing with year'!C40 -> 1700000 | E32: ='Changing with year'!AG40 -> 1455384.1 | F32: ='Changing with year'!AH40 -> -0.04 | G32: ='Changing with year'!AI40 -> -0.01 | H32: ='Changing with year'!AI40 -> -0.01 | I32: ='Changing with year'!AJ40 -> 0.01 | J32: ='Changing with year'!AJ40 -> 0.01 | K32: ='[1]Changing with year'!AK33 -> 0.01 | L32: =_xlfn.RRI(30,D32,E32) -> -0.0051652264
A33: 16 | B33: Diesel Vehicle Cost (Acquistion Cost incl. body/trailer, permit, registration, etc.) | C33: 15T Rigid | D33: ='Changing with year'!C81 -> 2000000 | E33: ='Changing with year'!AG81 -> 5692200 | F33: ='Changing with year'!AH81 -> 0.03 | G33: ='Changing with year'!AI81 -> 0.03 | H33: ='Changing with year'!AI81 -> 0.03 | I33: ='Changing with year'!AJ81 -> 0.03 | J33: ='Changing with year'!AJ81 -> 0.03 | K33: ='Changing with year'!AK81 -> 0.03 | M33: Other Model costs in hidden rows
C34: 19T Rigid | D34: ='Changing with year'!C82 -> 2750000 | E34: ='Changing with year'!AG82 -> 7513000 | F34: ='Changing with year'!AH82 -> 0.03 | G34: ='Changing with year'!AI82 -> 0.03 | H34: ='Changing with year'!AI82 -> 0.03 | I34: ='Changing with year'!AJ82 -> 0.03 | J34: ='Changing with year'!AJ82 -> 0.03 | K34: ='Changing with year'!AK82 -> 0.03
C35: 28T Rigid | D35: ='Changing with year'!C83 -> 3600000 | E35: ='Changing with year'!AG83 -> 9575700 | F35: ='Changing with year'!AH83 -> 0.03 | G35: ='Changing with year'!AI83 -> 0.03 | H35: ='Changing with year'!AI83 -> 0.03 | I35: ='Changing with year'!AJ83 -> 0.03 | J35: ='Changing with year'!AJ83 -> 0.03 | K35: ='Changing with year'!AK83 -> 0.03
C36: 35T Rigid | D36: ='Changing with year'!C84 -> 4000000 | E36: ='Changing with year'!AG84 -> 10546400 | F36: ='Changing with year'!AH84 -> 0.03 | G36: ='Changing with year'!AI84 -> 0.03 | H36: ='Changing with year'!AI84 -> 0.03 | I36: ='Changing with year'!AJ84 -> 0.03 | J36: ='Changing with year'!AJ84 -> 0.03 | K36: ='Changing with year'!AK84 -> 0.03
C37: 48T Rigid | D37: ='Changing with year'!C85 -> 4700000 | E37: ='Changing with year'!AG85 -> 12245900 | F37: ='Changing with year'!AH85 -> 0.03 | G37: ='Changing with year'!AI85 -> 0.03 | H37: ='Changing with year'!AI85 -> 0.03 | I37: ='Changing with year'!AJ85 -> 0.03 | J37: ='Changing with year'!AJ85 -> 0.03 | K37: ='Changing with year'!AK85 -> 0.03
C38: 28T Tipper | D38: ='Changing with year'!C86 -> 4200000 | E38: ='Changing with year'!AG86 -> 11032100 | F38: ='Changing with year'!AH86 -> 0.03 | G38: ='Changing with year'!AI86 -> 0.03 | H38: ='Changing with year'!AI86 -> 0.03 | I38: ='Changing with year'!AJ86 -> 0.03 | J38: ='Changing with year'!AJ86 -> 0.03 | K38: ='Changing with year'!AK86 -> 0.03
C39: 35T Tipper | D39: ='Changing with year'!C87 -> 4800000 | E39: ='Changing with year'!AG87 -> 12488800 | F39: ='Changing with year'!AH87 -> 0.03 | G39: ='Changing with year'!AI87 -> 0.03 | H39: ='Changing with year'!AI87 -> 0.03 | I39: ='Changing with year'!AJ87 -> 0.03 | J39: ='Changing with year'!AJ87 -> 0.03 | K39: ='Changing with year'!AK87 -> 0.03
C40: 40T Tractor | D40: ='Changing with year'!C88 -> 4300000 | E40: ='Changing with year'!AG88 -> 11274800 | F40: ='Changing with year'!AH88 -> 0.03 | G40: ='Changing with year'!AI88 -> 0.03 | H40: ='Changing with year'!AI88 -> 0.03 | I40: ='Changing with year'!AJ88 -> 0.03 | J40: ='Changing with year'!AJ88 -> 0.03 | K40: ='Changing with year'!AK88 -> 0.03
C41: 55T Tractor | D41: ='Changing with year'!C89 -> 5000000 | E41: ='Changing with year'!AG89 -> 12973700 | F41: ='Changing with year'!AH89 -> 0.03 | G41: ='Changing with year'!AI89 -> 0.03 | H41: ='Changing with year'!AI89 -> 0.03 | I41: ='Changing with year'!AJ89 -> 0.03 | J41: ='Changing with year'!AJ89 -> 0.03 | K41: ='Changing with year'!AK89 -> 0.03
A42: 17 | B42: CNG Vehicle Cost (Rs.) | C42: 28T Rigid | D42: ='Changing with year'!C94 -> 3850000 | E42: ='Changing with year'!AG94 -> 10182472 | F42: ='Changing with year'!AH94 -> 0.03 | G42: ='Changing with year'!AI94 -> 0.03 | H42: ='Changing with year'!AI94 -> 0.03 | I42: ='Changing with year'!AJ94 -> 0.03 | J42: ='Changing with year'!AJ94 -> 0.03 | K42: ='Changing with year'!AK94 -> 0.03 | M42: Diesel Vehicle Cost + CNG Cylinders Cost in 2025
A43: 18 | B43: LNG Vehicle Cost (Rs.) | C43: 55T Tractor | D43: ='Changing with year'!C113 -> 6156825 | E43: ='Changing with year'!AG113 -> 14532925 | F43: Diesel Truck Cost + LNG Cyl Cost + LNG System Cost
A44: 19 | B44: H2 ICE Vehicle Cost (Rs.) | C44: 28T Rigid | D44: ='Changing with year'!C119 -> 5179200 | E44: ='Changing with year'!AG119 -> 10518866 | F44: Diesel Truck Cost + H2 ICE Cylinder & System Cost
A45: 20 | B45: BET Mfg. Cost (% of Battery Cost) | C45: All Models | D45: 50% to 35% Manual entry | G45: ='Changing with year'!I128 -> 0.3 | H45: ='Changing with year'!N128 -> 0.3 | I45: ='Changing with year'!S128 -> 0.25 | J45: ='Changing with year'!X128 -> 0.25 | K45: ='Changing with year'!AC128 -> 0.25 | M45: As per our discussion during review
A46: 21 | B46: BET Cost (Rs.) | C46: 28T Rigid | D46: ='Changing with year'!C131 -> 8762500 | E46: ='Changing with year'!AG131 -> 11807263 | F46: Cost of (Diesel Truck - Eng. & Transmsn + ePowertrain) + Battery) + BET Mfg. Cost
A47: 22 | B47: FCET Mfg. Cost (% of Battery+FC Cost) | D47: ='Changing with year'!C141 -> 0.4 | F47: ='Changing with year'!D141 -> 0.4 | G47: ='Changing with year'!I141 -> 0.4 | H47: ='Changing with year'!N141 -> 0.4 | I47: ='Changing with year'!S141 -> 0.35 | J47: ='Changing with year'!X141 -> 0.3 | K47: ='Changing with year'!AC141 -> 0.25
A48: 23 | B48: FCET Cost (Rs.) | C48: 28T Rigid | D48: ='[1]Changing with year'!C137 -> 11491400 | E48: ='Changing with year'!AG144 -> 13184063 | F48: Cost of (Diesel Truck - Eng. & Transmsn + ePowertrain) + Battery + FC) + FCET Mfg. Cost
A49: 24 | B49: Maint. Cost - Diesel (Rs./km) | C49: 28T Mkt Load | D49: ='Changing with year'!C154 -> 4.2 | E49: ='Changing with year'!AG154 -> 13.62227 | F49: ='Changing with year'!AH154 -> 0.04 | G49: ='Changing with year'!AI154 -> 0.04 | H49: ='[1]Changing with year'!AI147 -> 0.04 | I49: ='[1]Changing with year'!AJ147 -> 0.04 | J49: ='[1]Changing with year'!AJ147 -> 0.04 | K49: ='[1]Changing with year'!AK147 -> 0.04
A50: 25 | B50: Maint. Cost - CNG, LNG & H2 ICE (Rs./km) | C50: 28T Mkt Load | D50: ='Changing with year'!C186 -> 4.7 | E50: ='Changing with year'!AG186 -> 15.243968 | F50: ='Changing with year'!AH186 -> 0.04 | G50: ='[1]Changing with year'!AI163 -> 0.04 | H50: ='[1]Changing with year'!AI163 -> 0.04 | I50: ='[1]Changing with year'!AJ163 -> 0.04 | J50: ='[1]Changing with year'!AJ163 -> 0.04 | K50: ='[1]Changing with year'!AK163 -> 0.04
A51: 26 | B51: Maint. Cost - BET incl Bat. Repl. (Rs./km) | C51: 28T Mkt Load | D51: ='Changing with year'!C218 -> 7.1777952 | E51: ='Changing with year'!AG218 -> 13.407945 | F51: ='Changing with year'!AH218 -> 0 | G51: ='[1]Changing with year'!AI179 -> 0.01 | H51: ='[1]Changing with year'!AI179 -> 0.01 | I51: ='[1]Changing with year'!AJ179 -> 0.025 | J51: ='[1]Changing with year'!AJ179 -> 0.025 | K51: ='[1]Changing with year'!AK173 -> 0.04 | L51: =_xlfn.RRI(30,D51,E51) -> 0.021046934
A52: 27 | B52: Maint. Cost - FCET incl Bat & FC Repl. (Rs./km) | C52: 28T Mkt Load | D52: ='Changing with year'!C218 -> 7.1777952 | E52: ='Changing with year'!AG218 -> 13.407945 | F52: ='Changing with year'!AH218 -> 0 | G52: ='[1]Changing with year'!AI195 -> -0.005 | H52: ='[1]Changing with year'!AI195 -> -0.005 | I52: ='[1]Changing with year'!AJ195 -> 0.02 | J52: ='[1]Changing with year'!AJ195 -> 0.02 | K52: ='[1]Changing with year'!AK195 -> 0.03 | L52: =_xlfn.RRI(30,D52,E52) -> 0.021046934
A53: 28 | B53: Toll Charges (Rs./km) | C53: 28T Rigid | D53: ='Changing with year'!C235 -> 5.2182857 | E53: ='Changing with year'!AG235 -> 3.5708409 | F53: ='Changing with year'!AH235 -> -0.025 | G53: ='[1]Changing with year'!AI212 -> 0.01 | H53: ='[1]Changing with year'!AI212 -> 0.01 | I53: ='[1]Changing with year'!AJ212 -> 0.01 | J53: ='[1]Changing with year'!AJ212 -> 0.01 | K53: ='[1]Changing with year'!AK212 -> 0.01
A54: 29 | B54: Manpower Cost ICE Trucks (Rs./annum) | C54: 28T Rigid | D54: ='Changing with year'!C257 -> 11.842143 | E54: ='Changing with year'!AG257 -> 25.147136 | F54: ='[1]Changing with year'!AH234 -> 0.045 | G54: ='[1]Changing with year'!AI234 -> 0.045 | H54: ='[1]Changing with year'!AI234 -> 0.045 | I54: ='[1]Changing with year'!AJ234 -> 0.045 | J54: ='[1]Changing with year'!AJ234 -> 0.045 | K54: ='[1]Changing with year'!AK234 -> 0.045
A55: 30 | B55: Manpower Cost BETs & FCETs (Rs./annum) | C55: 28T Rigid | D55: ='Changing with year'!C268 -> 8.5 | E55: ='Changing with year'!AG268 -> 11.456716 | F55: ='[1]Changing with year'!AH245 -> 0.045 | G55: ='[1]Changing with year'!AI245 -> 0.045 | H55: ='[1]Changing with year'!AI245 -> 0.045 | I55: ='[1]Changing with year'!AJ245 -> 0.045 | J55: ='[1]Changing with year'!AJ245 -> 0.045 | K55: ='[1]Changing with year'!AK245 -> 0.045
B57: TCO 19T Market Load (H2 Cost in 2055 - 220/70) | C57: Diesel | D57: ='B1 - TCO ML 19T'!C165 -> 33.521745 | E57: ='B1 - TCO ML 19T'!AG165 -> 78.262657
C58: CNG | D58: ='B1 - TCO ML 19T'!C166 -> 33.072847 | E58: ='B1 - TCO ML 19T'!AG166 -> 86.495082
C59: LNG | D59: ='B1 - TCO ML 19T'!C167 -> 33.134497 | E59: ='B1 - TCO ML 19T'!AG167 -> 85.122288
C60: BET | D60: ='B1 - TCO ML 19T'!C168 -> 40.041671 | E60: ='B1 - TCO ML 19T'!AG168 -> 57.817388 | F60: 2037 | G60: 2043
C61: H2-ICE | D61: ='B1 - TCO ML 19T'!C169 -> 66.706792 | E61: ='B1 - TCO ML 19T'!AG169 -> 67.895607
C62: FCET | D62: ='B1 - TCO ML 19T'!C170 -> 72.215837 | E62: ='B1 - TCO ML 19T'!AG170 -> 69.073503
C63: Diesel - 10% | D63: ='B1 - TCO ML 19T'!C171 -> 30.169571 | E63: ='B1 - TCO ML 19T'!AG171 -> 70.436391
B65: TCO 48T Market Load (H2 Cost in 2055 - 220/70) | C65: Diesel | D65: ='B3 - TCO ML 48T '!C165 -> 61.165655 | E65: ='B3 - TCO ML 48T '!AG165 -> 142.78594
C66: CNG | D66: ='B3 - TCO ML 48T '!C166 -> 58.833206 | E66: ='B3 - TCO ML 48T '!AG166 -> 153.30302
C67: LNG | D67: ='B3 - TCO ML 48T '!C167 -> 58.969566 | E67: ='B3 - TCO ML 48T '!AG167 -> 151.63268
C68: BET | D68: ='B3 - TCO ML 48T '!C168 -> 66.26642 | E68: ='B3 - TCO ML 48T '!AG168 -> 101.27897 | F68: 2034 | G68: 2038
C69: H2-ICE | D69: ='B3 - TCO ML 48T '!C169 -> 117.92752 | E69: ='B3 - TCO ML 48T '!AG169 -> 121.79401
C70: FCET | D70: ='B3 - TCO ML 48T '!C170 -> 121.54817 | E70: ='B3 - TCO ML 48T '!AG170 -> 121.65824
C71: Diesel - 10% | D71: ='B3 - TCO ML 48T '!C171 -> 55.04909 | E71: ='B3 - TCO ML 48T '!AG171 -> 128.50735
B73: TCO 28T Parcel Load (H2 Cost in 2055 - 220/70) | C73: Diesel | D73: ='B5 - TCO PL&FMCG 28T '!C165 -> 41.09072 | E73: ='B5 - TCO PL&FMCG 28T '!AG165 -> 95.740371
C74: CNG | D74: ='B5 - TCO PL&FMCG 28T '!C166 -> 39.969475 | E74: ='B5 - TCO PL&FMCG 28T '!AG166 -> 103.66877
C75: LNG | D75: ='B5 - TCO PL&FMCG 28T '!C167 -> 40.206321 | E75: ='B5 - TCO PL&FMCG 28T '!AG167 -> 102.65036
C76: BET | D76: ='B5 - TCO PL&FMCG 28T '!C168 -> 49.44802 | E76: ='B5 - TCO PL&FMCG 28T '!AG168 -> 72.442334 | F76: 2038 | G76: 2044
C77: H2-ICE | D77: ='B5 - TCO PL&FMCG 28T '!C169 -> 79.06506 | E77: ='B5 - TCO PL&FMCG 28T '!AG169 -> 83.202618
C78: FCET | D78: ='B5 - TCO PL&FMCG 28T '!C170 -> 82.763933 | E78: ='B5 - TCO PL&FMCG 28T '!AG170 -> 83.315987
C79: Diesel - 10% | D79: ='B5 - TCO PL&FMCG 28T '!C171 -> 36.981648 | E79: ='B5 - TCO PL&FMCG 28T '!AG171 -> 86.166334
B81: TCO 15T Perishables (H2 Cost in 2055 - 220/70) | C81: Diesel | D81: ='B6 Perishables 15T'!C165 -> 29.688488 | E81: ='B6 Perishables 15T'!AG165 -> 68.998421
C82: CNG | D82: ='B6 Perishables 15T'!C166 -> 29.047288 | E82: ='B6 Perishables 15T'!AG166 -> 75.517629
C83: LNG | D83: ='B6 Perishables 15T'!C167 -> 29.334585 | E83: ='B6 Perishables 15T'!AG167 -> 74.928355
C84: BET | D84: ='B6 Perishables 15T'!C168 -> 35.955395 | E84: ='B6 Perishables 15T'!AG168 -> 51.913906 | F84: 2038 | G84: 2044
C85: H2-ICE | D85: ='B6 Perishables 15T'!C169 -> 58.383175 | E85: ='B6 Perishables 15T'!AG169 -> 60.374349
C86: FCET | D86: ='B6 Perishables 15T'!C170 -> 63.766813 | E86: ='B6 Perishables 15T'!AG170 -> 61.374332
C87: Diesel - 10% | D87: ='B6 Perishables 15T'!C171 -> 26.719639 | E87: ='B6 Perishables 15T'!AG171 -> 62.098578
B89: TCO 28Tipper Const. & Mining (H2 Cost in 2055 - 220/70) | C89: Diesel | D89: ='B7 C&M 28Tip'!C165 -> 61.604723 | E89: ='B7 C&M 28Tip'!AG165 -> 148.62267
C90: CNG | D90: ='B7 C&M 28Tip'!C166 -> 60.93252 | E90: ='B7 C&M 28Tip'!AG166 -> 162.45191
C91: LNG | D91: ='B7 C&M 28Tip'!C167 -> 61.463428 | E91: ='B7 C&M 28Tip'!AG167 -> 158.13179
C92: BET | D92: ='B7 C&M 28Tip'!C168 -> 76.014743 | E92: ='B7 C&M 28Tip'!AG168 -> 118.28965 | F92: 2038 | G92: 2045
C93: H2-ICE | D93: ='B7 C&M 28Tip'!C169 -> 107.72319 | E93: ='B7 C&M 28Tip'!AG169 -> 134.02575
C94: FCET | D94: ='B7 C&M 28Tip'!C170 -> 119.28232 | E94: ='B7 C&M 28Tip'!AG170 -> 133.32747
C95: Diesel - 10% | D95: ='B7 C&M 28Tip'!C171 -> 55.444251 | E95: ='B7 C&M 28Tip'!AG171 -> 133.7604
B97: TCO 55T TT Cement (H2 Cost in 2055 - 220/70) | C97: Diesel | D97: ='B10 Cement 55 Tractor '!C165 -> 64.079057 | E97: ='B10 Cement 55 Tractor '!AG165 -> 147.44099
C98: CNG | D98: ='B10 Cement 55 Tractor '!C166 -> 61.125763 | E98: ='B10 Cement 55 Tractor '!AG166 -> 158.23574
C99: LNG | D99: ='B10 Cement 55 Tractor '!C167 -> 62.26334 | E99: ='B10 Cement 55 Tractor '!AG167 -> 158.08116
C100: BET | D100: ='B10 Cement 55 Tractor '!C168 -> 65.158998 | E100: ='B10 Cement 55 Tractor '!AG168 -> 99.453567 | F100: 2031 | G100: 2036
C101: H2-ICE | D101: ='B10 Cement 55 Tractor '!C169 -> 126.88133 | E101: ='B10 Cement 55 Tractor '!AG169 -> 123.69491
C102: FCET | D102: ='B10 Cement 55 Tractor '!C170 -> 128.4386 | E102: ='B10 Cement 55 Tractor '!AG170 -> 123.32249
C103: Diesel - 10% | D103: ='B10 Cement 55 Tractor '!C171 -> 57.671151 | E103: ='B10 Cement 55 Tractor '!AG171 -> 132.69689
B105: TCO 40T TT LPG (H2 Cost in 2055 - 220/70) | C105: Diesel | D105: ='B14 LPG Tankers 40T'!C165 -> 60.271456 | E105: ='B14 LPG Tankers 40T'!AG165 -> 149.5197
C106: CNG | D106: ='B14 LPG Tankers 40T'!C166 -> 59.411165 | E106: ='B14 LPG Tankers 40T'!AG166 -> 160.77392
C107: LNG | D107: ='B14 LPG Tankers 40T'!C167 -> 61.483762 | E107: ='B14 LPG Tankers 40T'!AG167 -> 161.91998
C108: BET | D108: ='B14 LPG Tankers 40T'!C168 -> 78.760076 | E108: ='B14 LPG Tankers 40T'!AG168 -> 123.44542 | F108: 2040 | G108: 2046
...

Sheet TCO Compaison
A1: TCO Comparison (Rs./km) - Summary
A2: Sl. No. | B2: Parameter | C2: Powertrain | D2: H2 Cost in 2055 - 330/100 | J2: H2 Cost in 2055 - 220/70 | P2: H2 Cost in 2055 - 170/70 | V2: H2 Cost in line with new Electricity Cost | AB2: TCO
D3: H2 Cost in 2055 - 330/100 | J3: H2 Cost in 2055 - 220/70 | P3: H2 Cost in 2055 - 170/70 | V3: H2 Cost in line with new Electricity Cost | AB3: 2025 | AD3: 2055
D4: TCO 2025 | E4: Diff with Diesel | F4: TCO 2055 | G4: Diff with Diesel | H4: Diff with BET | J4: TCO 2025 | K4: Diff with Diesel | L4: TCO 2055 | M4: Diff with Diesel | N4: Diff with BET | P4: TCO 2025 | Q4: Diff with Diesel | R4: TCO 2055 | S4: Diff with Diesel | T4: Diff with BET | V4: TCO 2025 | W4: Diff with Diesel | X4: TCO 2055 | Y4: Diff with Diesel | Z4: Diff with BET | AB4: TCO 2025 | AC4: Diff with Diesel | AD4: TCO 2055 | AE4: Diff with Diesel | AF4: Diff with BET (Rs.) | AG4: Diff with BET (%) | AK4: Remarks
A6: B1 | B6: 19T Market Load (H2 Cost in 2055 - 220/70) | C6: Diesel | D6: ='B1 - TCO ML 19T'!C165 -> 33.521745 | E6: =D6-D$6 -> 0 | F6: ='B1 - TCO ML 19T'!AG165 -> 78.262657 | G6: =F6-F$6 -> 0 | J6: 33.521745 | K6: =J6-J$6 -> 0 | L6: 75.454311 | M6: =L6-L$6 -> 0 | P6: 33.521745 | Q6: =P6-P$6 -> 0 | R6: 75.454311 | S6: =R6-R$6 -> 0 | V6: 33.521745 | W6: =V6-V$6 -> 0 | X6: 75.454311 | Y6: =X6-X$6 -> 0 | AB6: ='B1 - TCO ML 19T'!C165 -> 33.521745 | AC6: =AB6-AB$6 -> 0 | AD6: ='B1 - TCO ML 19T'!AG165 -> 78.262657 | AE6: =AD6-AD$6 -> 0
C7: CNG | D7: ='B1 - TCO ML 19T'!C166 -> 33.072847 | E7: =D7-D$6 -> -0.44889816 | F7: ='B1 - TCO ML 19T'!AG166 -> 86.495082 | G7: =F7-F$6 -> 8.2324248 | J7: 33.072847 | K7: =J7-J$6 -> -0.44889816 | L7: 80.358533 | M7: =L7-L$6 -> 4.9042215 | P7: 33.072847 | Q7: =P7-P$6 -> -0.44889816 | R7: 80.358533 | S7: =R7-R$6 -> 4.9042215 | V7: 33.072847 | W7: =V7-V$6 -> -0.44889816 | X7: 80.358533 | Y7: =X7-X$6 -> 4.9042215 | AB7: ='B1 - TCO ML 19T'!C166 -> 33.072847 | AC7: =AB7-AB$6 -> -0.44889816 | AD7: ='B1 - TCO ML 19T'!AG166 -> 86.495082 | AE7: =AD7-AD$6 -> 8.2324248
C8: LNG | D8: ='B1 - TCO ML 19T'!C167 -> 33.134497 | E8: =D8-D$6 -> -0.38724836 | F8: ='B1 - TCO ML 19T'!AG167 -> 85.122288 | G8: =F8-F$6 -> 6.8596311 | J8: 33.134497 | K8: =J8-J$6 -> -0.38724836 | L8: 79.732378 | M8: =L8-L$6 -> 4.2780664 | P8: 33.134497 | Q8: =P8-P$6 -> -0.38724836 | R8: 79.732378 | S8: =R8-R$6 -> 4.2780664 | V8: 33.134497 | W8: =V8-V$6 -> -0.38724836 | X8: 79.732378 | Y8: =X8-X$6 -> 4.2780664 | AB8: ='B1 - TCO ML 19T'!C167 -> 33.134497 | AC8: =AB8-AB$6 -> -0.38724836 | AD8: ='B1 - TCO ML 19T'!AG167 -> 85.122288 | AE8: =AD8-AD$6 -> 6.8596311
C9: BET | D9: ='B1 - TCO ML 19T'!C168 -> 40.041671 | E9: =D9-D$6 -> 6.5199255 | F9: ='B1 - TCO ML 19T'!AG168 -> 57.817388 | G9: =F9-F$6 -> -20.445269 | H9: =F9-F$9 -> 0 | J9: 45.808315 | K9: =J9-J$6 -> 12.28657 | L9: 58.600351 | M9: =L9-L$6 -> -16.85396 | N9: =L9-L$9 -> 0 | P9: 45.808315 | Q9: =P9-P$6 -> 12.28657 | R9: 58.600351 | S9: =R9-R$6 -> -16.85396 | T9: =R9-R$9 -> 0 | V9: 45.808315 | W9: =V9-V$6 -> 12.28657 | X9: 62.228801 | Y9: =X9-X$6 -> -13.22551 | Z9: =X9-X$9 -> 0 | AB9: ='B1 - TCO ML 19T'!C168 -> 40.041671 | AC9: =AB9-AB$6 -> 6.5199255 | AD9: ='B1 - TCO ML 19T'!AG168 -> 57.817388 | AE9: =AD9-AD$6 -> -20.445269
C10: H2-ICE | D10: ='B1 - TCO ML 19T'!C169 -> 66.706792 | E10: =D10-D$6 -> 33.185047 | F10: ='B1 - TCO ML 19T'!AG169 -> 67.895607 | G10: =F10-F$6 -> -10.36705 | H10: =F10-F$9 -> 10.078219 | J10: 70.136279 | K10: =J10-J$6 -> 36.614534 | L10: 64.460772 | M10: =L10-L$6 -> -10.993539 | N10: =L10-L$9 -> 5.8604212 | P10: 70.136279 | Q10: =P10-P$6 -> 36.614534 | R10: 61.267884 | S10: =R10-R$6 -> -14.186427 | T10: =R10-R$9 -> 2.667533 | V10: 70.136279 | W10: =V10-V$6 -> 36.614534 | X10: 68.207775 | Y10: =X10-X$6 -> -7.2465361 | Z10: =X10-X$9 -> 5.9789741 | AB10: ='B1 - TCO ML 19T'!C169 -> 66.706792 | AC10: =AB10-AB$6 -> 33.185047 | AD10: ='B1 - TCO ML 19T'!AG169 -> 67.895607 | AE10: =AD10-AD$6 -> -10.36705 | AF10: =AD10-AD$9 -> 10.078219 | AG10: =AF10/AD9 -> 0.17431122
C11: FCET | D11: ='B1 - TCO ML 19T'!C170 -> 72.215837 | E11: =D11-D$6 -> 38.694092 | F11: ='B1 - TCO ML 19T'!AG170 -> 69.073503 | G11: =F11-F$6 -> -9.1891534 | H11: =F11-F$9 -> 11.256116 | J11: 74.787953 | K11: =J11-J$6 -> 41.266207 | L11: 66.497377 | M11: =L11-L$6 -> -8.9569339 | N11: =L11-L$9 -> 7.8970265 | P11: 74.787953 | Q11: =P11-P$6 -> 41.266207 | R11: 64.102711 | S11: =R11-R$6 -> -11.3516 | T11: =R11-R$9 -> 5.5023603 | V11: 74.787953 | W11: =V11-V$6 -> 41.266207 | X11: 69.30763 | Y11: =X11-X$6 -> -6.1466816 | Z11: =X11-X$9 -> 7.0788286 | AB11: ='B1 - TCO ML 19T'!C170 -> 72.215837 | AC11: =AB11-AB$6 -> 38.694092 | AD11: ='B1 - TCO ML 19T'!AG170 -> 69.073503 | AE11: =AD11-AD$6 -> -9.1891534 | AF11: =AD11-AD$9 -> 11.256116 | AG11: =AF11/AD9 -> 0.19468392
C12: Diesel - 10% | D12: ='B1 - TCO ML 19T'!C171 -> 30.169571 | F12: ='B1 - TCO ML 19T'!AG171 -> 70.436391 | J12: 30.169571 | L12: 67.90888 | P12: 30.169571 | R12: 67.90888 | V12: 30.169571 | X12: 67.90888 | AB12: ='B1 - TCO ML 19T'!C171 -> 30.169571 | AD12: ='B1 - TCO ML 19T'!AG171 -> 70.436391
A14: B3 | B14: 48T Market Load (H2 Cost in 2055 - 220/70) | C14: Diesel | D14: 61.165655 | E14: =D14-D$14 -> 0 | F14: 137.75029 | G14: =F14-F$14 -> 0 | J14: 61.165655 | L14: 137.75029 | P14: 61.165655 | R14: 137.75029 | V14: 61.165655 | X14: 137.75029 | AB14: ='B3 - TCO ML 48T '!C165 -> 61.165655 | AD14: ='B3 - TCO ML 48T '!AG165 -> 142.78594
C15: CNG | D15: 58.833206 | E15: =D15-D$14 -> -2.3324495 | F15: 142.61354 | G15: =F15-F$14 -> 4.8632576 | J15: 58.833206 | K15: =J15-J$14 -> -2.3324495 | L15: 142.61354 | M15: =L15-L$14 -> 4.8632576 | P15: 58.833206 | Q15: =P15-P$14 -> -2.3324495 | R15: 142.61354 | S15: =R15-R$14 -> 4.8632576 | V15: 58.833206 | W15: =V15-V$14 -> -2.3324495 | X15: 142.61354 | Y15: =X15-X$14 -> 4.8632576 | AB15: ='B3 - TCO ML 48T '!C166 -> 58.833206 | AC15: =AB15-AB$14 -> -2.3324495 | AD15: ='B3 - TCO ML 48T '!AG166 -> 153.30302 | AE15: =AD15-AD$14 -> 10.517076
C16: LNG | D16: 58.969566 | E16: =D16-D$14 -> -2.19609 | F16: 142.1105 | G16: =F16-F$14 -> 4.3602137 | J16: 58.969566 | K16: =J16-J$14 -> -2.19609 | L16: 142.1105 | M16: =L16-L$14 -> 4.3602137 | P16: 58.969566 | Q16: =P16-P$14 -> -2.19609 | R16: 142.1105 | S16: =R16-R$14 -> 4.3602137 | V16: 58.969566 | W16: =V16-V$14 -> -2.19609 | X16: 142.1105 | Y16: =X16-X$14 -> 4.3602137 | AB16: ='B3 - TCO ML 48T '!C167 -> 58.969566 | AC16: =AB16-AB$14 -> -2.19609 | AD16: ='B3 - TCO ML 48T '!AG167 -> 151.63268 | AE16: =AD16-AD$14 -> 8.8467343
C17: BET | D17: 74.461126 | E17: =D17-D$14 -> 13.29547 | F17: 102.3916 | G17: =F17-F$14 -> -35.358684 | H17: =F17-F$17 -> 0 | J17: 74.461126 | K17: =J17-J$14 -> 13.29547 | L17: 102.3916 | M17: =L17-L$14 -> -35.358684 | N17: =L17-L$17 -> 0 | P17: 74.461126 | Q17: =P17-P$14 -> 13.29547 | R17: 102.3916 | S17: =R17-R$14 -> -35.358684 | T17: =R17-R$17 -> 0 | V17: 74.461126 | W17: =V17-V$14 -> 13.29547 | X17: 107.54782 | Y17: =X17-X$14 -> -30.202466 | Z17: =X17-X$17 -> 0 | AB17: ='B3 - TCO ML 48T '!C168 -> 66.26642 | AC17: =AB17-AB$14 -> 5.1007647 | AD17: ='B3 - TCO ML 48T '!AG168 -> 101.27897 | AE17: =AD17-AD$14 -> -41.50697
C18: H2-ICE | D18: 124.07694 | E18: =D18-D$14 -> 62.911288 | F18: 131.67055 | G18: =F18-F$14 -> -6.0797333 | H18: =F18-F$17 -> 29.278951 | J18: 124.07694 | K18: =J18-J$14 -> 62.911288 | L18: 115.635 | M18: =L18-L$14 -> -22.115291 | N18: =L18-L$17 -> 13.243393 | P18: 124.07694 | Q18: =P18-P$14 -> 62.911288 | R18: 109.90982 | S18: =R18-R$14 -> -27.84047 | T18: =R18-R$17 -> 7.518214 | V18: 124.07694 | W18: =V18-V$14 -> 62.911288 | X18: 122.35376 | Y18: =X18-X$14 -> -15.396527 | Z18: =X18-X$17 -> 14.805938 | AB18: ='B3 - TCO ML 48T '!C169 -> 117.92752 | AC18: =AB18-AB$14 -> 56.761863 | AD18: ='B3 - TCO ML 48T '!AG169 -> 121.79401 | AE18: =AD18-AD$14 -> -20.991932 | AF18: =AD18-AD$17 -> 20.515039 | AG18: =AF18/AD17 -> 0.20255971
C19: FCET | D19: 126.16024 | E19: =D19-D$14 -> 64.994582 | F19: 129.06565 | G19: =F19-F$14 -> -8.684639 | H19: =F19-F$17 -> 26.674045 | J19: 126.16024 | K19: =J19-J$14 -> 64.994582 | L19: 117.03898 | M19: =L19-L$14 -> -20.711308 | N19: =L19-L$17 -> 14.647377 | P19: 126.16024 | Q19: =P19-P$14 -> 64.994582 | R19: 112.7451 | S19: =R19-R$14 -> -25.005192 | T19: =R19-R$17 -> 10.353493 | V19: 126.16024 | W19: =V19-V$14 -> 64.994582 | X19: 122.07805 | Y19: =X19-X$14 -> -15.672234 | Z19: =X19-X$17 -> 14.530231 | AB19: ='B3 - TCO ML 48T '!C170 -> 121.54817 | AC19: =AB19-AB$14 -> 60.382513 | AD19: ='B3 - TCO ML 48T '!AG170 -> 121.65824 | AE19: =AD19-AD$14 -> -21.127701 | AF19: =AD19-AD$17 -> 20.379269 | AG19: =AF19/AD17 -> 0.20121916
C20: Diesel - 10% | D20: 55.04909 | F20: 123.97526 | J20: 55.04909 | L20: 123.97526 | P20: 55.04909 | R20: 123.97526 | V20: 55.04909 | X20: 123.97526 | AB20: ='B3 - TCO ML 48T '!C171 -> 55.04909 | AD20: ='B3 - TCO ML 48T '!AG171 -> 128.50735
A22: B5 | B22: 28T Parcel Load (H2 Cost in 2055 - 220/70) | C22: Diesel | D22: 41.09072 | F22: 92.495171 | J22: 41.09072 | L22: 92.495171 | P22: 41.09072 | R22: 92.495171 | V22: 41.09072 | X22: 92.495171 | AB22: ='B5 - TCO PL&FMCG 28T '!C165 -> 41.09072 | AD22: ='B5 - TCO PL&FMCG 28T '!AG165 -> 95.740371
C23: CNG | D23: 39.969475 | E23: =D23-D$22 -> -1.1212456 | F23: 96.76515 | G23: =F23-F$22 -> 4.2699791 | J23: 39.969475 | K23: =J23-J$22 -> -1.1212456 | L23: 96.76515 | M23: =L23-L$22 -> 4.2699791 | P23: 39.969475 | Q23: =P23-P$22 -> -1.1212456 | R23: 96.76515 | S23: =R23-R$22 -> 4.2699791 | V23: 39.969475 | W23: =V23-V$22 -> -1.1212456 | X23: 96.76515 | Y23: =X23-X$22 -> 4.2699791 | AB23: ='B5 - TCO PL&FMCG 28T '!C166 -> 39.969475 | AC23: =AB23-AB$22 -> -1.1212456 | AD23: ='B5 - TCO PL&FMCG 28T '!AG166 -> 103.66877 | AE23: =AD23-AD$22 -> 7.9283973
C24: LNG | D24: 40.206321 | E24: =D24-D$22 -> -0.88439972 | F24: 96.507024 | G24: =F24-F$22 -> 4.0118524 | J24: 40.206321 | K24: =J24-J$22 -> -0.88439972 | L24: 96.507024 | M24: =L24-L$22 -> 4.0118524 | P24: 40.206321 | Q24: =P24-P$22 -> -0.88439972 | R24: 96.507024 | S24: =R24-R$22 -> 4.0118524 | V24: 40.206321 | W24: =V24-V$22 -> -0.88439972 | X24: 96.507024 | Y24: =X24-X$22 -> 4.0118524 | AB24: ='B5 - TCO PL&FMCG 28T '!C167 -> 40.206321 | AC24: =AB24-AB$22 -> -0.88439972 | AD24: ='B5 - TCO PL&FMCG 28T '!AG167 -> 102.65036 | AE24: =AD24-AD$22 -> 6.9099916
C25: BET | D25: 56.428695 | E25: =D25-D$22 -> 15.337974 | F25: 73.390132 | G25: =F25-F$22 -> -19.10504 | H25: =F25-F$25 -> 0 | J25: 56.428695 | K25: =J25-J$22 -> 15.337974 | L25: 73.390132 | M25: =L25-L$22 -> -19.10504 | N25: =L25-L$25 -> 0 | P25: 56.428695 | Q25: =P25-P$22 -> 15.337974 | R25: 73.390132 | S25: =R25-R$22 -> -19.10504 | T25: =R25-R$25 -> 0 | V25: 56.428695 | W25: =V25-V$22 -> 15.337974 | X25: 77.782466 | Y25: =X25-X$22 -> -14.712705 | Z25: =X25-X$25 -> 0 | AB25: ='B5 - TCO PL&FMCG 28T '!C168 -> 49.44802 | AC25: =AB25-AB$22 -> 8.3572991 | AD25: ='B5 - TCO PL&FMCG 28T '!AG168 -> 72.442334 | AE25: =AD25-AD$22 -> -23.298037
C26: H2-ICE | D26: 83.028023 | E26: =D26-D$22 -> 41.937302 | F26: 89.567502 | G26: =F26-F$22 -> -2.9276693 | H26: =F26-F$25 -> 16.17737 | J26: 83.028023 | K26: =J26-J$22 -> 41.937302 | L26: 79.233476 | M26: =L26-L$22 -> -13.261696 | N26: =L26-L$25 -> 5.8433441 | P26: 83.028023 | Q26: =P26-P$22 -> 41.937302 | R26: 75.543916 | S26: =R26-R$22 -> -16.951255 | T26: =R26-R$25 -> 2.1537844 | V26: 83.028023 | W26: =V26-V$22 -> 41.937302 | X26: 83.563346 | Y26: =X26-X$22 -> -8.9318253 | Z26: =X26-X$25 -> 5.7808799 | AB26: ='B5 - TCO PL&FMCG 28T '!C169 -> 79.06506 | AC26: =AB26-AB$22 -> 37.974339 | AD26: ='B5 - TCO PL&FMCG 28T '!AG169 -> 83.202618 | AE26: =AD26-AD$22 -> -12.537753 | AF26: =AD26-AD$25 -> 10.760284 | AG26: =AF26/AD25 -> 0.14853585
C27: FCET | D27: 85.736155 | E27: =D27-D$22 -> 44.645435 | F27: 88.08965 | G27: =F27-F$22 -> -4.4055214 | H27: =F27-F$25 -> 14.699518 | J27: 85.736155 | K27: =J27-J$22 -> 44.645435 | L27: 80.33913 | M27: =L27-L$22 -> -12.156041 | N27: =L27-L$25 -> 6.9489986 | P27: 85.736155 | Q27: =P27-P$22 -> 44.645435 | R27: 77.57196 | S27: =R27-R$22 -> -14.923211 | T27: =R27-R$25 -> 4.1818288 | V27: 85.736155 | W27: =V27-V$22 -> 44.645435 | X27: 83.586533 | Y27: =X27-X$22 -> -8.9086384 | Z27: =X27-X$25 -> 5.8040668 | AB27: ='B5 - TCO PL&FMCG 28T '!C170 -> 82.763933 | AC27: =AB27-AB$22 -> 41.673212 | AD27: ='B5 - TCO PL&FMCG 28T '!AG170 -> 83.315987 | AE27: =AD27-AD$22 -> -12.424384 | AF27: =AD27-AD$25 -> 10.873653 | AG27: =AF27/AD25 -> 0.15010081
C28: Diesel - 10% | D28: 36.981648 | F28: 83.245654 | J28: 36.981648 | L28: 83.245654 | P28: 36.981648 | R28: 83.245654 | V28: 36.981648 | X28: 83.245654 | AB28: ='B5 - TCO PL&FMCG 28T '!C171 -> 36.981648 | AD28: ='B5 - TCO PL&FMCG 28T '!AG171 -> 86.166334
A30: B6 | B30: 15T Perishables (H2 Cost in 2055 - 220/70) | C30: Diesel | D30: 29.688488 | F30: 66.564521 | J30: 29.688488 | L30: 66.564521 | P30: 29.688488 | R30: 66.564521 | V30: 29.688488 | X30: 66.564521 | AB30: ='B6 Perishables 15T'!C165 -> 29.688488 | AD30: ='B6 Perishables 15T'!AG165 -> 68.998421
C31: CNG | D31: 29.047288 | E31: =D31-D$30 -> -0.6411998 | F31: 70.25773 | G31: =F31-F$30 -> 3.6932086 | J31: 29.047288 | K31: =J31-J$30 -> -0.6411998 | L31: 70.25773 | M31: =L31-L$30 -> 3.6932086 | P31: 29.047288 | Q31: =P31-P$30 -> -0.6411998 | R31: 70.25773 | S31: =R31-R$30 -> 3.6932086 | V31: 29.047288 | W31: =V31-V$30 -> -0.6411998 | X31: 70.25773 | Y31: =X31-X$30 -> 3.6932086 | AB31: ='B6 Perishables 15T'!C166 -> 29.047288 | AC31: =AB31-AB$30 -> -0.6411998 | AD31: ='B6 Perishables 15T'!AG166 -> 75.517629 | AE31: =AD31-AD$30 -> 6.5192081
C32: LNG | D32: 29.334585 | E32: =D32-D$30 -> -0.35390248 | F32: 70.283392 | G32: =F32-F$30 -> 3.7188706 | J32: 29.334585 | K32: =J32-J$30 -> -0.35390248 | L32: 70.283392 | M32: =L32-L$30 -> 3.7188706 | P32: 29.334585 | Q32: =P32-P$30 -> -0.35390248 | R32: 70.283392 | S32: =R32-R$30 -> 3.7188706 | V32: 29.334585 | W32: =V32-V$30 -> -0.35390248 | X32: 70.283392 | Y32: =X32-X$30 -> 3.7188706 | AB32: ='B6 Perishables 15T'!C167 -> 29.334585 | AC32: =AB32-AB$30 -> -0.35390248 | AD32: ='B6 Perishables 15T'!AG167 -> 74.928355 | AE32: =AD32-AD$30 -> 5.9299344
C33: BET | D33: 41.115025 | E33: =D33-D$30 -> 11.426537 | F33: 52.614452 | G33: =F33-F$30 -> -13.950069 | H33: =F33-F$33 -> 0 | J33: 41.115025 | K33: =J33-J$30 -> 11.426537 | L33: 52.614452 | M33: =L33-L$30 -> -13.950069 | N33: =L33-L$33 -> 0 | P33: 41.115025 | Q33: =P33-P$30 -> 11.426537 | R33: 54.630322 | S33: =R33-R$30 -> -11.934199 | T33: =R33-R$33 -> 0 | V33: 41.115025 | W33: =V33-V$30 -> 11.426537 | X33: 55.86096 | Y33: =X33-X$30 -> -10.703561 | Z33: =X33-X$33 -> 0 | AB33: ='B6 Perishables 15T'!C169 -> 58.383175 | AC33: =AB33-AB$30 -> 28.694687 | AD33: ='B6 Perishables 15T'!AG168 -> 51.913906 | AE33: =AD33-AD31 -> -23.603723
C34: H2-ICE | D34: 61.355397 | E34: =D34-D$30 -> 31.666909 | F34: 65.148012 | G34: =F34-F$30 -> -1.4165094 | H34: =F34-F$33 -> 12.53356 | J34: 61.355397 | K34: =J34-J$30 -> 31.666909 | L34: 57.397492 | M34: =L34-L$30 -> -9.1670292 | N34: =L34-L$33 -> 4.7830402 | P34: 61.633175 | Q34: =P34-P$30 -> 31.944687 | R34: 52.614452 | S34: =R34-R$30 -> -13.950069 | T34: =R34-R$33 -> -2.0158704 | V34: 61.355397 | W34: =V34-V$30 -> 31.666909 | X34: 60.644895 | Y34: =X34-X$30 -> -5.9196265 | Z34: =X34-X$33 -> 4.7839348 | AB34: ='B6 Perishables 15T'!C168 -> 35.955395 | AC34: =AB34-AB$30 -> 6.2669075 | AD34: ='B6 Perishables 15T'!AG169 -> 60.374349 | AE34: =AD34-AD30 -> -8.6240719 | AF34: =AD34-AD$33 -> 8.460443 | AG34: =AF34/AD33 -> 0.16297065
C35: FCET | D35: 65.995979 | E35: =D35-D$30 -> 36.307492 | F35: 64.954579 | G35: =F35-F$30 -> -1.6099417 | H35: =F35-F$33 -> 12.340128 | J35: 65.995979 | K35: =J35-J$30 -> 36.307492 | L35: 59.141689 | M35: =L35-L$30 -> -7.4228315 | N35: =L35-L$33 -> 6.5272378 | P35: 65.995979 | Q35: =P35-P$30 -> 36.307492 | R35: 57.066312 | S35: =R35-R$30 -> -9.4982089 | T35: =R35-R$33 -> 2.4359901 | V35: 65.995979 | W35: =V35-V$30 -> 36.307492 | X35: 61.577241 | Y35: =X35-X$30 -> -4.9872795 | Z35: =X35-X$33 -> 5.7162818 | AB35: ='B6 Perishables 15T'!C170 -> 63.766813 | AC35: =AB35-AB$30 -> 34.078325 | AD35: ='B6 Perishables 15T'!AG170 -> 61.374332 | AE35: =AD35-AD$30 -> -7.6240884 | AF35: =AD35-AD$33 -> 9.4604264 | AG35: =AF35/AD33 -> 0.18223299
C36: Diesel - 10% | D36: 26.719639 | F36: 59.908069 | J36: 26.719639 | L36: 59.908069 | P36: 26.719639 | R36: 59.908069 | V36: 26.719639 | X36: 59.908069 | AB36: ='B6 Perishables 15T'!C171 -> 26.719639 | AD36: ='B6 Perishables 15T'!AG171 -> 62.098578
A38: B7 | B38: 28Tipper Const. & Mining (H2 Cost in 2055 - 220/70) | C38: Diesel | D38: 61.604723 | F38: 144.77967 | J38: 61.604723 | L38: 144.77967 | P38: 61.604723 | R38: 144.77967 | V38: 61.604723 | X38: 144.77967 | AB38: ='B7 C&M 28Tip'!C165 -> 61.604723 | AD38: ='B7 C&M 28Tip'!AG165 -> 148.62267
C39: CNG | D39: 60.93252 | E39: =D39-D$38 -> -0.67220325 | F39: 154.16757 | G39: =F39-F$38 -> 9.387899 | J39: 60.93252 | K39: =J39-J$38 -> -0.67220325 | L39: 154.16757 | M39: =L39-L$38 -> 9.387899 | P39: 60.93252 | Q39: =P39-P$38 -> -0.67220325 | R39: 154.16757 | S39: =R39-R$38 -> 9.387899 | V39: 60.93252 | W39: =V39-V$38 -> -0.67220325 | X39: 154.16757 | Y39: =X39-X$38 -> 9.387899 | AB39: ='B7 C&M 28Tip'!C166 -> 60.93252 | AC39: =AB39-AB$38 -> -0.67220325 | AD39: ='B7 C&M 28Tip'!AG166 -> 162.45191 | AE39: =AD39-AD$38 -> 13.829241
C40: LNG | D40: 61.463428 | E40: =D40-D$38 -> -0.14129574 | F40: 150.80704 | G40: =F40-F$38 -> 6.0273686 | J40: 61.463428 | K40: =J40-J$38 -> -0.14129574 | L40: 150.80704 | M40: =L40-L$38 -> 6.0273686 | P40: 61.463428 | Q40: =P40-P$38 -> -0.14129574 | R40: 150.80704 | S40: =R40-R$38 -> 6.0273686 | V40: 61.463428 | W40: =V40-V$38 -> -0.14129574 | X40: 150.80704 | Y40: =X40-X$38 -> 6.0273686 | AB40: ='B7 C&M 28Tip'!C167 -> 61.463428 | AC40: =AB40-AB$38 -> -0.14129574 | AD40: ='B7 C&M 28Tip'!AG167 -> 158.13179 | AE40: =AD40-AD$38 -> 9.5091192
C41: BET | D41: 83.905941 | E41: =D41-D$38 -> 22.301218 | F41: 119.36107 | G41: =F41-F$38 -> -25.418602 | H41: =F41-F$41 -> 0 | J41: 83.905941 | K41: =J41-J$38 -> 22.301218 | L41: 119.36107 | M41: =L41-L$38 -> -25.418602 | N41: =L41-L$41 -> 0 | P41: 83.905941 | Q41: =P41-P$38 -> 22.301218 | R41: 119.36107 | S41: =R41-R$38 -> -25.418602 | T41: =R41-R$41 -> 0 | V41: 83.905941 | W41: =V41-V$38 -> 22.301218 | X41: 123.77636 | Y41: =X41-X$38 -> -21.003309 | Z41: =X41-X$41 -> 0 | AB41: ='B7 C&M 28Tip'!C168 -> 76.014743 | AC41: =AB41-AB$38 -> 14.41002 | AD41: ='B7 C&M 28Tip'!AG168 -> 118.28965 | AE41: =AD41-AD$38 -> -30.333024
C42: H2-ICE | D42: 112.41617 | E42: =D42-D$38 -> 50.811448 | F42: 141.56311 | G42: =F42-F$38 -> -3.2165622 | H42: =F42-F$41 -> 22.20204 | J42: 112.41617 | K42: =J42-J$38 -> 50.811448 | L42: 129.32545 | M42: =L42-L$38 -> -15.454225 | N42: =L42-L$41 -> 9.9643767 | P42: 112.41617 | Q42: =P42-P$38 -> 50.811448 | R42: 124.95623 | S42: =R42-R$38 -> -19.82344 | T42: =R42-R$41 -> 5.5951613 | V42: 112.41617 | W42: =V42-V$38 -> 50.811448 | X42: 134.45292 | Y42: =X42-X$38 -> -10.326747 | Z42: =X42-X$41 -> 10.676562 | AB42: ='B7 C&M 28Tip'!C169 -> 107.72319 | AC42: =AB42-AB$38 -> 46.118466 | AD42: ='B7 C&M 28Tip'!AG169 -> 134.02575 | AE42: =AD42-AD$38 -> -14.596924 | AF42: =AD42-AD$41 -> 15.7361 | AG42: =AF42/AD41 -> 0.13303024
C43: FCET | D43: 122.80206 | E43: =D43-D$38 -> 61.197332 | F43: 138.98049 | G43: =F43-F$38 -> -5.7991809 | H43: =F43-F$41 -> 19.619421 | J43: 122.80206 | K43: =J43-J$38 -> 61.197332 | L43: 129.80224 | M43: =L43-L$38 -> -14.977428 | N43: =L43-L$41 -> 10.441174 | P43: 122.80206 | Q43: =P43-P$38 -> 61.197332 | R43: 126.52533 | S43: =R43-R$38 -> -18.25434 | T43: =R43-R$41 -> 7.1642621 | V43: 122.80206 | W43: =V43-V$38 -> 61.197332 | X43: 133.64785 | Y43: =X43-X$38 -> -11.131819 | Z43: =X43-X$41 -> 9.8714894 | AB43: ='B7 C&M 28Tip'!C170 -> 119.28232 | AC43: =AB43-AB$38 -> 57.677595 | AD43: ='B7 C&M 28Tip'!AG170 -> 133.32747 | AE43: =AD43-AD$38 -> -15.295202 | AF43: =AD43-AD$41 -> 15.037822 | AG43: =AF43/AD41 -> 0.12712712
C44: Diesel - 10% | D44: 55.444251 | F44: 130.3017 | J44: 55.444251 | L44: 130.3017 | P44: 55.444251 | R44: 130.3017 | V44: 55.444251 | X44: 130.3017 | AB44: ='B7 C&M 28Tip'!C171 -> 55.444251 | AD44: ='B7 C&M 28Tip'!AG171 -> 133.7604
A46: B10 | B46: 55T TT Cement (H2 Cost in 2055 - 220/70) | C46: Diesel | D46: 64.079057 | F46: 141.8243 | J46: 64.079057 | L46: 141.8243 | P46: 64.079057 | R46: 141.8243 | V46: 64.079057 | X46: 141.8243 | AB46: ='B10 Cement 55 Tractor '!C165 -> 64.079057 | AD46: ='B10 Cement 55 Tractor '!AG165 -> 147.44099
C47: CNG | D47: 61.125763 | E47: =D47-D$46 -> -2.9532937 | F47: 146.40096 | G47: =F47-F$46 -> 4.5766655 | J47: 61.125763 | K47: =J47-J$46 -> -2.9532937 | L47: 146.40096 | M47: =L47-L$46 -> 4.5766655 | P47: 61.125763 | Q47: =P47-P$46 -> -2.9532937 | R47: 146.40096 | S47: =R47-R$46 -> 4.5766655 | V47: 61.125763 | W47: =V47-V$46 -> -2.9532937 | X47: 146.40096 | Y47: =X47-X$46 -> 4.5766655 | AB47: ='B10 Cement 55 Tractor '!C166 -> 61.125763 | AC47: =AB47-AB$46 -> -2.9532937 | AD47: ='B10 Cement 55 Tractor '!AG166 -> 158.23574 | AE47: =AD47-AD$46 -> 10.794747
C48: LNG | D48: 62.26334 | E48: =D48-D$46 -> -1.8157163 | F48: 147.50097 | G48: =F48-F$46 -> 5.6766688 | J48: 62.26334 | K48: =J48-J$46 -> -1.8157163 | L48: 147.50097 | M48: =L48-L$46 -> 5.6766688 | P48: 62.26334 | Q48: =P48-P$46 -> -1.8157163 | R48: 147.50097 | S48: =R48-R$46 -> 5.6766688 | V48: 62.26334 | W48: =V48-V$46 -> -1.8157163 | X48: 147.50097 | Y48: =X48-X$46 -> 5.6766688 | AB48: ='B10 Cement 55 Tractor '!C167 -> 62.26334 | AC48: =AB48-AB$46 -> -1.8157163 | AD48: ='B10 Cement 55 Tractor '!AG167 -> 158.08116 | AE48: =AD48-AD$46 -> 10.640172
C49: BET | D49: 73.960719 | E49: =D49-D$46 -> 9.881662 | F49: 100.64862 | G49: =F49-F$46 -> -41.175682 | H49: =F49-F$49 -> 0 | J49: 73.960719 | K49: =J49-J$46 -> 9.881662 | L49: 100.64862 | M49: =L49-L$46 -> -41.175682 | N49: =L49-L$49 -> 0 | P49: 73.960719 | Q49: =P49-P$46 -> 9.881662 | R49: 100.64862 | S49: =R49-R$46 -> -41.175682 | T49: =R49-R$49 -> 0 | V49: 73.960719 | W49: =V49-V$46 -> 9.881662 | X49: 106.18678 | Y49: =X49-X$46 -> -35.637521 | Z49: =X49-X$49 -> 0 | AB49: ='B10 Cement 55 Tractor '!C168 -> 65.158998 | AC49: =AB49-AB$46 -> 1.0799413 | AD49: ='B10 Cement 55 Tractor '!AG168 -> 99.453567 | AE49: =AD49-AD$46 -> -47.987422
C50: H2-ICE | D50: 133.74031 | E50: =D50-D$46 -> 69.661252 | F50: 134.71105 | G50: =F50-F$46 -> -7.1132455 | H50: =F50-F$49 -> 34.062436 | J50: 133.74031 | K50: =J50-J$46 -> 69.661252 | L50: 116.82524 | M50: =L50-L$46 -> -24.99906 | N50: =L50-L$49 -> 16.176621 | P50: 133.74031 | Q50: =P50-P$46 -> 69.661252 | R50: 110.43946 | S50: =R50-R$46 -> -31.384837 | T50: =R50-R$49 -> 9.7908448 | V50: 133.74031 | W50: =V50-V$46 -> 69.661252 | X50: 124.31924 | Y50: =X50-X$46 -> -17.505054 | Z50: =X50-X$49 -> 18.132467 | AB50: ='B10 Cement 55 Tractor '!C169 -> 126.88133 | AC50: =AB50-AB$46 -> 62.802278 | AD50: ='B10 Cement 55 Tractor '!AG169 -> 123.69491 | AE50: =AD50-AD$46 -> -23.746082 | AF50: =AD50-AD$49 -> 24.24134 | AG50: =AF50/AD49 -> 0.2437453
C51: FCET | D51: 133.58283 | E51: =D51-D$46 -> 69.503774 | F51: 131.5846 | G51: =F51-F$46 -> -10.239696 | H51: =F51-F$49 -> 30.935986 | J51: 133.58283 | K51: =J51-J$46 -> 69.503774 | L51: 118.17024 | M51: =L51-L$46 -> -23.654057 | N51: =L51-L$49 -> 17.521625 | P51: 133.58283 | Q51: =P51-P$46 -> 69.503774 | R51: 113.38091 | S51: =R51-R$46 -> -28.443389 | T51: =R51-R$49 -> 12.732292 | V51: 133.58283 | W51: =V51-V$46 -> 69.503774 | X51: 123.79075 | Y51: =X51-X$46 -> -18.033552 | Z51: =X51-X$49 -> 17.603969 | AB51: ='B10 Cement 55 Tractor '!C170 -> 128.4386 | AC51: =AB51-AB$46 -> 64.359544 | AD51: ='B10 Cement 55 Tractor '!AG170 -> 123.32249 | AE51: =AD51-AD$46 -> -24.118496 | AF51: =AD51-AD$49 -> 23.868926 | AG51: =AF51/AD49 -> 0.2400007
C52: Diesel - 10% | D52: 57.671151 | F52: 127.64187 | J52: 57.671151 | L52: 127.64187 | P52: 57.671151 | R52: 127.64187 | V52: 57.671151 | X52: 127.64187 | AB52: ='B10 Cement 55 Tractor '!C171 -> 57.671151 | AD52: ='B10 Cement 55 Tractor '!AG171 -> 132.69689
A54: B14 | B54: 40T TT LPG (H2 Cost in 2055 - 220/70) | C54: Diesel | D54: 60.271456 | F54: 145.4632 | J54: 60.271456 | L54: 145.4632 | P54: 60.271456 | R54: 145.4632 | V54: 60.271456 | X54: 145.4632 | AB54: ='B14 LPG Tankers 40T'!C165 -> 60.271456 | AD54: ='B14 LPG Tankers 40T'!AG165 -> 149.5197
C55: CNG | D55: 59.411165 | E55: =D55-D$54 -> -0.86029135 | F55: 152.05356 | G55: =F55-F$54 -> 6.5903592 | J55: 59.411165 | K55: =J55-J$54 -> -0.86029135 | L55: 152.05356 | M55: =L55-L$54 -> 6.5903592 | P55: 59.411165 | Q55: =P55-P$54 -> -0.86029135 | R55: 152.05356 | S55: =R55-R$54 -> 6.5903592 | V55: 59.411165 | W55: =V55-V$54 -> -0.86029135 | X55: 152.05356 | Y55: =X55-X$54 -> 6.5903592 | AB55: ='B14 LPG Tankers 40T'!C166 -> 59.411165 | AC55: =AB55-AB$54 -> -0.86029135 | AD55: ='B14 LPG Tankers 40T'!AG166 -> 160.77392 | AE55: =AD55-AD$54 -> 11.254219
C56: LNG | D56: 61.483762 | E56: =D56-D$54 -> 1.2123054 | F56: 154.1993 | G56: =F56-F$54 -> 8.7361001 | J56: 61.483762 | K56: =J56-J$54 -> 1.2123054 | L56: 154.1993 | M56: =L56-L$54 -> 8.7361001 | P56: 61.483762 | Q56: =P56-P$54 -> 1.2123054 | R56: 154.1993 | S56: =R56-R$54 -> 8.7361001 | V56: 61.483762 | W56: =V56-V$54 -> 1.2123054 | X56: 154.1993 | Y56: =X56-X$54 -> 8.7361001 | AB56: ='B14 LPG Tankers 40T'!C167 -> 61.483762 | AC56: =AB56-AB$54 -> 1.2123054 | AD56: ='B14 LPG Tankers 40T'!AG167 -> 161.91998 | AE56: =AD56-AD$54 -> 12.400283
C57: BET | D57: 86.347766 | E57: =D57-D$54 -> 26.07631 | F57: 124.47563 | G57: =F57-F$54 -> -20.987566 | H57: =F57-F$57 -> 0 | J57: 86.347766 | K57: =J57-J$54 -> 26.07631 | L57: 124.47563 | M57: =L57-L$54 -> -20.987566 | N57: =L57-L$57 -> 0 | P57: 86.347766 | Q57: =P57-P$54 -> 26.07631 | R57: 124.47563 | S57: =R57-R$54 -> -20.987566 | T57: =R57-R$57 -> 0 | V57: 86.347766 | W57: =V57-V$54 -> 26.07631 | X57: 129.24991 | Y57: =X57-X$54 -> -16.213289 | Z57: =X57-X$57 -> 0 | AB57: ='B14 LPG Tankers 40T'!C168 -> 78.760076 | AC57: =AB57-AB$54 -> 18.48862 | AD57: ='B14 LPG Tankers 40T'!AG169 -> 133.76536 | AE57: =AD57-AD$54 -> -15.754336
C58: H2-ICE | D58: 115.48941 | E58: =D58-D$54 -> 55.217951 | F58: 141.72147 | G58: =F58-F$54 -> -3.7417321 | H58: =F58-F$57 -> 17.245834 | J58: 115.48941 | K58: =J58-J$54 -> 55.217951 | L58: 128.80393 | M58: =L58-L$54 -> -16.659265 | N58: =L58-L$57 -> 4.3283007 | P58: 115.48941 | Q58: =P58-P$54 -> 55.217951 | R58: 124.19198 | S58: =R58-R$54 -> -21.271215 | T58: =R58-R$57 -> -0.28364896 | V58: 115.48941 | W58: =V58-V$54 -> 55.217951 | X58: 134.21627 | Y58: =X58-X$54 -> -11.246927 | Z58: =X58-X$57 -> 4.966362 | AB58: ='B14 LPG Tankers 40T'!C169 -> 110.5357 | AC58: =AB58-AB$54 -> 50.264247 | AD58: ='B14 LPG Tankers 40T'!AG168 -> 123.44542 | AE58: =AD58-AD$54 -> -26.07428 | AF58: =AD59-AD$58 -> 17.524677 | AG58: =AF58/AD57 -> 0.13101058
C59: FCET | D59: 128.54406 | E59: =D59-D$54 -> 68.272608 | F59: 146.93717 | G59: =F59-F$54 -> 1.4739754 | H59: =F59-F$57 -> 22.461541 | J59: 128.54406 | K59: =J59-J$54 -> 68.272608 | L59: 137.24902 | M59: =L59-L$54 -> -8.2141744 | N59: =L59-L$57 -> 12.773391 | P59: 128.54406 | Q59: =P59-P$54 -> 68.272608 | R59: 133.79006 | S59: =R59-R$54 -> -11.673137 | T59: =R59-R$57 -> 9.3144292 | V59: 128.54406 | W59: =V59-V$54 -> 68.272608 | X59: 141.30828 | Y59: =X59-X$54 -> -4.1549209 | Z59: =X59-X$57 -> 12.058368 | AB59: ='B14 LPG Tankers 40T'!C170 -> 124.82879 | AC59: =AB59-AB$54 -> 64.55733 | AD59: ='B14 LPG Tankers 40T'!AG170 -> 140.9701 | AE59: =AD59-AD$54 -> -8.5496025 | AF59: =AD60-AD$58 -> 11.12231 | AG59: =AF59/AD57 -> 0.083147907
C60: Diesel - 10% | D60: 54.244311 | F60: 130.91688 | J60: 54.244311 | L60: 130.91688 | P60: 54.244311 | R60: 130.91688 | V60: 54.244311 | X60: 130.91688 | AB60: ='B14 LPG Tankers 40T'!C171 -> 54.244311 | AD60: ='B14 LPG Tankers 40T'!AG171 -> 134.56773

Sheet Results
C3: Parameter Values | D3: PT Mix - 2045 Estimates | J3: PT Mix - 2055 Estimates | N3: CO2 Reduction (Cum.) | O3: Cum. Diesel Savings | P3: H2 Reqd. in 2055 | Q3: Energy Reqd. in 2055
D4: Diesel | E4: CNG | F4: LNG | G4: BET | H4: H2 ICE | I4: H2 FCET | J4: BET | K4: H2 ICE | L4: H2 FCET | N4: Bil. Tons | O4: Bil. Ltrs. | P4: Mil. Tons | Q4: TWh
D5: ='Estimation SS2045'!R174 -> 0.096140252 | E5: ='Estimation SS2045'!S174 -> 0.049059805 | F5: ='Estimation SS2045'!T174 -> 0.0048070126 | G5: ='Estimation SS2045'!U174 -> 0.76063905 | H5: ='Estimation SS2045'!V174 -> 0.04934257 | I5: ='Estimation SS2045'!W174 -> 0.040152693 | J5: ='Estimation 100% ZET 2055'!O161 -> 0.87248713 | K5: ='Estimation 100% ZET 2055'!P161 -> 0.065941536 | L5: ='Estimation 100% ZET 2055'!Q161 -> 0.061571331 | N5: ='Emissions '!K118 -> 4622.0332 | O5: ='Energy Requirementsfinal'!E198 -> 2570.3878 | P5: ='Energy Requirementsfinal'!M197 -> 13.205755 | Q5: ='Energy Requirementsfinal'!J197 -> 903.35203
D6: ='Estimation SS2045'!R175 -> 68000 | E6: ='Estimation SS2045'!S175 -> 34700 | F6: ='Estimation SS2045'!T175 -> 3400 | G6: ='Estimation SS2045'!U175 -> 538000 | H6: ='Estimation SS2045'!V175 -> 34900 | I6: ='Estimation SS2045'!W175 -> 28400 | J6: ='Estimation 100% ZET 2055'!O162 -> 898400 | K6: ='Estimation 100% ZET 2055'!P162 -> 67900 | L6: ='Estimation 100% ZET 2055'!Q162 -> 63400

Sheet Dashboard
B3: Parameters | C3: What | E3: How | F3: Values/ Restriction | G3: Default
A4: 1 | B4: Diesel/LNG/CNG Price | C4: Value | D4: Year | E4: Drop down | F4: 2026 to 2055
D5: Value | E5: Value Entry | F5: Max. Rs.500
C6: CAGR % | D6: Year range | E6: Drop down | F6: 2025-30 2031-35 2036-40 2041-45 2046-50 2051-55
D7: Change % | E7: Value Entry | F7: Max. 10%
A8: 2 | B8: Energy Price (incl. CAAS) | C8: Value | D8: Year | E8: Drop down | F8: 2026 to 2055
D9: Value | E9: Value Entry | F9: Max. Rs.500
C10: CAGR % | D10: Year range | E10: Drop down | F10: 2025-30 2031-35 2036-40 2041-45 2046-50 2051-55
D11: Change % | E11: Value Entry | F11: Max. 10%
A12: 3 | B12: Green H2 Prodn. Cost | C12: Value | D12: Year | E12: Drop down | F12: 2026 to 2055
D13: Value | E13: Value Entry | F13: Max. Rs.500
C14: CAGR % | D14: Year range | E14: Drop down | F14: 2025-30 2031-35 2036-40 2041-45 2046-50 2051-55
D15: Change % | E15: Value Entry | F15: Max. 10%
A16: 4 | B16: H2 Compression, Transportation & Dispense Cost | C16: Value | D16: Year | E16: Drop down | F16: 2026 to 2055
D17: Value | E17: Value Entry | F17: Max. Rs.500
C18: CAGR % | D18: Year range | E18: Drop down | F18: 2025-30 2031-35 2036-40 2041-45 2046-50 2051-55
D19: Change % | E19: Value Entry | F19: Max. 10%
A20: 5 | B20: Battery Price / kWh | C20: Value | D20: Year | E20: Drop down | F20: 2026 to 2055
D21: Value | E21: Value Entry | F21: Max. Rs.500
C22: CAGR % | D22: Year range | E22: Drop down | F22: 2025-30 2031-35 2036-40 2041-45 2046-50 2051-55
D23: Change % | E23: Value Entry | F23: Max. 10%
A24: 6 | B24: Fuel Cell Price / kW | C24: Value | D24: Year | E24: Drop down | F24: 2026 to 2055
D25: Value | E25: Value Entry | F25: Max. Rs.500
C26: CAGR % | D26: Year range | E26: Drop down | F26: 2025-30 2031-35 2036-40 2041-45 2046-50 2051-55
D27: Change % | E27: Value Entry | F27: Max. 10%
A28: 7 | B28: Diesel Maintenance Cost/km (for Each Bucket) | D28: Bucket | E28: Drop down | F28: B1 to B14
C29: Maint. Cost | D29: Year | E29: Drop down | F29: 2026 to 2055
D30: Value | E30: Value Entry
C31: CAGR % | D31: Year range | E31: Drop down | F31: 2025-30 2031-35 2036-40 2041-45 2046-50 2051-55
D32: Change % | E32: Value Entry | F32: Max. 10%
A33: 8 | B33: BET Related Aggregates Maintenance Cost/km incl Battery Replacement (for Each Bucket) | D33: Bucket | E33: Drop down | F33: B1 to B14
C34: Maint. Cost | D34: Year | E34: Drop down | F34: 2026 to 2055
D35: Value | E35: Value Entry
C36: CAGR % | D36: Year range | E36: Drop down | F36: 2025-30 2031-35 2036-40 2041-45 2046-50 2051-55
D37: Change % | E37: Value Entry | F37: Max. 10%
A38: 9 | B38: FCET Related Aggregates Maintenance Cost/km incl Battery & FC Replacement (for Each Bucket) | D38: Bucket | E38: Drop down | F38: B1 to B14
C39: Maint. Cost | D39: Year | E39: Drop down | F39: 2026 to 2055
D40: Value | E40: Value Entry
C41: CAGR % | D41: Year range | E41: Drop down | F41: 2025-30 2031-35 2036-40 2041-45 2046-50 2051-55
D42: Change % | E42: Value Entry | F42: Max. 10%
A43: 10 | B43: Battery Life (no.of Cycles) | C43: Value | E43: Value Entry | F43: 4 digit value | G43: 3000
A44: 11 | B44: Fuel Cell Life (no.of Hours) | C44: Value | E44: Value Entry | F44: 5 digit value | G44: 25000
A45: 12 | B45: Funding (non-ZETs) | C45: Rate | D45: % | E45: Value Entry | G45: 0.12
C46: Tenure | D46: Years | E46: Value Entry | G46: 7 Years
A47: 13 | B47: Funding (ZETs) | C47: Rate | D47: % | E47: Value Entry | G47: 0.12
C48: Tenure | D48: Years | E48: Value Entry | G48: 7 Years

Sheet Input Parameters
A1: Parameter Assumptions:
A2: Sl. No. | B2: Parameter | E2: Assumptions/Values & Trend | H2: Remarks
E3: Base Value (2025) | F3: Trend | G3: Value (2055)
A4: 1 | B4: Product Pilot Year/ Base Year | C4: Diesel/CNG/LNG | D4: Year | E4: 2025 | H4: Based on discussions with OEMs, Fuel & Energy producers/Suppliers, Charging Service Providers, Tier 1 Suppliers, Industry Experts & other relevant stakeholders
C5: BET | E5: 2025
C6: H2 ICE | E6: 2028
C7: H2 FCET | E7: 2030
A8: 2 | B8: Product Start of Sale - All Geography/Variants Year | C8: CNG | E8: 2028
C9: LNG | E9: 2028
C10: BET | E10: 2027
C11: H2 ICE | E11: 2034
C12: H2 FCET | E12: 2038
A13: 3 | B13: Power Train Maturity Year - Products, Technology & Eco-system | C13: CNG | E13: 2030
C14: LNG | E14: 2033
C15: BET | E15: 2035
C16: H2 ICE | E16: 2042
C17: H2 FCET | E17: 2045
A18: 4 | B18: Inflection Point (3% Share) | C18: BET | E18: 2032
C19: H2 ICE | E19: 2049
C20: H2 FCET | E20: 2050
A21: 5 | B21: ICE Trucks Price (Diesel/CNG/LNG/H2) - On-road Price for Fully Built Trucks including taxes & registration | C21: Diesel Truck Price | D21: INR | E21: On-road price of each model | F21: 3.0% Annual Increase (based on past trend) | H21: Rs. 4,00,000/- increase for BS7 effective 2030
C22: CNG Cylinder System Capacity | D22: Litres/Kg. | E22: 480 l/96 kg 15T Trucks & 960 l/192 kg. for Heavier trucks | H22: CNG Option for Rigid Trucks only
C23: CNG Cylinder Cost | D23: INR | E23: Rs.1,50,000/- & Rs.2,50,000/- | F23: 3.0% Annual Increase
C24: CNG Truck Price | D24: INR | E24: Diesel Truck Price + CNG Cylinder System Cost
C25: LNG Cylinder System Capacity | D25: Litres/Kg. | E25: 450 l/158 kg for 40T Trucks & 990 l/ 347 kg. for Heavier Trucks | H25: - LNG Option for Articulated Trucks only - Lower CAGR for LNG Cylinders due to cost reduction on account of indiginization & volume build up
C26: LNG Cylinder Cost per kg. of LNG | D26: INR | E26: Rs.3050/- | F26: 1.0% Annual Increase | G26: Rs.4100/-
C27: LNG Pipe/Valves System Cost | D27: INR | E27: Rs.1,00,000/- per Truck | F27: 1.0% Annual Increase | G27: Rs.1,35,000/-
C28: LNG Truck Price | D28: INR | E28: Diesel Truck Price + LNG Cyl Cost + LNG Valves System Cost
C29: H2 Cylinder System Capacity | D29: Litres/Kg. | E29: 1200 litres/28 kg
C30: H2 Cylinder Cost per kg. of H2 | D30: INR | E30: Rs.56,000/- | F30: 2026-30: -5.0% 2031-40: -4.0% 2041-50: +1.0% 2051-55: +1.0% | G30: Rs.33,500/- | H30: Reduction in cost initially through Indiginesation & Increased Capacity Utilization
C31: H2 Truck Price | D31: INR | E31: Diesel Truck Price + H2 Cylinder System Cost
A32: 6 | B32: BET Price | C32: Diesel Engine & Transmission Cost | D32: INR | E32: 3 sets of values for various GVW of trucks | F32: 2.0% Annual Increase
C33: ePowertrain Cost | D33: INR | E33: Rs.14,00,000/- for 4x2 Trucks & Rs.17,00,000/- for Heavier Trucks | F33: 2026-30: -4.0% 2031-40: -1.0% 2041-50: +1.0% 2051-55: +1.0% | G33: Rs.12,00,000/- & Rs.14,55,000/- | H33: Reduction in cost initially through Technology Improvements, Indiginesation & Increased Capacity Utilization
C34: Battery Pack Capacity, kWh | D34: kWh | E34: 200-350 kWh for various Models
C35: Battery Pack Cost per kWh | D35: INR | E35: Rs.9,900/- (USD110) | F35: 2026-30: -1.5% 2031-40: -2.5.% 2041-50: -1.0% 2051-55: +1.0% | G35: Rs.6,800/- | H35: Reduction in cost initially through Technology Improvements, Indiginesation & Increased Capacity Utilization
C36: BET Mfg. & Other Costs (% of Battery & ePowertrain Costs | D36: % | E36: 2026-30: from 50% to 35% progressively 2031-40: 30% 2041-55: 25 % | H36: - Additional Cost for Investment on Manufacturing Facilities & Margin. - Reduction over a period as capacity builds up
C37: BET Price | D37: INR | E37: Diesel Truck Price - (Engine & Transmission Costs) + ePowertrain Cost + Battery Cost + BET Mfg. Costs
A38: 7 | B38: FCET Price | C38: Fuel Cell Cost per kW | D38: INR | E38: Rs.36,000/- | F38: 2026-30: -3.0% 2031-40: -3.0.% 2041-50: -2.0% 2051-55: +1.0% | G38: Rs.19,600/- | H38: Reduction in cost initially through Technology Improvements, Indiginesation & Increased Capacity Utilization
C39: Fuel Cell Power Rating | D39: kW | E39: 80 kW for upto 40T Trucks & 120 kW for Heavier Trucks
C40: Battery Pack Capacity for FCET | D40: kWh | E40: 70 kWh for upto 40T Trucks & 80 kWh for Heavier Trucks
C41: Battery Pack Cost per kWh | D41: INR | E41: (Same as values under BETs)
C42: FCET Mfg. & Other Costs (% of Battery, Fuel Cell & ePowertrain Costs) | D42: % | E42: 2026-40: 40% 2041-45: 35% 2046-50: 30 % 2051-55: 25% | H42: Additional Cost for Investment on Manufacturing Facilities & Margin. Reduction over a period as capacity builds up
C43: FCET Price | D43: INR | E43: Diesel Truck Price - (Engine & Transmission Costs) + ePowertrain Cost + Battery Cost + Fuel Cell Cost + FCET Mfg. Costs
A44: 8 | B44: Fuel/Energy Costs | C44: Diesel Price per litre | D44: INR | E44: 88.926296 | F44: 0.02 | G44: 161.20523 | H44: BS6 increase in 2030
C45: CNG Price per kg. | D45: INR | E45: 89.61 | F45: 0.03 | G45: 211.17183
C46: LNG Price per kg. | D46: INR | E46: 85.49 | F46: 0.03 | G46: 201.46279
C47: Electricity Charges per kWh | D47: INR | E47: 7.5 | F47: 2026-30 : 2% 2031-40 : -2% 2041-50 : -1% 2051-55 : 2.5% | G47: 6.9229971 | H47: - Reduction expected between 2031-50 due to increase in RE share.
C48: Demand Charges & CAAS Costs per kWh | D48: INR | E48: 4.43 | G48: 3.68 | H48: - Progressive reduction due to increased capacity utilization at Charge Stations - Weighted average of mix of Public charging & Shipper/Customer end charging - Predominantly Shipper end charging initially and progressive switching to Public Charging as volume grows
C49: Green H2 Production Cost per kg. | D49: INR | E49: 546.5 | F49: - Electric Energy required for Prodn. of 1 kg. of H2: 2026-30 : 53 kWh 2031-40 : 50 kWh 2041-50 : 45 kWh 2051-55 : 42 kWh - Electric Energy Cost: Discom rate minus Rs.2/- per kWh | G49: 270.53188 | H49: - H2 Production Cost per kg = Cost of Electricity X Energy Consumption by Electrolyser + Capex + Opex - Electric Energy Cost is less than Discom rate due to mix of captive RE source - Capex & Opex per kg comes down with increased capacity utilization
C50: Green H2 Compression, Storage & Dispense Costs per kg. | D50: INR | E50: 175 | F50: 2026-30 : -4% 2031-40 : -3% 2041-50 : -3% 2051-55 : -2% | G50: 70.138953 | H50: Progressive reduction due to improved transportation methods (pipeline), technology improvement in compression and increased capacity utilization at Fuel Stations
A51: 9 | B51: Maintenance Costs (Average per km of for 10 years of operation) | C51: Diesel | D51: INR | E51: OEM AMC for Chassis + Suspension, Body & FC Repairs Costs + Tyre Costs (based on no. of tyres & life) - Varies applicationwise
C52: CNG/LNG | D52: INR | E52: Diesel Maintenance Cost (above) + Rs.0.50/- | H52: Additional cost for SI engine over CI engine
C53: H2 ICE | D53: INR
C54: BET (incl. one time replacement of batteries) | D54: INR | E54: Diesel Maint. Cost less Engine & Transmission maint. cost + ePowertrain Maint. Cost + Battery Replacement cost
C55: FCET (inc. one time replacement of batteries & Fuel Cell replenishent costs) | D55: INR | E55: Diesel Maint. Cost less Engine & Transmission + ePowertrain Maint. Cost + Battery Replacement cost + FC Replenishment cost
A56: 10 | B56: Resale Value after 7 years (% of Initial Purchase Price) | C56: Diesel | D56: % | E56: 0.5 | F56: 2026-35: 50% 2036-45 : 40% 2045-55 : 30% | G56: 0.3 | H56: - Resale Value varies for different Models, Applications & Powertrain - Values shown here are for a 55T Tractor for Cement Application - Resale Value for Diesel Truck reduces as the market swithches over to Zero Emission Trucks - CNG & LNG Trucks fetch lesser resale value as compared to equivalent Diesel Trucks due to higher maintenance costs - Resale Value of ZETs increase as the Adoption increases - However uncertainty in residual life of the battery & Fuel Cell restricts resale prices
C57: CNG/LNG | D57: % | E57: 0.45 | F57: 2026-35: 45% 2036-45 : 35% 2045-55 : 25% | G57: 0.25
C58: H2 ICE | D58: % | E58: 0.2 | F58: 2026-35: 20% 2036-45 : 30% 2045-55 : 35% | G58: 0.35
C59: BET | D59: % | E59: 0.15 | F59: 2026-35: 15% 2036-45 : 25% 2045-55 : 35% | G59: 0.35
C60: FCET | D60: % | E60: 0.05 | F60: 2026-35: 05% 2036-45 : 15% 2045-55 : 25% | G60: 0.25
A61: 11 | B61: Manpower Costs / Km. (Driver & Crew) | C61: Diesel/CNG/LNG | D61: INR | E61: 5.5 | F61: 0.045 | G61: 21 | H61: Overall long term wage increase considered
C62: BET/FCET | D62: INR | E62: 6 | G62: 23
A63: 12 | B63: Toll Charges/km | C63: Rate based on GVW Rating/No. of Axles | D63: INR | E63: Rs.5.30/- to 9.00/- per km for various models | F63: 0.01 | G63: Rs.7.15/- to 12,15/- per km for various models | H63: Marginal Increase considered. Increase or decrease will not have significant impact on adoption as the rates are equal for all powertrains.
A64: 13 | B64: Other Fixed Parameters | C64: Rate of Interest & Tenure (Fossil & ZETs) | E64: 12.0% & 7 years
C65: Insurance Cost | D65: % | E65: 2% of Truck Price annually
C66: Fuel/Energy Efficiency | D66: kmpl km/kg kWh/km | E66: - Varies with Model & Application - For Diesel, CNG, LNG & Electric Trucks (Inputs from OEMs & Users) - H2 ICE Trucks (km/kg.) - 3x Diesel kmpl - FCET (km/kg) - 4x Diesel kmpl
C67: Operational Parameters - Distance per day & year, etc. | E67: - Varies with Model & Application - Inputs from OEMs & Field Study with Users
C68: Rated Payload Reduction/loss | E68: 8 kg./kWh loss for batteries & 4 kg./kW for Fuel Cell for BETs & FCETs | H68: Reduction in payload rating impacts adoption of BETs & FCETs negatively for applications which are sensitive to payload rating
C69: Vehicle TAT & Gradeability Factor | E69: Diesel : 100% CNG : 95% LNG : 95% H2 ICE : 95% BET : 115% FCET: 115% | H69: Better TAT & Gradeability has positive impact on Adoption
C70: Range & Filling Time Factor | E70: Diesel : 100% CNG : 105% LNG : 110% H2 ICE : 100% BET : 120% FCET: 100% | H70: Lower Range per fill & Higher Filling Time impacts adoption negatively

Sheet Charge station economics
A1: Economics of BET charging infrastructure - 4 nos. 240kW chargers
A3: Space required for 1 BET charging bay | B3: =75*25 -> 1875
A4: Space required for waiting vehicle | B4: =75*25 -> 1875
A5: Space required for maneuvring | B5: 1250
A6: Space required per charging bay | B6: =SUM(B3:B5) -> 5000
A7: Area per acre in sft | B7: 43636
A8: Less - Allowance for land constraints / office space | B8: -3636
A9: Available for charger bay | B9: =B8+B7 -> 40000
A10: No. of bays possible in 1 acre * | B10: =B9/B6 -> 8
A11: * Can be slightly higher in captive chargers (eg. In warehouses, factories where waiting space need not be high)
A13: Assuming land cost of Rs.2 crores per acre :
A15: For 0.5 acre plot / 2 chargers
B16: Rs. Lacs
A17: Land cost | B17: 100
A18: Cost of 240kW chargers (20L x4) | B18: 80 | C18: (includes civil work, installation)
A19: Power connection expenses (HT line, transformer etc) | B19: 20
A20: Capex excluding land | B20: =B18+B19 -> 100
A21: Assuming 25 days/month operation; for 4 chargers - energy dispensation
A23: For Captive user (Shipper / Operator) | B23: 2026 | C23: 2027 | D23: 2028 | E23: 2029 | F23: 2030 | G23: 2031 | H23: 2032 | I23: 2033 | J23: 2034 | K23: 2035 | L23: 2036 | M23: 2037 | N23: 2038 | O23: 2039 | P23: 2040 | Q23: 2041 | R23: 2042 | S23: 2043 | T23: 2044 | U23: 2045 | V23: 2046 | W23: 2047 | X23: 2048 | Y23: 2049 | Z23: 2050 | AA23: 2051 | AB23: 2052 | AC23: 2053 | AD23: 2054 | AE23: 2055
A24: Monthly demand charges (for 960kW) - Rs. 305/kVA; power factor taken as 0.98 (Rs. Lacs) | B24: =305*960/0.98/100000 -> 2.9877551 | C24: =B24 -> 2.9877551 | D24: =C24 -> 2.9877551 | E24: =D24 -> 2.9877551 | F24: =E24 -> 2.9877551 | G24: =F24 -> 2.9877551 | H24: =G24 -> 2.9877551 | I24: =H24 -> 2.9877551 | J24: =I24 -> 2.9877551 | ... AE24: =AD24 -> 2.9877551
A25: Man power (2 person / 2 shift) - Rs. Lacs | B25: 1 | C25: =B25*1.07 -> 1.07 | D25: =C25*1.07 -> 1.1449 | E25: =D25*1.07 -> 1.225043 | F25: =E25*1.07 -> 1.310796 | G25: =F25*1.07 -> 1.4025517 | H25: =G25*1.07 -> 1.5007304 | I25: =H25*1.07 -> 1.6057815 | J25: =I25*1.07 -> 1.7181862 | ... AE25: =AD25*1.07 -> 7.114257
A26: Administrative overheads @10% of manpower cost Rs. Lacs | B26: =B25*0.1 -> 0.1 | C26: =C25*0.1 -> 0.107 | D26: =D25*0.1 -> 0.11449 | E26: =E25*0.1 -> 0.1225043 | F26: =F25*0.1 -> 0.1310796 | G26: =G25*0.1 -> 0.14025517 | H26: =H25*0.1 -> 0.15007304 | I26: =I25*0.1 -> 0.16057815 | ... AE26: =AE25*0.1 -> 0.7114257
A27: Fixed cost per month (Rs. Lacs) | B27: =SUM(B24:B26) -> 4.0877551 | C27: =SUM(C24:C26) -> 4.1647551 | D27: =SUM(D24:D26) -> 4.2471451 | E27: =SUM(E24:E26) -> 4.3353024 | F27: =SUM(F24:F26) -> 4.4296307 | G27: =SUM(G24:G26) -> 4.530562 | H27: =SUM(H24:H26) -> 4.6385585 | I27: =SUM(I24:I26) -> 4.7541147 | ... AE27: =SUM(AE24:AE26) -> 10.813438
A28: No. of hours operated per day | B28: 8 | C28: 9 | D28: 10 | E28: 12 | F28: 14 | G28: 14 | H28: 14 | I28: 14 | J28: 14 | K28: 14 | L28: 14 | M28: 14 | N28: 14 | O28: 14 | P28: 14 | Q28: 14 | R28: 14 | S28: 14 | T28: 14 | U28: 14 | V28: 14 | W28: 14 | X28: 14 | Y28: 14 | Z28: 14 | AA28: 14 | AB28: 14 | AC28: 14 | AD28: 14 | AE28: 14
A29: Capacity utilisation (based on max 20 hrs charging / day) | B29: =B28/20 -> 0.4 | C29: =C28/20 -> 0.45 | D29: =D28/20 -> 0.5 | E29: =E28/20 -> 0.6 | F29: =F28/20 -> 0.7 | G29: =G28/20 -> 0.7 | H29: =H28/20 -> 0.7 | I29: =I28/20 -> 0.7 | ... AE29: =AE28/20 -> 0.7
A30: Energy dispensed per month (kWh) | B30: =B28*25*240*4 -> 192000 | C30: =C28*25*240*4 -> 216000 | D30: =D28*25*240*4 -> 240000 | E30: =E28*25*240*4 -> 288000 | F30: =F28*25*240*4 -> 336000 | G30: =G28*25*240*4 -> 336000 | H30: =H28*25*240*4 -> 336000 | I30: =I28*25*240*4 -> 336000 | ... AE30: =AE28*25*240*4 -> 336000
A31: Monthly fixed cost amortised over energy dispensed (Rs./kWh) | B31: =B27*100000/B30 -> 2.1290391 | C31: =C27*100000/C30 -> 1.9281274 | D31: =D27*100000/D30 -> 1.7696438 | E31: =E27*100000/E30 -> 1.5053133 | F31: =F27*100000/F30 -> 1.3183425 | G31: =G27*100000/G30 -> 1.3483815 | H31: =H27*100000/H30 -> 1.3805234 | I31: =I27*100000/I30 -> 1.4149151 | ... AE31: =AE27*100000/AE30 -> 3.2182851
A32: Total energy dispensed in 5 years (kWh) | B32: =12*SUM(B30:F30) -> 15264000
A33: Capex amortisation over 5 years (Rs./kWh) | B33: =B20*100000/B32 -> 0.65513627
A34: Total additional cost incurred by operator/shipper - Rs/kWh | B34: =B31+$B33 -> 2.7841754 | C34: =C31+$B33 -> 2.5832636 | D34: =D31+$B33 -> 2.4247801 | E34: =E31+$B33 -> 2.1604496 | F34: =F31+$B33 -> 1.9734787 | G34: =G31 -> 1.3483815 | H34: =H31 -> 1.3805234 | I34: =I31 -> 1.4149151 | J34: =J31 -> 1.4517143 | K34: =K31 -> 1.4910894 | L34: =L31 -> 1.5332207 | M34: =M31 -> 1.5783013 | N34: =N31 -> 1.6265375 | ... AE34: =AE31 -> 3.2182851
A36: For Charging As Service (CAS) operator | B36: 2026 | C36: 2027 | D36: 2028 | E36: 2029 | F36: 2030 | G36: 2031 | H36: 2032 | I36: 2033 | J36: 2034 | K36: 2035 | L36: 2036 | M36: 2037 | N36: 2038 | O36: 2039 | P36: 2040 | Q36: 2041 | R36: 2042 | S36: 2043 | T36: 2044 | U36: 2045 | V36: 2046 | W36: 2047 | X36: 2048 | Y36: 2049 | Z36: 2050 | AA36: 2051 | AB36: 2052 | AC36: 2053 | AD36: 2054 | AE36: 2055
A37: Monthly demand charges (for 960kW) - Rs. 305/kVA; power factor taken as 0.98 - Rs. Lacs | B37: =305*960/0.98/100000 -> 2.9877551 | C37: =B37 -> 2.9877551 | D37: =C37 -> 2.9877551 | E37: =D37 -> 2.9877551 | F37: =E37 -> 2.9877551 | G37: =F37 -> 2.9877551 | H37: =G37 -> 2.9877551 | I37: =H37 -> 2.9877551 | J37: =I37 -> 2.9877551 | ... AE37: =AD37 -> 2.9877551
A38: Man power cost (2 person / 2 shift) - Rs. Lacs | B38: 1 | C38: =B38*1.07 -> 1.07 | D38: =C38*1.07 -> 1.1449 | E38: =D38*1.07 -> 1.225043 | F38: =E38*1.07 -> 1.310796 | G38: =F38*1.07 -> 1.4025517 | H38: =G38*1.07 -> 1.5007304 | I38: =H38*1.07 -> 1.6057815 | J38: =I38*1.07 -> 1.7181862 | ... AE38: =AD38*1.07 -> 7.114257
A39: Land rental taken @ 4% pa & 3% increase pa - Rs. Lacs | B39: =B17*0.04/12 -> 0.33333333 | C39: =B39*1.03 -> 0.34333333 | D39: =C39*1.03 -> 0.35363333 | E39: =D39*1.03 -> 0.36424233 | F39: =E39*1.03 -> 0.3751696 | G39: =F39*1.03 -> 0.38642469 | H39: =G39*1.03 -> 0.39801743 | I39: =H39*1.03 -> 0.40995796 | J39: =I39*1.03 -> 0.42225669 | ... AE39: =AD39*1.03 -> 0.78552184
A40: Administrative overheads @5% of manpower cost Rs. Lacs | B40: =B38*0.05 -> 0.05 | C40: =C38*0.05 -> 0.0535 | D40: =D38*0.05 -> 0.057245 | E40: =E38*0.05 -> 0.06125215 | F40: =F38*0.05 -> 0.065539801 | G40: =G38*0.05 -> 0.070127587 | H40: =H38*0.05 -> 0.075036518 | I40: =I38*0.05 -> 0.080289074 | ... AE40: =AE38*0.05 -> 0.35571285
A41: Fixed cost per month | B41: =SUM(B37:B40) -> 4.3710884 | C41: =SUM(C37:C40) -> 4.4545884 | D41: =SUM(D37:D40) -> 4.5435334 | E41: =SUM(E37:E40) -> 4.6382926 | F41: =SUM(F37:F40) -> 4.7392605 | G41: =SUM(G37:G40) -> 4.8468591 | H41: =SUM(H37:H40) -> 4.9615394 | I41: =SUM(I37:I40) -> 5.0837836 | ... AE41: =SUM(AE37:AE40) -> 11.243247
A42: Capacity utilisation (based on max 20 hrs charging / day) | B42: 0.1 | C42: 0.15 | D42: 0.2 | E42: 0.25 | F42: 0.3 | G42: 0.35 | H42: 0.4 | I42: 0.5 | J42: 0.6 | K42: 0.7 | L42: 0.7 | M42: 0.7 | N42: 0.7 | O42: 0.7 | P42: 0.7 | Q42: 0.7 | R42: 0.7 | S42: 0.7 | T42: 0.7 | U42: 0.7 | V42: 0.7 | W42: 0.7 | X42: 0.7 | Y42: 0.7 | Z42: 0.7 | AA42: 0.7 | AB42: 0.7 | AC42: 0.7 | AD42: 0.7 | AE42: 0.7
A43: No. of hours operated per day | B43: =B42*20 -> 2 | C43: =C42*20 -> 3 | D43: =D42*20 -> 4 | E43: =E42*20 -> 5 | F43: =F42*20 -> 6 | G43: =G42*20 -> 7 | H43: =H42*20 -> 8 | I43: =I42*20 -> 10 | ... AE43: =AE42*20 -> 14
A44: Power dispensed per month (kW) | B44: =B43*25*240*4 -> 48000 | C44: =C43*25*240*4 -> 72000 | D44: =D43*25*240*4 -> 96000 | E44: =E43*25*240*4 -> 120000 | F44: =F43*25*240*4 -> 144000 | G44: =G43*25*240*4 -> 168000 | H44: =H43*25*240*4 -> 192000 | I44: =I43*25*240*4 -> 240000 | ... AE44: =AE43*25*240*4 -> 336000
A45: Monthly fixed cost amortised over power dispensed (Rs./kW) | B45: =B41*100000/B44 -> 9.1064342 | C45: =C41*100000/C44 -> 6.1869284 | D45: =D41*100000/D44 -> 4.7328473 | E45: =E41*100000/E44 -> 3.8652438 | F45: =F41*100000/F44 -> 3.2911531 | G45: =G41*100000/G44 -> 2.8850352 | H45: =H41*100000/H44 -> 2.5841351 | I45: =I41*100000/I44 -> 2.1182432 | ... AE45: =AE41*100000/AE44 -> 3.3462044
A46: Total power dispensed in 5 years (kW) | B46: =12*SUM(B44:F44) -> 5760000
A47: Capex amortisation over 5 years (Rs./kW) | B47: =$B20*100000/$B46 -> 1.7361111 | C47: =$B20*100000/$B46 -> 1.7361111 | D47: =$B20*100000/$B46 -> 1.7361111 | E47: =$B20*100000/$B46 -> 1.7361111 | F47: =$B20*100000/$B46 -> 1.7361111
A48: Total additional cost incurred by CAS operator (excluding energy cost) | B48: =B45+B47 -> 10.842545 | C48: =C45+C47 -> 7.9230395 | D48: =D45+D47 -> 6.4689584 | E48: =E45+E47 -> 5.6013549 | F48: =F45+F47 -> 5.0272642 | G48: =G45+G47 -> 2.8850352 | H48: =H45+H47 -> 2.5841351 | I48: =I45+I47 -> 2.1182432 | ... AE48: =AE45+AE47 -> 3.3462044
A49: Add - profit margin for CAS operator @ 10% | B49: =B48*0.1 -> 1.0842545 | C49: =C48*0.1 -> 0.79230395 | D49: =D48*0.1 -> 0.64689584 | E49: =E48*0.1 -> 0.56013549 | F49: =F48*0.1 -> 0.50272642 | G49: =G48*0.1 -> 0.28850352 | H49: =H48*0.1 -> 0.25841351 | I49: =I48*0.1 -> 0.21182432 | ... AE49: =AE48*0.1 -> 0.33462044
A50: Price charged by CAS operator to shipper/operator | B50: =B48+B49 -> 11.9268 | C50: =C48+C49 -> 8.7153434 | D50: =D48+D49 -> 7.1158543 | E50: =E48+E49 -> 6.1614904 | F50: =F48+F49 -> 5.5299907 | G50: =G48+G49 -> 3.1735387 | H50: =H48+H49 -> 2.8425486 | I50: =I48+I49 -> 2.3300675 | ... AE50: =AE48+AE49 -> 3.6808249
A51: Averaged over 5 year tenure | B51: =AVERAGE(B50:F50) -> 7.8898957 | G51: Capex amortised in first 5 years

Sheet Charging trend
AF2: Remarks
B3: 2026 | C3: 2027 | D3: 2028 | E3: 2029 | F3: 2030 | G3: 2031 | H3: 2032 | I3: 2033 | J3: 2034 | K3: 2035 | L3: 2036 | M3: 2037 | N3: 2038 | O3: 2039 | P3: 2040 | Q3: 2041 | R3: 2042 | S3: 2043 | T3: 2044 | U3: 2045 | V3: 2046 | W3: 2047 | X3: 2048 | Y3: 2049 | Z3: 2050 | AA3: 2051 | AB3: 2052 | AC3: 2053 | AD3: 2054 | AE3: 2055
A4: Closed loop runs | B4: 0.9 | C4: 0.85 | D4: 0.8 | E4: 0.75 | F4: 0.6 | G4: 0.5 | H4: 0.4 | I4: 0.3 | J4: 0.2 | K4: 0.2 | L4: 0.2 | M4: 0.2 | N4: 0.2 | O4: 0.2 | P4: 0.2 | Q4: 0.2 | R4: 0.2 | S4: 0.2 | T4: 0.2 | U4: 0.2 | V4: 0.2 | W4: 0.2 | X4: 0.2 | Y4: 0.2 | Z4: 0.2 | AA4: 0.2 | AB4: 0.2 | AC4: 0.2 | AD4: 0.2 | AE4: 0.2 | AF4: Only captive use tippers & RMC trucks will have closed loop operation
A5: Point 2 Point movement | B5: 0.1 | C5: 0.15 | D5: 0.2 | E5: 0.25 | F5: 0.4 | G5: 0.5 | H5: 0.6 | I5: 0.7 | J5: 0.8 | K5: 0.8 | L5: 0.8 | M5: 0.8 | N5: 0.8 | O5: 0.8 | P5: 0.8 | Q5: 0.8 | R5: 0.8 | S5: 0.8 | T5: 0.8 | U5: 0.8 | V5: 0.8 | W5: 0.8 | X5: 0.8 | Y5: 0.8 | Z5: 0.8 | AA5: 0.8 | AB5: 0.8 | AC5: 0.8 | AD5: 0.8 | AE5: 0.8 | AF5: Application coverage inline with ecosystem maturity
A7: Closed loop runs - charging locations
A8: Operator end | B8: 0 | C8: 0.02 | D8: 0.05 | E8: 0.12 | F8: 0.16 | G8: 0.2 | H8: 0.2 | I8: 0.2 | J8: 0.23 | K8: 0.3 | L8: 0.33 | M8: 0.36 | N8: 0.27 | O8: 0.28 | P8: 0.4 | Q8: 0.39 | R8: 0.37 | S8: 0.35 | T8: 0.33 | U8: 0.3 | V8: 0.27 | W8: 0.25 | X8: 0.23 | Y8: 0.2 | Z8: 0.18 | AA8: 0.15 | AB8: 0.1 | AC8: 0.08 | AD8: 0.05 | AE8: 0 | AF8: Closed loop operation usually run by larger fleet owners and are more likley to invest on own infra & may have good economics
A9: Shipper end | B9: 0.9 | C9: 0.8 | D9: 0.7 | E9: 0.58 | F9: 0.52 | G9: 0.45 | H9: 0.4 | I9: 0.35 | J9: 0.3 | K9: 0.2 | L9: 0.16 | M9: 0.12 | N9: 0.1 | O9: 0.08 | P9: 0.05 | Q9: 0.02 | R9: 0 | S9: 0 | T9: 0 | U9: 0 | V9: 0 | W9: 0 | X9: 0 | Y9: 0 | Z9: 0 | AA9: 0 | AB9: 0 | AC9: 0 | AD9: 0 | AE9: 0 | AF9: Shippers may quickly offload charging to operators
A10: Public charging | B10: 0.1 | C10: 0.18 | D10: 0.25 | E10: 0.3 | F10: 0.32 | G10: 0.35 | H10: 0.4 | I10: 0.45 | J10: 0.47 | K10: 0.5 | L10: 0.51 | M10: 0.52 | N10: 0.53 | O10: 0.54 | P10: 0.55 | Q10: 0.59 | R10: 0.63 | S10: 0.65 | T10: 0.67 | U10: 0.7 | V10: 0.73 | W10: 0.75 | X10: 0.77 | Y10: 0.8 | Z10: 0.82 | AA10: 0.85 | AB10: 0.9 | AC10: 0.92 | AD10: 0.95 | AE10: 1 | AF10: Adoption to public charging can be slower due to good economics by operators
A12: Point 2 Point movement
A13: Operator end | B13: 0 | C13: 0.02 | D13: 0.03 | E13: 0.05 | F13: 0.07 | G13: 0.1 | H13: 0.13 | I13: 0.16 | J13: 0.2 | K13: 0.2 | L13: 0.2 | M13: 0.2 | N13: 0.2 | O13: 0.2 | P13: 0.2 | Q13: 0.2 | R13: 0.18 | S13: 0.16 | T13: 0.14 | U13: 0.12 | V13: 0.1 | W13: 0.08 | X13: 0.06 | Y13: 0.04 | Z13: 0.02 | AA13: 0 | AB13: 0 | AC13: 0 | AD13: 0 | AE13: 0 | AF13: Operators may find difficulty in establishing own network due to multiple routes
A14: Shipper end | B14: 0.1 | C14: 0.09 | D14: 0.1 | E14: 0.1 | F14: 0.1 | G14: 0.1 | H14: 0.09 | I14: 0.09 | J14: 0.1 | K14: 0.09 | L14: 0.08 | M14: 0.07 | N14: 0.06 | O14: 0.05 | P14: 0.02 | Q14: 0 | R14: 0 | S14: 0 | T14: 0 | U14: 0 | V14: 0 | W14: 0 | X14: 0 | Y14: 0 | Z14: 0 | AA14: 0 | AB14: 0 | AC14: 0 | AD14: 0 | AE14: 0 | AF14: Shippers may quickly offload charging to operators
A15: Public charging | B15: 0.9 | C15: 0.89 | D15: 0.87 | E15: 0.85 | F15: 0.83 | G15: 0.8 | H15: 0.78 | I15: 0.75 | J15: 0.7 | K15: 0.71 | L15: 0.72 | M15: 0.73 | N15: 0.74 | O15: 0.75 | P15: 0.78 | Q15: 0.8 | R15: =1-SUM(S13:S14) -> 0.84 | S15: =1-SUM(T13:T14) -> 0.86 | T15: =1-SUM(U13:U14) -> 0.88 | U15: =1-SUM(V13:V14) -> 0.9 | V15: =1-SUM(W13:W14) -> 0.92 | W15: =1-SUM(X13:X14) -> 0.94 | X15: =1-SUM(Y13:Y14) -> 0.96 | Y15: =1-SUM(Z13:Z14) -> 0.98 | ... AE15: =1-SUM(AF13:AF14) -> 1 | AF15: Dependancy on public chargers higher due to lead distances
A17: Overall share
A18: Operator end | B18: =B8*B$4+B$5*B13 -> 0 | C18: =C8*C$4+C$5*C13 -> 0.02 | D18: =D8*D$4+D$5*D13 -> 0.046 | E18: =E8*E$4+E$5*E13 -> 0.1025 | F18: =F8*F$4+F$5*F13 -> 0.124 | G18: =G8*G$4+G$5*G13 -> 0.15 | H18: =H8*H$4+H$5*H13 -> 0.158 | I18: =I8*I$4+I$5*I13 -> 0.172 | ... AE18: =AE8*AE$4+AE$5*AE13 -> 0
A19: Shipper end | B19: =B9*B$4+B$5*B14 -> 0.82 | C19: =C9*C$4+C$5*C14 -> 0.6935 | D19: =D9*D$4+D$5*D14 -> 0.58 | E19: =E9*E$4+E$5*E14 -> 0.46 | F19: =F9*F$4+F$5*F14 -> 0.352 | G19: =G9*G$4+G$5*G14 -> 0.275 | H19: =H9*H$4+H$5*H14 -> 0.214 | I19: =I9*I$4+I$5*I14 -> 0.168 | ... AE19: =AE9*AE$4+AE$5*AE14 -> 0
A20: Public charging | B20: =B10*B$4+B$5*B15 -> 0.18 | C20: =C10*C$4+C$5*C15 -> 0.2865 | D20: =D10*D$4+D$5*D15 -> 0.374 | E20: =E10*E$4+E$5*E15 -> 0.4375 | F20: =F10*F$4+F$5*F15 -> 0.524 | G20: =G10*G$4+G$5*G15 -> 0.575 | H20: =H10*H$4+H$5*H15 -> 0.628 | I20: =I10*I$4+I$5*I15 -> 0.66 | ... AE20: =AE10*AE$4+AE$5*AE15 -> 1

Sheet Electricity incl CAAS
A1: Year | C1: 2025 | D1: 2026 | E1: 2027 | F1: 2028 | G1: 2029 | H1: 2030 | I1: 2031 | J1: 2032 | K1: 2033 | L1: 2034 | M1: 2035 | N1: 2036 | O1: 2037 | P1: 2038 | Q1: 2039 | R1: 2040 | S1: 2041 | T1: 2042 | U1: 2043 | V1: 2044 | W1: 2045 | X1: 2046 | Y1: 2047 | Z1: 2048 | AA1: 2049 | AB1: 2050 | AC1: 2051 | AD1: 2052 | AE1: 2053 | AF1: 2054 | AG1: 2055 | AH1: % Change 2026-30 | AI1: % Change 2031-40 | AJ1: % Change 2041-50 | AK1: % Change in 2051-55
A2: Final Values for Model
A3: Weighted average cost - captive/CAS charging
A4: Cost of electricity from DISCOM Rs./kWh | D4: ='Electricity incl CAAS'!D16*'Electricity incl CAAS'!D12+'Electricity incl CAAS'!D13*('Electricity incl CAAS'!D21+'Electricity incl CAAS'!D23) -> 7.65 | E4: ='Electricity incl CAAS'!E16*'Electricity incl CAAS'!E12+'Electricity incl CAAS'!E13*('Electricity incl CAAS'!E21+'Electricity incl CAAS'!E23) -> 7.803 | F4: ='Electricity incl CAAS'!F16*'Electricity incl CAAS'!F12+'Electricity incl CAAS'!F13*('Electricity incl CAAS'!F21+'Electricity incl CAAS'!F23) -> 7.95906 | G4: ='Electricity incl CAAS'!G16*'Electricity incl CAAS'!G12+'Electricity incl CAAS'!G13*('Electricity incl CAAS'!G21+'Electricity incl CAAS'!G23) -> 8.1182412 | H4: ='Electricity incl CAAS'!H16*'Electricity incl CAAS'!H12+'Electricity incl CAAS'!H13*('Electricity incl CAAS'!H21+'Electricity incl CAAS'!H23) -> 8.280606 | I4: ='Electricity incl CAAS'!I16*'Electricity incl CAAS'!I12+'Electricity incl CAAS'!I13*('Electricity incl CAAS'!I21+'Electricity incl CAAS'!I23) -> 8.1149939 | J4: ='Electricity incl CAAS'!J16*'Electricity incl CAAS'!J12+'Electricity incl CAAS'!J13*('Electricity incl CAAS'!J21+'Electricity incl CAAS'!J23) -> 7.952694 | K4: ='Electricity incl CAAS'!K16*'Electricity incl CAAS'!K12+'Electricity incl CAAS'!K13*('Electricity incl CAAS'!K21+'Electricity incl CAAS'!K23) -> 7.7936401 | ... AG4: ='Electricity incl CAAS'!AG16*'Electricity incl CAAS'!AG12+'Electricity incl CAAS'!AG13*('Electricity incl CAAS'!AG21+'Electricity incl CAAS'!AG23) -> 6.9229971 | AH4: 0.02 | AI4: -0.02 | AJ4: -0.01 | AK4: 0.025
A5: Fixed demand charges Rs/kWh | D5: ='Charge station economics'!B24/'Charge station economics'!B30*100000*'Electricity incl CAAS'!D12+'Charge station economics'!B37*100000/'Charge station economics'!B44*'Electricity incl CAAS'!D13 -> 2.3964286 | E5: ='Charge station economics'!C24/'Charge station economics'!C30*100000*'Electricity incl CAAS'!E12+'Charge station economics'!C37*100000/'Charge station economics'!C44*'Electricity incl CAAS'!E13 -> 2.175805 | F5: ='Charge station economics'!D24/'Charge station economics'!D30*100000*'Electricity incl CAAS'!F12+'Charge station economics'!D37*100000/'Charge station economics'!D44*'Electricity incl CAAS'!F13 -> 1.9432857 | G5: ='Charge station economics'!E24/'Charge station economics'!E30*100000*'Electricity incl CAAS'!G12+'Charge station economics'!E37*100000/'Charge station economics'!E44*'Electricity incl CAAS'!G13 -> 1.6728316 | H5: ='Charge station economics'!F24/'Charge station economics'!F30*100000*'Electricity incl CAAS'!H12+'Charge station economics'!F37*100000/'Charge station economics'!F44*'Electricity incl CAAS'!H13 -> 1.5104762 | I5: ='Charge station economics'!G24/'Charge station economics'!G30*100000*'Electricity incl CAAS'!I12+'Charge station economics'!G37*100000/'Charge station economics'!G44*'Electricity incl CAAS'!I13 -> 1.4005102 | J5: ='Charge station economics'!H24/'Charge station economics'!H30*100000*'Electricity incl CAAS'!J12+'Charge station economics'!H37*100000/'Charge station economics'!H44*'Electricity incl CAAS'!J13 -> 1.3080321 | K5: ='Charge station economics'!I24/'Charge station economics'!I30*100000*'Electricity incl CAAS'!K12+'Charge station economics'!I37*100000/'Charge station economics'!I44*'Electricity incl CAAS'!K13 -> 1.123965 | ... AG5: ='Charge station economics'!AE24/'Charge station economics'!AE30*100000*'Electricity incl CAAS'!AG12+'Charge station economics'!AE37*100000/'Charge station economics'!AE44*'Electricity incl CAAS'!AG13 -> 0.88921283
A6: Other costs (land/CAS margin etc.) Rs./kWh | D6: ='Electricity incl CAAS'!D29-D5-D4 -> 2.0334192 | E6: ='Electricity incl CAAS'!E29-E5-E4 -> 2.1642995 | F6: ='Electricity incl CAAS'!F29-F5-F4 -> 2.2359561 | G6: ='Electricity incl CAAS'!G29-G5-G4 -> 2.2380733 | H6: ='Electricity incl CAAS'!H29-H5-H4 -> 2.3266148 | I6: ='Electricity incl CAAS'!I29-I5-I4 -> 0.99733671 | J6: ='Electricity incl CAAS'!J29-J5-J4 -> 0.99064315 | K6: ='Electricity incl CAAS'!K29-K5-K4 -> 0.89495066 | ... AG6: ='Electricity incl CAAS'!AG29-AG5-AG4 -> 2.791612
A7: Total Charging infra cost Rs./kWh | D7: =SUM(D5:D6) -> 4.4298478 | E7: =SUM(E5:E6) -> 4.3401045 | F7: =SUM(F5:F6) -> 4.1792418 | G7: =SUM(G5:G6) -> 3.910905 | H7: =SUM(H5:H6) -> 3.837091 | I7: =SUM(I5:I6) -> 2.3978469 | J7: =SUM(J5:J6) -> 2.2986752 | K7: =SUM(K5:K6) -> 2.0189157 | ... AG7: =SUM(AG5:AG6) -> 3.6808249
A9: Cost of electricity from DISCOM Rs./kW | C9: 7.5 | D9: =C9*(1+$AH9) -> 7.65 | E9: =D9*(1+$AH9) -> 7.803 | F9: =E9*(1+$AH9) -> 7.95906 | G9: =F9*(1+$AH9) -> 8.1182412 | H9: =G9*(1+$AH9) -> 8.280606 | I9: =H9*(1+$AI9) -> 8.1149939 | J9: =I9*(1+$AI9) -> 7.952694 | K9: =J9*(1+$AI9) -> 7.7936401 | L9: =K9*(1+$AI9) -> 7.6377673 | M9: =L9*(1+$AI9) -> 7.485012 | N9: =M9*(1+$AI9) -> 7.3353118 | O9: =N9*(1+$AI9) -> 7.1886055 | P9: =O9*(1+$AI9) -> 7.0448334 | ... R9: =Q9*(1+$AI9) -> 6.765858 | S9: =R9*(1+$AJ9) -> 6.6981994 | T9: =S9*(1+$AJ9) -> 6.6312174 | U9: =T9*(1+$AJ9) -> 6.5649053 | V9: =U9*(1+$AJ9) -> 6.4992562 | W9: =V9*(1+$AJ9) -> 6.4342636 | X9: =W9*(1+$AJ9) -> 6.369921 | Y9: =X9*(1+$AJ9) -> 6.3062218 | Z9: =Y9*(1+$AJ9) -> 6.2431596 | ... AB9: =AA9*(1+$AJ9) -> 6.1189207 | AC9: =AB9*(1+$AK9) -> 6.2718937 | AD9: =AC9*(1+$AK9) -> 6.4286911 | AE9: =AD9*(1+$AK9) -> 6.5894083 | AF9: =AE9*(1+$AK9) -> 6.7541435 | AG9: =AF9*(1+$AK9) -> 6.9229971 | AH9: ='Electricity incl CAAS'!AH4 -> 0.02 | AI9: ='Electricity incl CAAS'!AI4 -> -0.02 | AJ9: ='Electricity incl CAAS'!AJ4 -> -0.01 | AK9: ='Electricity incl CAAS'!AK4 -> 0.025
A11: Charging mix
A12: By Operator/Shipper | D12: ='Charging trend'!B18+'Charging trend'!B19 -> 0.82 | E12: ='Charging trend'!C18+'Charging trend'!C19 -> 0.7135 | F12: ='Charging trend'!D18+'Charging trend'!D19 -> 0.626 | G12: ='Charging trend'!E18+'Charging trend'!E19 -> 0.5625 | H12: ='Charging trend'!F18+'Charging trend'!F19 -> 0.476 | I12: ='Charging trend'!G18+'Charging trend'!G19 -> 0.425 | J12: ='Charging trend'!H18+'Charging trend'!H19 -> 0.372 | K12: ='Charging trend'!I18+'Charging trend'!I19 -> 0.34 | ... AG12: ='Charging trend'!AE18+'Charging trend'!AE19 -> 0
A13: By CAAS operator | D13: ='Charging trend'!B20 -> 0.18 | E13: ='Charging trend'!C20 -> 0.2865 | F13: ='Charging trend'!D20 -> 0.374 | G13: ='Charging trend'!E20 -> 0.4375 | H13: ='Charging trend'!F20 -> 0.524 | I13: ='Charging trend'!G20 -> 0.575 | J13: ='Charging trend'!H20 -> 0.628 | K13: ='Charging trend'!I20 -> 0.66 | ... AG13: ='Charging trend'!AE20 -> 1
A15: For Operator / Shipper
A16: Electricity purchase cost - Rs./kWh | D16: =D9 -> 7.65 | E16: =E9 -> 7.803 | F16: =F9 -> 7.95906 | G16: =G9 -> 8.1182412 | H16: =H9 -> 8.280606 | I16: =I9 -> 8.1149939 | J16: =J9 -> 7.952694 | K16: =K9 -> 7.7936401 | ... AG16: =AG9 -> 6.9229971
A17: Add on for - Operator/Shipper - Rs./kWh | D17: ='Charge station economics'!B34 -> 2.7841754 | E17: ='Charge station economics'!C34 -> 2.5832636 | F17: ='Charge station economics'!D34 -> 2.4247801 | G17: ='Charge station economics'!E34 -> 2.1604496 | H17: ='Charge station economics'!F34 -> 1.9734787 | I17: ='Charge station economics'!G34 -> 1.3483815 | J17: ='Charge station economics'!H34 -> 1.3805234 | K17: ='Charge station economics'!I34 -> 1.4149151 | ... AG17: ='Charge station economics'!AE34 -> 3.2182851
A18: Cost of charging - Rs./kWh | D18: =D16+D17 -> 10.434175 | E18: =E16+E17 -> 10.386264 | F18: =F16+F17 -> 10.38384 | G18: =G16+G17 -> 10.278691 | H18: =H16+H17 -> 10.254085 | I18: =I16+I17 -> 9.4633755 | J18: =J16+J17 -> 9.3332174 | K18: =K16+K17 -> 9.2085552 | ... AG18: =AG16+AG17 -> 10.141282
A20: For CAS operator
A21: Electricity purchase cost - Rs./kWh | D21: =D9 -> 7.65 | E21: =E9 -> 7.803 | F21: =F9 -> 7.95906 | G21: =G9 -> 8.1182412 | H21: =H9 -> 8.280606 | I21: =I9 -> 8.1149939 | J21: =J9 -> 7.952694 | K21: =K9 -> 7.7936401 | ... AG21: =AG9 -> 6.9229971
A22: Govt Subsidy/DISCOM discount for CAS on energy cost | D22: 0 | E22: 0 | F22: 0 | G22: 0 | H22: 0 | I22: 0 | J22: 0 | K22: 0 | L22: 0 | M22: 0 | N22: 0 | O22: 0 | P22: 0 | Q22: 0 | R22: 0 | S22: 0 | T22: 0 | U22: 0 | V22: 0 | W22: 0 | X22: 0 | Y22: 0 | Z22: 0 | AA22: 0 | AB22: 0 | AC22: 0 | AD22: 0 | AE22: 0 | AF22: 0 | AG22: 0
A23: Less - subsidy/discount for CAS on electricity cost - Rs./kWh | D23: =D21*D22 -> 0 | E23: =E21*E22 -> 0 | F23: =F21*F22 -> 0 | G23: =G21*G22 -> 0 | H23: =H21*H22 -> 0 | I23: =I21*I22 -> 0 | J23: =J21*J22 -> 0 | K23: =K21*K22 -> 0 | ... AG23: =AG21*AG22 -> 0
A24: Add on for - CAAS operator - Rs./kWh | D24: ='Charge station economics'!B50 -> 11.9268 | E24: ='Charge station economics'!C50 -> 8.7153434 | F24: ='Charge station economics'!D50 -> 7.1158543 | G24: ='Charge station economics'!E50 -> 6.1614904 | H24: ='Charge station economics'!F50 -> 5.5299907 | I24: ='Charge station economics'!G50 -> 3.1735387 | J24: ='Charge station economics'!H50 -> 2.8425486 | K24: ='Charge station economics'!I50 -> 2.3300675 | ... AG24: ='Charge station economics'!AE50 -> 3.6808249
A25: Cost of charging - Rs./kWh | D25: =SUM(D21:D24) -> 19.5768 | E25: =SUM(E21:E24) -> 16.518343 | F25: =SUM(F21:F24) -> 15.074914 | G25: =SUM(G21:G24) -> 14.279732 | H25: =SUM(H21:H24) -> 13.810597 | I25: =SUM(I21:I24) -> 11.288533 | J25: =SUM(J21:J24) -> 10.795243 | K25: =SUM(K21:K24) -> 10.123708 | ... AG25: =SUM(AG21:AG24) -> 10.603822
A27: Extra for CAS charging over captive charging | D27: =D25/D18-1 -> 0.87621917 | E27: =E25/E18-1 -> 0.59040287 | F27: =F25/F18-1 -> 0.4517668 | G27: =G25/G18-1 -> 0.38925588 | H27: =H25/H18-1 -> 0.34683855 | I27: =I25/I18-1 -> 0.19286534 | J27: =J25/J18-1 -> 0.15664751 | K27: =K25/K18-1 -> 0.09938067 | ... AG27: =AG25/AG18-1 -> 0.045609596
A29: Weighted average energy cost to truck operator Rs./kWhr | D29: =D18*D12+D25*D13 -> 12.079848 | E29: =E18*E12+E25*E13 -> 12.143104 | F29: =F18*F12+F25*F13 -> 12.138302 | G29: =G18*G12+G25*G13 -> 12.029146 | H29: =H18*H12+H25*H13 -> 12.117697 | I29: =I18*I12+I25*I13 -> 10.512841 | J29: =J18*J12+J25*J13 -> 10.251369 | K29: =K18*K12+K25*K13 -> 9.8125558 | ... AG29: =AG18*AG12+AG25*AG13 -> 10.603822
A31: Note - End price charged by CAS operator
A32: Add GST @ 18% (not considered as cost due to input credit) | D32: =D25*0.18 -> 3.523824 | E32: =E25*0.18 -> 2.9733018 | F32: =F25*0.18 -> 2.7134846 | G32: =G25*0.18 -> 2.5703517 | H32: =H25*0.18 -> 2.4859074 | I32: =I25*0.18 -> 2.0319359 | J32: =J25*0.18 -> 1.9431437 | K32: =K25*0.18 -> 1.8222674 | ... AG32: =AG25*0.18 -> 1.908688
A33: Price payable by truck operator | D33: =D32+D25 -> 23.100624 | E33: =E32+E25 -> 19.491645 | F33: =F32+F25 -> 17.788399 | G33: =G32+G25 -> 16.850083 | H33: =H32+H25 -> 16.296504 | I33: =I32+I25 -> 13.320468 | J33: =J32+J25 -> 12.738386 | K33: =K32+K25 -> 11.945975 | ... AG33: =AG32+AG25 -> 12.51251
A36: Assumptions | AG36: Power tariff assumption :
AD37: 2026-30 | AF37: Renewable still smaller portion of overall energy mix - hence increasing
A38: Currently CAS operators main challenge is low capacity utilisation (~10%) which leads to high cost unit kW | AD38: 2031-40 | AF38: RE Power peaks in this decade. Energy prices dropping continously
A39: This is mainly due to high share of closed loop operation, where charging infra is with shippers now | AD39: 2041-50 | AF39: RE price continues to drop - albeit slowly.
A40: Around 80% of M&HDV truck operation is point to point, which will call for enroute charging | AD40: 2051-55 | AF40: Electricity prices increase due to government levies imposed (to compensate diesel revenue loss)
A41: Hence shift to public charging infra is inevitable in long run.
A42: We foresee capacity utilisation for CAS operators to reach parity with captive chargers by 2035
A43: This, coupled with incentives/bulk discounts likely from DISCOMs / government incentives to CAS operators expected to reduce cost significantly
AH46: 0 | AI46: -0.04 | AJ46: -0.02 | AK46: -0.01
AH47: 0 | AI47: 0 | AJ47: 0.01 | AK47: 0.01 | AM47: Increasing capacity utilisation may keep land cost down initially
AH48: -0.05 | AI48: -0.02 | AJ48: 0.02 | AK48: 0.02
AH49: -0.05 | AI49: -0.02 | AJ49: 0.02 | AK49: 0.02
AL50: 0 | AM50: Energy Subsidy per kWh till 2040 | AN50: 2056 | AO50: 2057 | AP50: 2063 | AQ50: 2064 | AR50: 2065

Sheet AnnualSalesSummary Revised
B1: Annual Sales Projections - Applicationwise & Segmentwise: | AK1: Share of TIV
B2: Year | C2: 2023 | D2: 2024 | E2: 2025 | F2: 2026 | G2: 2027 | H2: 2028 | I2: 2029 | J2: 2030 | K2: 2031 | L2: 2032 | M2: 2033 | N2: 2034 | O2: 2035 | P2: 2036 | Q2: 2037 | R2: 2038 | S2: 2039 | T2: 2040 | U2: 2041 | V2: 2042 | W2: 2043 | X2: 2044 | Y2: 2045 | Z2: 2046 | AA2: 2047 | AB2: 2048 | AC2: 2049 | AD2: 2050 | AE2: 2051 | AF2: 2052 | AG2: 2053 | AH2: 2054 | AI2: 2055 | AK2: Overall | AL2: 2045 | AM2: 2055
A3: 1 | B3: Market Load Total | C3: 80476.835 | D3: =SUM(D4:D10) -> 62420 | E3: =SUM(E4:E10) -> 53050 | F3: =SUM(F4:F10) -> 67561.099 | G3: =SUM(G4:G10) -> 61680 | H3: =SUM(H4:H10) -> 62290 | I3: =SUM(I4:I10) -> 69750 | J3: =SUM(J4:J10) -> 72530 | K3: =SUM(K4:K10) -> 72530 | ... AI3: =SUM(AI4:AI10) -> 170140 | AK3: =SUM(D3:AI3)/SUM($D$75:$AI$75)% -> 18.930114 | AL3: =Y3/Y$75 -> 0.18119477 | AM3: =AI3/AI$75 -> 0.16521173 | AN3: =Y75*(AL4+AL5+AL6) -> 90420
B4: Rigid|12T - 19T | D4: 22640 | E4: 19240 | F4: 37887.652 | G4: 22370 | H4: 22590 | I4: 25300 | J4: 26310 | K4: 26310 | L4: 30260 | M4: 32980 | N4: 33970 | O4: 36690 | P4: 38160 | Q4: 39300 | R4: 40090 | S4: 40090 | T4: 40490 | U4: 41700 | V4: 42950 | W4: 43810 | X4: 45120 | Y4: 46470 | Z4: 47860 | AA4: 49300 | AB4: 49300 | AC4: 50290 | AD4: 54310 | AE4: 57030 | AF4: 59310 | AG4: 60500 | AH4: 61710 | AI4: 61710 | AK4: =SUM(D4:AI4)/SUM($D$75:$AI$75)% -> 6.9366349 | AL4: =Y4/Y$75 -> 0.065705196 | AM4: =AI4/AI$75 -> 0.059922511 | AN4: =Y75*(AL7+AL8+AL9+AL10) -> 37730
B5: Rigid|19T - 28.5T | D5: 19290 | E5: 16400 | F5: 11460.314 | G5: 19070 | H5: 19260 | I5: 21570 | J5: 22430 | K5: 22430 | L5: 25790 | M5: 28110 | N5: 28950 | O5: 31270 | P5: 32520 | Q5: 33500 | R5: 34170 | S5: 34170 | T5: 34510 | U5: 35550 | V5: 36620 | W5: 37350 | X5: 38470 | Y5: 39620 | Z5: 40810 | AA5: 42030 | AB5: 42030 | AC5: 42870 | AD5: 46300 | AE5: 48620 | AF5: 50560 | AG5: 51570 | AH5: 52600 | AI5: 52600 | AK5: =SUM(D5:AI5)/SUM($D$75:$AI$75)% -> 5.8024497 | AL5: =Y5/Y$75 -> 0.056019795 | AM5: =AI5/AI$75 -> 0.051076391
B6: Rigid|28.5T - 40T | D6: 2120 | E6: 1800 | F6: 2054.7985 | G6: 2090 | H6: 2110 | I6: 2360 | J6: 2450 | K6: 2450 | L6: 2820 | M6: 3070 | N6: 3160 | O6: 3410 | P6: 3550 | Q6: 3660 | R6: 3730 | S6: 3730 | T6: 3770 | U6: 3880 | V6: 4000 | W6: 4080 | X6: 4200 | Y6: 4330 | Z6: 4460 | AA6: 4590 | AB6: 4590 | AC6: 4680 | AD6: 5050 | AE6: 5300 | AF6: 5510 | AG6: 5620 | AH6: 5730 | AI6: 5730 | AK6: =SUM(D6:AI6)/SUM($D$75:$AI$75)% -> 0.63779021 | AL6: =Y6/Y$75 -> 0.0061223047 | AM6: =AI6/AI$75 -> 0.0055640251
B7: Rigid|>40T | D7: 12720 | E7: 10810 | F7: 10464.16 | G7: 12570 | H7: 12700 | I7: 14220 | J7: 14790 | K7: 14790 | L7: 17010 | M7: 18540 | N7: 19100 | O7: 20630 | P7: 21460 | Q7: 22100 | R7: 22540 | S7: 22540 | T7: 22770 | U7: 23450 | V7: 24150 | W7: 24630 | X7: 25370 | Y7: 26130 | Z7: 26910 | AA7: 27720 | AB7: 27720 | AC7: 28270 | AD7: 30530 | AE7: 32060 | AF7: 33340 | AG7: 34010 | AH7: 34690 | AI7: 34690 | AK7: =SUM(D7:AI7)/SUM($D$75:$AI$75)% -> 3.8422253 | AL7: =Y7/Y$75 -> 0.036945917 | AM7: =AI7/AI$75 -> 0.033685171
B8: TT | 31T - 40T | D8: 0 | E8: 0 | F8: 0 | G8: 0 | H8: 0 | I8: 0 | J8: 0 | K8: 0 | L8: 0 | M8: 0 | N8: 0 | O8: 0 | P8: 0 | Q8: 0 | R8: 0 | S8: 0 | T8: 0 | U8: 0 | V8: 0 | W8: 0 | X8: 0 | Y8: 0 | Z8: 0 | AA8: 0 | AB8: 0 | AC8: 0 | AD8: 0 | AE8: 0 | AF8: 0 | AG8: 0 | AH8: 0 | AI8: 0 | AK8: =SUM(D8:AI8)/SUM($D$75:$AI$75)% -> 0 | AL8: =Y8/Y$75 -> 0 | AM8: =AI8/AI$75 -> 0
B9: TT | 40 T - 46T | D9: 440 | E9: 370 | F9: 264.28841 | G9: 430 | H9: 430 | I9: 480 | J9: 500 | K9: 500 | L9: 580 | M9: 630 | N9: 650 | O9: 700 | P9: 730 | Q9: 750 | R9: 770 | S9: 770 | T9: 780 | U9: 800 | V9: 820 | W9: 840 | X9: 870 | Y9: 900 | Z9: 930 | AA9: 960 | AB9: 960 | AC9: 980 | AD9: 1060 | AE9: 1110 | AF9: 1150 | AG9: 1170 | AH9: 1190 | AI9: 1190 | AK9: =SUM(D9:AI9)/SUM($D$75:$AI$75)% -> 0.13120856 | AL9: =Y9/Y$75 -> 0.0012725345 | AM9: =AI9/AI$75 -> 0.0011555305
B10: TT | 46T - 55T | D10: 5210 | E10: 4430 | F10: 5429.8863 | G10: 5150 | H10: 5200 | I10: 5820 | J10: 6050 | K10: 6050 | L10: 6960 | M10: 7590 | N10: 7820 | O10: 8450 | P10: 8790 | Q10: 9050 | R10: 9230 | S10: 9230 | T10: 9320 | U10: 9600 | V10: 9890 | W10: 10090 | X10: 10390 | Y10: 10700 | Z10: 11020 | AA10: 11350 | AB10: 11350 | AC10: 11580 | AD10: 12510 | AE10: 13140 | AF10: 13670 | AG10: 13940 | AH10: 14220 | AI10: 14220 | AK10: =SUM(D10:AI10)/SUM($D$75:$AI$75)% -> 1.5798055 | AL10: =Y10/Y$75 -> 0.015129021 | AM10: =AI10/AI$75 -> 0.013808104
A11: 2 | B11: Parcel Load, FMCG & eCommerce | C11: 68588.245 | D11: =SUM(D12:D18) -> 33250 | E11: =SUM(E12:E18) -> 29920 | F11: =SUM(F12:F18) -> 37913.029 | G11: =SUM(G12:G18) -> 36500 | H11: =SUM(H12:H18) -> 37230 | I11: =SUM(I12:I18) -> 41700 | J11: =SUM(J12:J18) -> 43380 | K11: =SUM(K12:K18) -> 45560 | ... AI11: =SUM(AI12:AI18) -> 177720 | AK11: =SUM(D11:AI11)/SUM($D$75:$AI$75)% -> 15.677939 | AL11: =Y11/Y$75 -> 0.16533051 | AM11: =AI11/AI$75 -> 0.17257217
B12: Rigid|12T - 19T | D12: 10160 | E12: 9140 | F12: 18002.593 | G12: 11150 | H12: 11370 | I12: 12730 | J12: 13240 | K12: 13900 | L12: 15990 | M12: 17430 | N12: 17950 | O12: 19210 | P12: 20360 | Q12: 21580 | R12: 22870 | S12: 25160 | T12: 26920 | U12: 29070 | V12: 30810 | W12: 32660 | X12: 34290 | Y12: 35660 | Z12: 37090 | AA12: 38570 | AB12: 39340 | AC12: 40910 | AD12: 45000 | AE12: 47250 | AF12: 49610 | AG12: 51590 | AH12: 53650 | AI12: 54190 | AK12: =SUM(D12:AI12)/SUM($D$75:$AI$75)% -> 4.816444 | AL12: =Y12/Y$75 -> 0.050420643 | AM12: =AI12/AI$75 -> 0.052620335
B13: Rigid|19T - 28.5T | D13: 8120 | E13: 7310 | F13: 5107.5736 | G13: 8910 | H13: 9090 | I13: 10180 | J13: 10590 | K13: 11120 | L13: 12790 | M13: 13940 | N13: 14360 | O13: 15370 | P13: 16290 | Q13: 17270 | R13: 18310 | S13: 20140 | T13: 21550 | U13: 23270 | V13: 24670 | W13: 26150 | X13: 27460 | Y13: 28560 | Z13: 29700 | AA13: 30890 | AB13: 31510 | AC13: 32770 | AD13: 36050 | AE13: 37850 | AF13: 39740 | AG13: 41330 | AH13: 42980 | AI13: 43410 | AK13: =SUM(D13:AI13)/SUM($D$75:$AI$75)% -> 3.8069772 | AL13: =Y13/Y$75 -> 0.04038176 | AM13: =AI13/AI$75 -> 0.042152588
B14: Rigid|28.5T - 40T | D14: 1770 | E14: 1590 | F14: 1816.706 | G14: 1940 | H14: 1980 | I14: 2220 | J14: 2310 | K14: 2430 | L14: 2790 | M14: 3040 | N14: 3130 | O14: 3350 | P14: 3550 | Q14: 3760 | R14: 3990 | S14: 4390 | T14: 4700 | U14: 5080 | V14: 5380 | W14: 5700 | X14: 5990 | Y14: 6230 | Z14: 6480 | AA14: 6740 | AB14: 6870 | AC14: 7140 | AD14: 7850 | AE14: 8240 | AF14: 8650 | AG14: 9000 | AH14: 9360 | AI14: 9450 | AK14: =SUM(D14:AI14)/SUM($D$75:$AI$75)% -> 0.83341055 | AL14: =Y14/Y$75 -> 0.0088087663 | AM14: =AI14/AI$75 -> 0.0091762718
B15: Rigid|>40T | D15: 5300 | E15: 4770 | F15: 4616.5913 | G15: 5820 | H15: 5940 | I15: 6650 | J15: 6920 | K15: 7270 | L15: 8360 | M15: 9110 | N15: 9380 | O15: 10040 | P15: 10640 | Q15: 11280 | R15: 11960 | S15: 13160 | T15: 14080 | U15: 15210 | V15: 16120 | W15: 17090 | X15: 17940 | Y15: 18660 | Z15: 19410 | AA15: 20190 | AB15: 20590 | AC15: 21410 | AD15: 23550 | AE15: 24730 | AF15: 25970 | AG15: 27010 | AH15: 28090 | AI15: 28370 | AK15: =SUM(D15:AI15)/SUM($D$75:$AI$75)% -> 2.4943175 | AL15: =Y15/Y$75 -> 0.026383881 | AM15: =AI15/AI$75 -> 0.027548236
B16: TT | 31T - 40T | D16: 4590 | E16: 4130 | F16: 6262.7032 | G16: 5040 | H16: 5140 | I16: 5760 | J16: 5990 | K16: 6290 | L16: 7230 | M16: 7880 | N16: 8120 | O16: 8690 | P16: 9210 | Q16: 9760 | R16: 10350 | S16: 11390 | T16: 12190 | U16: 13170 | V16: 13960 | W16: 14800 | X16: 15540 | Y16: 16160 | Z16: 16810 | AA16: 17480 | AB16: 17830 | AC16: 18540 | AD16: 20390 | AE16: 21410 | AF16: 22480 | AG16: 23380 | AH16: 24320 | AI16: 24560 | AK16: =SUM(D16:AI16)/SUM($D$75:$AI$75)% -> 2.1714843 | AL16: =Y16/Y$75 -> 0.022849063 | AM16: =AI16/AI$75 -> 0.023848596
B17: TT | 40 T - 46T | D17: 3310 | E17: 2980 | F17: 2106.8625 | G17: 3640 | H17: 3710 | I17: 4160 | J17: 4330 | K17: 4550 | L17: 5230 | M17: 5700 | N17: 5870 | O17: 6280 | P17: 6660 | Q17: 7060 | R17: 7480 | S17: 8230 | T17: 8810 | U17: 9510 | V17: 10080 | W17: 10680 | X17: 11210 | Y17: 11660 | Z17: 12130 | AA17: 12620 | AB17: 12870 | AC17: 13380 | AD17: 14720 | AE17: 15460 | AF17: 16230 | AG17: 16880 | AH17: 17560 | AI17: 17740 | AK17: =SUM(D17:AI17)/SUM($D$75:$AI$75)% -> 1.555305 | AL17: =Y17/Y$75 -> 0.016486391 | AM17: =AI17/AI$75 -> 0.017226144
B18: TT | 46T - 55T | D18: 0 | E18: 0 | F18: 0 | G18: 0 | H18: 0 | I18: 0 | J18: 0 | K18: 0 | L18: 0 | M18: 0 | N18: 0 | O18: 0 | P18: 0 | Q18: 0 | R18: 0 | S18: 0 | T18: 0 | U18: 0 | V18: 0 | W18: 0 | X18: 0 | Y18: 0 | Z18: 0 | AA18: 0 | AB18: 0 | AC18: 0 | AD18: 0 | AE18: 0 | AF18: 0 | AG18: 0 | AH18: 0 | AI18: 0 | AK18: =SUM(D18:AI18)/SUM($D$75:$AI$75)% -> 0 | AL18: =Y18/Y$75 -> 0 | AM18: =AI18/AI$75 -> 0
A19: 3 | B19: Perishables & Fish Total | C19: 18909 | D19: =SUM(D20:D26) -> 18510 | E19: =SUM(E20:E26) -> 16670 | F19: =SUM(F20:F26) -> 23532.149 | G19: =SUM(G20:G26) -> 19270 | H19: =SUM(H20:H26) -> 19450 | I19: =SUM(I20:I26) -> 20620 | J19: =SUM(J20:J26) -> 21030 | K19: =SUM(K20:K26) -> 22090 | ... AI19: =SUM(AI20:AI26) -> 75210 | AK19: =SUM(D19:AI19)/SUM($D$75:$AI$75)% -> 6.7998432 | AL19: =Y19/Y$75 -> 0.069876281 | AM19: =AI19/AI$75 -> 0.073031471
B20: Rigid|12T - 19T | D20: 9850 | E20: 8870 | F20: 16842.027 | G20: 10250 | H20: 10350 | I20: 10970 | J20: 11190 | K20: 11750 | L20: 12690 | M20: 13320 | N20: 13990 | O20: 14830 | P20: 15720 | Q20: 16660 | R20: 17160 | S20: 18190 | T20: 19460 | U20: 21210 | V20: 23120 | W20: 24040 | X20: 25240 | Y20: 26250 | Z20: 27830 | AA20: 29220 | AB20: 29800 | AC20: 30690 | AD20: 32530 | AE20: 33510 | AF20: 34850 | AG20: 36590 | AH20: 37690 | AI20: 39950 | AK20: =SUM(D20:AI20)/SUM($D$75:$AI$75)% -> 3.6360876 | AL20: =Y20/Y$75 -> 0.037115589 | AM20: =AI20/AI$75 -> 0.03879281
B21: Rigid|19T - 28.5T | D21: 2210 | E21: 1990 | F21: 1341.4201 | G21: 2300 | H21: 2320 | I21: 2460 | J21: 2510 | K21: 2640 | L21: 2850 | M21: 2990 | N21: 3140 | O21: 3330 | P21: 3530 | Q21: 3740 | R21: 3850 | S21: 4080 | T21: 4370 | U21: 4760 | V21: 5190 | W21: 5400 | X21: 5670 | Y21: 5900 | Z21: 6250 | AA21: 6560 | AB21: 6690 | AC21: 6890 | AD21: 7300 | AE21: 7520 | AF21: 7820 | AG21: 8210 | AH21: 8460 | AI21: 8970 | AK21: =SUM(D21:AI21)/SUM($D$75:$AI$75)% -> 0.80326817 | AL21: =Y21/Y$75 -> 0.0083421704 | AM21: =AI21/AI$75 -> 0.0087101755
B22: Rigid|28.5T - 40T | D22: 180 | E22: 160 | F22: 178.0692 | G22: 190 | H22: 190 | I22: 200 | J22: 200 | K22: 210 | L22: 230 | M22: 240 | N22: 250 | O22: 270 | P22: 290 | Q22: 310 | R22: 320 | S22: 340 | T22: 360 | U22: 390 | V22: 430 | W22: 450 | X22: 470 | Y22: 490 | Z22: 520 | AA22: 550 | AB22: 560 | AC22: 580 | AD22: 610 | AE22: 630 | AF22: 660 | AG22: 690 | AH22: 710 | AI22: 750 | AK22: =SUM(D22:AI22)/SUM($D$75:$AI$75)% -> 0.066963539 | AL22: =Y22/Y$75 -> 0.00069282432 | AM22: =AI22/AI$75 -> 0.00072827554
B23: Rigid|>40T | D23: 5830 | E23: 5250 | F23: 4900.1407 | G23: 6070 | H23: 6130 | I23: 6500 | J23: 6630 | K23: 6960 | L23: 7520 | M23: 7900 | N23: 8300 | O23: 8800 | P23: 9330 | Q23: 9890 | R23: 10190 | S23: 10800 | T23: 11560 | U23: 12600 | V23: 13730 | W23: 14280 | X23: 14990 | Y23: 15590 | Z23: 16530 | AA23: 17360 | AB23: 17710 | AC23: 18240 | AD23: 19330 | AE23: 19910 | AF23: 20710 | AG23: 21750 | AH23: 22400 | AI23: 23740 | AK23: =SUM(D23:AI23)/SUM($D$75:$AI$75)% -> 2.1320618 | AL23: =Y23/Y$75 -> 0.022043125 | AM23: =AI23/AI$75 -> 0.023052348
B24: TT | 31T - 40T | D24: 0 | E24: 0 | F24: 0 | G24: 0 | H24: 0 | I24: 0 | J24: 0 | K24: 0 | L24: 0 | M24: 0 | N24: 0 | O24: 0 | P24: 0 | Q24: 0 | R24: 0 | S24: 0 | T24: 0 | U24: 0 | V24: 0 | W24: 0 | X24: 0 | Y24: 0 | Z24: 0 | AA24: 0 | AB24: 0 | AC24: 0 | AD24: 0 | AE24: 0 | AF24: 0 | AG24: 0 | AH24: 0 | AI24: 0 | AK24: =SUM(D24:AI24)/SUM($D$75:$AI$75)% -> 0 | AL24: =Y24/Y$75 -> 0 | AM24: =AI24/AI$75 -> 0
B25: TT | 40 T - 46T | D25: 440 | E25: 400 | F25: 270.49236 | G25: 460 | H25: 460 | I25: 490 | J25: 500 | K25: 530 | L25: 570 | M25: 600 | N25: 630 | O25: 670 | P25: 710 | Q25: 750 | R25: 770 | S25: 820 | T25: 880 | U25: 960 | V25: 1050 | W25: 1090 | X25: 1140 | Y25: 1190 | Z25: 1260 | AA25: 1320 | AB25: 1350 | AC25: 1390 | AD25: 1470 | AE25: 1510 | AF25: 1570 | AG25: 1650 | AH25: 1700 | AI25: 1800 | AK25: =SUM(D25:AI25)/SUM($D$75:$AI$75)% -> 0.16146204 | AL25: =Y25/Y$75 -> 0.0016825733 | AM25: =AI25/AI$75 -> 0.0017478613
B26: TT | 46T - 55T | D26: 0 | E26: 0 | F26: 0 | G26: 0 | H26: 0 | I26: 0 | J26: 0 | K26: 0 | L26: 0 | M26: 0 | N26: 0 | O26: 0 | P26: 0 | Q26: 0 | R26: 0 | S26: 0 | T26: 0 | U26: 0 | V26: 0 | W26: 0 | X26: 0 | Y26: 0 | Z26: 0 | AA26: 0 | AB26: 0 | AC26: 0 | AD26: 0 | AE26: 0 | AF26: 0 | AG26: 0 | AH26: 0 | AI26: 0 | AK26: =SUM(D26:AI26)/SUM($D$75:$AI$75)% -> 0 | AL26: =Y26/Y$75 -> 0 | AM26: =AI26/AI$75 -> 0
A27: 4 | B27: Constructin & Mining | C27: 5870.7951 | D27: =SUM(D28:D34) -> 85620 | E27: =SUM(E28:E34) -> 87330 | F27: =SUM(F28:F34) -> 83974.96 | G27: =SUM(G28:G34) -> 99030 | H27: =SUM(H28:H34) -> 101000 | I27: =SUM(I28:I34) -> 108080 | J27: =SUM(J28:J34) -> 110250 | K27: =SUM(K28:K34) -> 115770 | ... AI27: =SUM(AI28:AI34) -> 299130 | AK27: =SUM(D27:AI27)/SUM($D$75:$AI$75)% -> 29.864762 | AL27: =Y27/Y$75 -> 0.29712266 | AM27: =AI27/AI$75 -> 0.29046542
B28: Rigid|12T - 19T | D28: 5390 | E28: 5500 | F28: 10255.122 | G28: 6240 | H28: 6360 | I28: 6810 | J28: 6950 | K28: 7300 | L28: 7880 | M28: 8270 | N28: 8600 | O28: 8940 | P28: 9210 | Q28: 9580 | R28: 9960 | S28: 10360 | T28: 10770 | U28: 11200 | V28: 11650 | W28: 12120 | X28: 12600 | Y28: 13230 | Z28: 13760 | AA28: 14310 | AB28: 14600 | AC28: 14890 | AD28: 15630 | AE28: 16100 | AF28: 16580 | AG28: 17240 | AH28: 17930 | AI28: 18830 | AK28: =SUM(D28:AI28)/SUM($D$75:$AI$75)% -> 1.906948 | AL28: =Y28/Y$75 -> 0.018706257 | AM28: =AI28/AI$75 -> 0.018284571
B29: Rigid|19T - 28.5T | D29: 29580 | E29: 30170 | F29: 19977.841 | G29: 34210 | H29: 34890 | I29: 37330 | J29: 38080 | K29: 39980 | L29: 43180 | M29: 45340 | N29: 47150 | O29: 49040 | P29: 50510 | Q29: 52530 | R29: 54630 | S29: 56820 | T29: 59090 | U29: 61450 | V29: 63910 | W29: 66470 | X29: 69130 | Y29: 72590 | Z29: 75490 | AA29: 78510 | AB29: 80080 | AC29: 81680 | AD29: 85760 | AE29: 88330 | AF29: 90980 | AG29: 94620 | AH29: 98400 | AI29: 103320 | AK29: =SUM(D29:AI29)/SUM($D$75:$AI$75)% -> 10.267693 | AL29: =Y29/Y$75 -> 0.10263697 | AM29: =AI29/AI$75 -> 0.10032724
B30: Rigid|28.5T - 40T | D30: 18720 | E30: 19090 | F30: 20630.017 | G30: 21650 | H30: 22080 | I30: 23630 | J30: 24100 | K30: 25310 | L30: 27330 | M30: 28700 | N30: 29850 | O30: 31040 | P30: 31970 | Q30: 33250 | R30: 34580 | S30: 35960 | T30: 37400 | U30: 38900 | V30: 40460 | W30: 42080 | X30: 43760 | Y30: 45950 | Z30: 47790 | AA30: 49700 | AB30: 50690 | AC30: 51700 | AD30: 54290 | AE30: 55920 | AF30: 57600 | AG30: 59900 | AH30: 62300 | AI30: 65420 | AK30: =SUM(D30:AI30)/SUM($D$75:$AI$75)% -> 6.5420279 | AL30: =Y30/Y$75 -> 0.064969954 | AM30: =AI30/AI$75 -> 0.063525048
B31: Rigid|>40T | D31: 18900 | E31: 19280 | F31: 17675.144 | G31: 21860 | H31: 22300 | I31: 23860 | J31: 24340 | K31: 25560 | L31: 27600 | M31: 28980 | N31: 30140 | O31: 31350 | P31: 32290 | Q31: 33580 | R31: 34920 | S31: 36320 | T31: 37770 | U31: 39280 | V31: 40850 | W31: 42480 | X31: 44180 | Y31: 46390 | Z31: 48250 | AA31: 50180 | AB31: 51180 | AC31: 52200 | AD31: 54810 | AE31: 56450 | AF31: 58140 | AG31: 60470 | AH31: 62890 | AI31: 66030 | AK31: =SUM(D31:AI31)/SUM($D$75:$AI$75)% -> 6.5885278 | AL31: =Y31/Y$75 -> 0.065592082 | AM31: =AI31/AI$75 -> 0.064117379
B32: TT | 31T - 40T | D32: 0 | E32: 0 | F32: 0 | G32: 0 | H32: 0 | I32: 0 | J32: 0 | K32: 0 | L32: 0 | M32: 0 | N32: 0 | O32: 0 | P32: 0 | Q32: 0 | R32: 0 | S32: 0 | T32: 0 | U32: 0 | V32: 0 | W32: 0 | X32: 0 | Y32: 0 | Z32: 0 | AA32: 0 | AB32: 0 | AC32: 0 | AD32: 0 | AE32: 0 | AF32: 0 | AG32: 0 | AH32: 0 | AI32: 0 | AK32: =SUM(D32:AI32)/SUM($D$75:$AI$75)% -> 0 | AL32: =Y32/Y$75 -> 0 | AM32: =AI32/AI$75 -> 0
B33: TT | 40 T - 46T | D33: 0 | E33: 0 | F33: 0 | G33: 0 | H33: 0 | I33: 0 | J33: 0 | K33: 0 | L33: 0 | M33: 0 | N33: 0 | O33: 0 | P33: 0 | Q33: 0 | R33: 0 | S33: 0 | T33: 0 | U33: 0 | V33: 0 | W33: 0 | X33: 0 | Y33: 0 | Z33: 0 | AA33: 0 | AB33: 0 | AC33: 0 | AD33: 0 | AE33: 0 | AF33: 0 | AG33: 0 | AH33: 0 | AI33: 0 | AK33: =SUM(D33:AI33)/SUM($D$75:$AI$75)% -> 0 | AL33: =Y33/Y$75 -> 0 | AM33: =AI33/AI$75 -> 0
B34: TT | 46T - 55T | D34: 13030 | E34: 13290 | F34: 15436.836 | G34: 15070 | H34: 15370 | I34: 16450 | J34: 16780 | K34: 17620 | L34: 19030 | M34: 19980 | N34: 20780 | O34: 21610 | P34: 22260 | Q34: 23150 | R34: 24080 | S34: 25040 | T34: 26040 | U34: 27080 | V34: 28160 | W34: 29290 | X34: 30460 | Y34: 31980 | Z34: 33260 | AA34: 34590 | AB34: 35280 | AC34: 35990 | AD34: 37790 | AE34: 38920 | AF34: 40090 | AG34: 41690 | AH34: 43360 | AI34: 45530 | AK34: =SUM(D34:AI34)/SUM($D$75:$AI$75)% -> 4.5595654 | AL34: =Y34/Y$75 -> 0.045217391 | AM34: =AI34/AI$75 -> 0.04421118
A35: 5 | B35: Steel & Metal Products Total | C35: 29982.99 | D35: =SUM(D36:D42) -> 19780 | E35: =SUM(E36:E42) -> 19980 | F35: =SUM(F36:F42) -> 23706.62 | G35: =SUM(G36:G42) -> 22450 | H35: =SUM(H36:H42) -> 22670 | I35: =SUM(I36:I42) -> 25390 | J35: =SUM(J36:J42) -> 25900 | K35: =SUM(K36:K42) -> 27710 | ... AI35: =SUM(AI36:AI42) -> 122850 | AK35: =SUM(D35:AI35)/SUM($D$75:$AI$75)% -> 9.551263 | AL35: =Y35/Y$75 -> 0.09708024 | AM35: =AI35/AI$75 -> 0.11929153
B36: Rigid|12T - 19T | D36: 1020 | E36: 1030 | F36: 1903.1905 | G36: 1160 | H36: 1170 | I36: 1310 | J36: 1340 | K36: 1430 | L36: 1590 | M36: 1700 | N36: 1750 | O36: 1860 | P36: 2050 | Q36: 2190 | R36: 2320 | S36: 2480 | T36: 2680 | U36: 2870 | V36: 3070 | W36: 3280 | X36: 3410 | Y36: 3550 | Z36: 3690 | AA36: 3840 | AB36: 4030 | AC36: 4310 | AD36: 4650 | AE36: 4930 | AF36: 5230 | AG36: 5540 | AH36: 5870 | AI36: 6340 | AK36: =SUM(D36:AI36)/SUM($D$75:$AI$75)% -> 0.4970889 | AL36: =Y36/Y$75 -> 0.0050194415 | AM36: =AI36/AI$75 -> 0.0061563559
B37: Rigid|19T - 28.5T | D37: 0 | E37: 0 | F37: 0 | G37: 0 | H37: 0 | I37: 0 | J37: 0 | K37: 0 | L37: 0 | M37: 0 | N37: 0 | O37: 0 | P37: 0 | Q37: 0 | R37: 0 | S37: 0 | T37: 0 | U37: 0 | V37: 0 | W37: 0 | X37: 0 | Y37: 0 | Z37: 0 | AA37: 0 | AB37: 0 | AC37: 0 | AD37: 0 | AE37: 0 | AF37: 0 | AG37: 0 | AH37: 0 | AI37: 0 | AK37: =SUM(D37:AI37)/SUM($D$75:$AI$75)% -> 0 | AL37: =Y37/Y$75 -> 0 | AM37: =AI37/AI$75 -> 0
B38: Rigid|28.5T - 40T | D38: 0 | E38: 0 | F38: 0 | G38: 0 | H38: 0 | I38: 0 | J38: 0 | K38: 0 | L38: 0 | M38: 0 | N38: 0 | O38: 0 | P38: 0 | Q38: 0 | R38: 0 | S38: 0 | T38: 0 | U38: 0 | V38: 0 | W38: 0 | X38: 0 | Y38: 0 | Z38: 0 | AA38: 0 | AB38: 0 | AC38: 0 | AD38: 0 | AE38: 0 | AF38: 0 | AG38: 0 | AH38: 0 | AI38: 0 | AK38: =SUM(D38:AI38)/SUM($D$75:$AI$75)% -> 0 | AL38: =Y38/Y$75 -> 0 | AM38: =AI38/AI$75 -> 0
B39: Rigid|>40T | D39: 0 | E39: 0 | F39: 0 | G39: 0 | H39: 0 | I39: 0 | J39: 0 | K39: 0 | L39: 0 | M39: 0 | N39: 0 | O39: 0 | P39: 0 | Q39: 0 | R39: 0 | S39: 0 | T39: 0 | U39: 0 | V39: 0 | W39: 0 | X39: 0 | Y39: 0 | Z39: 0 | AA39: 0 | AB39: 0 | AC39: 0 | AD39: 0 | AE39: 0 | AF39: 0 | AG39: 0 | AH39: 0 | AI39: 0 | AK39: =SUM(D39:AI39)/SUM($D$75:$AI$75)% -> 0 | AL39: =Y39/Y$75 -> 0 | AM39: =AI39/AI$75 -> 0
B40: TT | 31T - 40T | D40: 0 | E40: 0 | F40: 0 | G40: 0 | H40: 0 | I40: 0 | J40: 0 | K40: 0 | L40: 0 | M40: 0 | N40: 0 | O40: 0 | P40: 0 | Q40: 0 | R40: 0 | S40: 0 | T40: 0 | U40: 0 | V40: 0 | W40: 0 | X40: 0 | Y40: 0 | Z40: 0 | AA40: 0 | AB40: 0 | AC40: 0 | AD40: 0 | AE40: 0 | AF40: 0 | AG40: 0 | AH40: 0 | AI40: 0 | AK40: =SUM(D40:AI40)/SUM($D$75:$AI$75)% -> 0 | AL40: =Y40/Y$75 -> 0 | AM40: =AI40/AI$75 -> 0
B41: TT | 40 T - 46T | D41: 0 | E41: 0 | F41: 0 | G41: 0 | H41: 0 | I41: 0 | J41: 0 | K41: 0 | L41: 0 | M41: 0 | N41: 0 | O41: 0 | P41: 0 | Q41: 0 | R41: 0 | S41: 0 | T41: 0 | U41: 0 | V41: 0 | W41: 0 | X41: 0 | Y41: 0 | Z41: 0 | AA41: 0 | AB41: 0 | AC41: 0 | AD41: 0 | AE41: 0 | AF41: 0 | AG41: 0 | AH41: 0 | AI41: 0 | AK41: =SUM(D41:AI41)/SUM($D$75:$AI$75)% -> 0 | AL41: =Y41/Y$75 -> 0 | AM41: =AI41/AI$75 -> 0
B42: TT | 46T - 55T | D42: 18760 | E42: 18950 | F42: 21803.429 | G42: 21290 | H42: 21500 | I42: 24080 | J42: 24560 | K42: 26280 | L42: 29170 | M42: 31210 | N42: 32150 | O42: 34080 | P42: 37490 | Q42: 40110 | R42: 42520 | S42: 45500 | T42: 49140 | U42: 52580 | V42: 56260 | W42: 60200 | X42: 62610 | Y42: 65110 | Z42: 67710 | AA42: 70420 | AB42: 73940 | AC42: 79120 | AD42: 85450 | AE42: 90580 | AF42: 96010 | AG42: 101770 | AH42: 107880 | AI42: 116510 | AK42: =SUM(D42:AI42)/SUM($D$75:$AI$75)% -> 9.0541741 | AL42: =Y42/Y$75 -> 0.092060799 | AM42: =AI42/AI$75 -> 0.11313518
A43: 6 | B43: Tankers - Petroleum & CNG Total | C43: 43753.526 | D43: =SUM(D44:D50) -> 10240 | E43: =SUM(E44:E50) -> 9530 | F43: =SUM(F44:F50) -> 9902.419 | G43: =SUM(G44:G50) -> 10030 | H43: =SUM(H44:H50) -> 10130 | I43: =SUM(I44:I50) -> 10640 | J43: =SUM(J44:J50) -> 10960 | K43: =SUM(K44:K50) -> 11500 | ... AI43: =SUM(AI44:AI50) -> 26780 | AK43: =SUM(D43:AI43)/SUM($D$75:$AI$75)% -> 2.9703882 | AL43: =Y43/Y$75 -> 0.030427713 | AM43: =AI43/AI$75 -> 0.026004292
B44: Rigid|12T - 19T | D44: 3050 | E44: 2840 | F44: 4998.0337 | G44: 2990 | H44: 3020 | I44: 3170 | J44: 3270 | K44: 3430 | L44: 3670 | M44: 3930 | N44: 4090 | O44: 4290 | P44: 4500 | Q44: 4680 | R44: 4960 | S44: 5210 | T44: 5370 | U44: 5480 | V44: 5640 | W44: 5810 | X44: 6100 | Y44: 6410 | Z44: 6540 | AA44: 6670 | AB44: 6740 | AC44: 6870 | AD44: 7010 | AE44: 7220 | AF44: 7360 | AG44: 7580 | AH44: 7730 | AI44: 7960 | AK44: =SUM(D44:AI44)/SUM($D$75:$AI$75)% -> 0.89539891 | AL44: =Y44/Y$75 -> 0.0090632732 | AM44: =AI44/AI$75 -> 0.0077294311
B45: Rigid|19T - 28.5T | D45: 4190 | E45: 3900 | F45: 2436.995 | G45: 4100 | H45: 4140 | I45: 4350 | J45: 4480 | K45: 4700 | L45: 5030 | M45: 5380 | N45: 5600 | O45: 5880 | P45: 6170 | Q45: 6420 | R45: 6810 | S45: 7150 | T45: 7360 | U45: 7510 | V45: 7740 | W45: 7970 | X45: 8370 | Y45: 8790 | Z45: 8970 | AA45: 9150 | AB45: 9240 | AC45: 9420 | AD45: 9610 | AE45: 9900 | AF45: 10100 | AG45: 10400 | AH45: 10610 | AI45: 10930 | AK45: =SUM(D45:AI45)/SUM($D$75:$AI$75)% -> 1.2046094 | AL45: =Y45/Y$75 -> 0.01242842 | AM45: =AI45/AI$75 -> 0.010613402
B46: Rigid|28.5T - 40T | D46: 350 | E46: 330 | F46: 333.12945 | G46: 350 | H46: 350 | I46: 370 | J46: 380 | K46: 400 | L46: 430 | M46: 460 | N46: 480 | O46: 500 | P46: 530 | Q46: 550 | R46: 580 | S46: 610 | T46: 630 | U46: 640 | V46: 660 | W46: 680 | X46: 710 | Y46: 750 | Z46: 770 | AA46: 790 | AB46: 800 | AC46: 820 | AD46: 840 | AE46: 870 | AF46: 890 | AG46: 920 | AH46: 940 | AI46: 970 | AK46: =SUM(D46:AI46)/SUM($D$75:$AI$75)% -> 0.10454035 | AL46: =Y46/Y$75 -> 0.0010604454 | AM46: =AI46/AI$75 -> 0.00094190303
B47: Rigid|>40T | D47: 2650 | E47: 2460 | F47: 2134.2609 | G47: 2590 | H47: 2620 | I47: 2750 | J47: 2830 | K47: 2970 | L47: 3180 | M47: 3400 | N47: 3540 | O47: 3720 | P47: 3910 | Q47: 4070 | R47: 4310 | S47: 4530 | T47: 4670 | U47: 4760 | V47: 4900 | W47: 5050 | X47: 5300 | Y47: 5570 | Z47: 5680 | AA47: 5790 | AB47: 5850 | AC47: 5970 | AD47: 6090 | AE47: 6270 | AF47: 6400 | AG47: 6590 | AH47: 6720 | AI47: 6920 | AK47: =SUM(D47:AI47)/SUM($D$75:$AI$75)% -> 0.76583955 | AL47: =Y47/Y$75 -> 0.0078755744 | AM47: =AI47/AI$75 -> 0.0067195557
B48: TT | 31T - 40T | D48: 0 | E48: 0 | F48: 0 | G48: 0 | H48: 0 | I48: 0 | J48: 0 | K48: 0 | L48: 0 | M48: 0 | N48: 0 | O48: 0 | P48: 0 | Q48: 0 | R48: 0 | S48: 0 | T48: 0 | U48: 0 | V48: 0 | W48: 0 | X48: 0 | Y48: 0 | Z48: 0 | AA48: 0 | AB48: 0 | AC48: 0 | AD48: 0 | AE48: 0 | AF48: 0 | AG48: 0 | AH48: 0 | AI48: 0 | AK48: =SUM(D48:AI48)/SUM($D$75:$AI$75)% -> 0 | AL48: =Y48/Y$75 -> 0 | AM48: =AI48/AI$75 -> 0
B49: TT | 40 T - 46T | D49: 0 | E49: 0 | F49: 0 | G49: 0 | H49: 0 | I49: 0 | J49: 0 | K49: 0 | L49: 0 | M49: 0 | N49: 0 | O49: 0 | P49: 0 | Q49: 0 | R49: 0 | S49: 0 | T49: 0 | U49: 0 | V49: 0 | W49: 0 | X49: 0 | Y49: 0 | Z49: 0 | AA49: 0 | AB49: 0 | AC49: 0 | AD49: 0 | AE49: 0 | AF49: 0 | AG49: 0 | AH49: 0 | AI49: 0 | AK49: =SUM(D49:AI49)/SUM($D$75:$AI$75)% -> 0 | AL49: =Y49/Y$75 -> 0 | AM49: =AI49/AI$75 -> 0
B50: TT | 46T - 55T | D50: 0 | E50: 0 | F50: 0 | G50: 0 | H50: 0 | I50: 0 | J50: 0 | K50: 0 | L50: 0 | M50: 0 | N50: 0 | O50: 0 | P50: 0 | Q50: 0 | R50: 0 | S50: 0 | T50: 0 | U50: 0 | V50: 0 | W50: 0 | X50: 0 | Y50: 0 | Z50: 0 | AA50: 0 | AB50: 0 | AC50: 0 | AD50: 0 | AE50: 0 | AF50: 0 | AG50: 0 | AH50: 0 | AI50: 0 | AK50: =SUM(D50:AI50)/SUM($D$75:$AI$75)% -> 0 | AL50: =Y50/Y$75 -> 0 | AM50: =AI50/AI$75 -> 0
A51: 7 | B51: Tankers - Milk, Edible Oil & Water Total | C51: 8631.2575 | D51: =SUM(D52:D58) -> 9670 | E51: =SUM(E52:E58) -> 9000 | F51: =SUM(F52:F58) -> 9986.4068 | G51: =SUM(G52:G58) -> 9820 | H51: =SUM(H52:H58) -> 10020 | I51: =SUM(I52:I58) -> 10420 | J51: =SUM(J52:J58) -> 10850 | K51: =SUM(K52:K58) -> 11390 | ... AI51: =SUM(AI52:AI58) -> 50090 | AK51: =SUM(D51:AI51)/SUM($D$75:$AI$75)% -> 3.7402097 | AL51: =Y51/Y$75 -> 0.036380346 | AM51: =AI51/AI$75 -> 0.048639096
B52: Rigid|12T - 19T | D52: 3400 | E52: 3160 | F52: 5733.7498 | G52: 3450 | H52: 3520 | I52: 3660 | J52: 3810 | K52: 4000 | L52: 4240 | M52: 4450 | N52: 4670 | O52: 4950 | P52: 5250 | Q52: 5460 | R52: 5790 | S52: 6140 | T52: 6510 | U52: 6970 | V52: 7460 | W52: 7910 | X52: 8380 | Y52: 9050 | Z52: 9770 | AA52: 10550 | AB52: 10760 | AC52: 11510 | AD52: 12430 | AE52: 13180 | AF52: 14100 | AG52: 15230 | AH52: 16600 | AI52: 17600 | AK52: =SUM(D52:AI52)/SUM($D$75:$AI$75)% -> 1.3261648 | AL52: =Y52/Y$75 -> 0.012796041 | AM52: =AI52/AI$75 -> 0.017090199
B53: Rigid|19T - 28.5T | D53: 4330 | E53: 4030 | F53: 2592.1043 | G53: 4400 | H53: 4490 | I53: 4670 | J53: 4860 | K53: 5100 | L53: 5410 | M53: 5680 | N53: 5960 | O53: 6320 | P53: 6700 | Q53: 6970 | R53: 7390 | S53: 7830 | T53: 8300 | U53: 8880 | V53: 9500 | W53: 10070 | X53: 10670 | Y53: 11520 | Z53: 12440 | AA53: 13440 | AB53: 13710 | AC53: 14670 | AD53: 15840 | AE53: 16790 | AF53: 17970 | AG53: 19410 | AH53: 21160 | AI53: 22430 | AK53: =SUM(D53:AI53)/SUM($D$75:$AI$75)% -> 1.6652208 | AL53: =Y53/Y$75 -> 0.016288441 | AM53: =AI53/AI$75 -> 0.021780294
B54: Rigid|28.5T - 40T | D54: 350 | E54: 330 | F54: 342.13295 | G54: 360 | H54: 370 | I54: 380 | J54: 400 | K54: 420 | L54: 450 | M54: 470 | N54: 490 | O54: 520 | P54: 550 | Q54: 570 | R54: 600 | S54: 640 | T54: 680 | U54: 730 | V54: 780 | W54: 830 | X54: 880 | Y54: 950 | Z54: 1030 | AA54: 1110 | AB54: 1130 | AC54: 1210 | AD54: 1310 | AE54: 1390 | AF54: 1490 | AG54: 1610 | AH54: 1750 | AI54: 1860 | AK54: =SUM(D54:AI54)/SUM($D$75:$AI$75)% -> 0.1379954 | AL54: =Y54/Y$75 -> 0.0013432308 | AM54: =AI54/AI$75 -> 0.0018061233
B55: Rigid|>40T | D55: 1590 | E55: 1480 | F55: 1318.4197 | G55: 1610 | H55: 1640 | I55: 1710 | J55: 1780 | K55: 1870 | L55: 1980 | M55: 2080 | N55: 2180 | O55: 2310 | P55: 2450 | Q55: 2550 | R55: 2700 | S55: 2860 | T55: 3030 | U55: 3240 | V55: 3470 | W55: 3680 | X55: 3900 | Y55: 4210 | Z55: 4550 | AA55: 4910 | AB55: 5010 | AC55: 5360 | AD55: 5790 | AE55: 6140 | AF55: 6570 | AG55: 7100 | AH55: 7740 | AI55: 8200 | AK55: =SUM(D55:AI55)/SUM($D$75:$AI$75)% -> 0.61082872 | AL55: =Y55/Y$75 -> 0.0059526334 | AM55: =AI55/AI$75 -> 0.0079624792
B56: TT | 31T - 40T | D56: 0 | E56: 0 | F56: 0 | G56: 0 | H56: 0 | I56: 0 | J56: 0 | K56: 0 | L56: 0 | M56: 0 | N56: 0 | O56: 0 | P56: 0 | Q56: 0 | R56: 0 | S56: 0 | T56: 0 | U56: 0 | V56: 0 | W56: 0 | X56: 0 | Y56: 0 | Z56: 0 | AA56: 0 | AB56: 0 | AC56: 0 | AD56: 0 | AE56: 0 | AF56: 0 | AG56: 0 | AH56: 0 | AI56: 0 | AK56: =SUM(D56:AI56)/SUM($D$75:$AI$75)% -> 0 | AL56: =Y56/Y$75 -> 0 | AM56: =AI56/AI$75 -> 0
B57: TT | 40 T - 46T | D57: 0 | E57: 0 | F57: 0 | G57: 0 | H57: 0 | I57: 0 | J57: 0 | K57: 0 | L57: 0 | M57: 0 | N57: 0 | O57: 0 | P57: 0 | Q57: 0 | R57: 0 | S57: 0 | T57: 0 | U57: 0 | V57: 0 | W57: 0 | X57: 0 | Y57: 0 | Z57: 0 | AA57: 0 | AB57: 0 | AC57: 0 | AD57: 0 | AE57: 0 | AF57: 0 | AG57: 0 | AH57: 0 | AI57: 0 | AK57: =SUM(D57:AI57)/SUM($D$75:$AI$75)% -> 0 | AL57: =Y57/Y$75 -> 0 | AM57: =AI57/AI$75 -> 0
B58: TT | 46T - 55T | D58: 0 | E58: 0 | F58: 0 | G58: 0 | H58: 0 | I58: 0 | J58: 0 | K58: 0 | L58: 0 | M58: 0 | N58: 0 | O58: 0 | P58: 0 | Q58: 0 | R58: 0 | S58: 0 | T58: 0 | U58: 0 | V58: 0 | W58: 0 | X58: 0 | Y58: 0 | Z58: 0 | AA58: 0 | AB58: 0 | AC58: 0 | AD58: 0 | AE58: 0 | AF58: 0 | AG58: 0 | AH58: 0 | AI58: 0 | AK58: =SUM(D58:AI58)/SUM($D$75:$AI$75)% -> 0 | AL58: =Y58/Y$75 -> 0 | AM58: =AI58/AI$75 -> 0
A59: 8 | B59: LPG Total | C59: 3169.2457 | D59: =SUM(D60:D66) -> 7810 | E59: =SUM(E60:E66) -> 6250 | F59: =SUM(F60:F66) -> 8410.3069 | G59: =SUM(G60:G66) -> 7010 | H59: =SUM(H60:H66) -> 7140 | I59: =SUM(I60:I66) -> 7430 | J59: =SUM(J60:J66) -> 7500 | K59: =SUM(K60:K66) -> 7790 | ... AI59: =SUM(AI60:AI66) -> 9570 | AK59: =SUM(D59:AI59)/SUM($D$75:$AI$75)% -> 1.4708757 | AL59: =Y59/Y$75 -> 0.012866737 | AM59: =AI59/AI$75 -> 0.0092927959
B60: Rigid|12T - 19T | D60: 2690 | E60: 2150 | F60: 4087.8873 | G60: 2420 | H60: 2470 | I60: 2570 | J60: 2600 | K60: 2700 | L60: 2840 | M60: 2870 | N60: 2930 | O60: 2990 | P60: 3020 | Q60: 2870 | R60: 3010 | S60: 3100 | T60: 3100 | U60: 3130 | V60: 3130 | W60: 3160 | X60: 3160 | Y60: 3160 | Z60: 3190 | AA60: 3320 | AB60: 3250 | AC60: 3250 | AD60: 3280 | AE60: 3350 | AF60: 3420 | AG60: 3390 | AH60: 3320 | AI60: 3320 | AK60: =SUM(D60:AI60)/SUM($D$75:$AI$75)% -> 0.5164996 | AL60: =Y60/Y$75 -> 0.0044680099 | AM60: =AI60/AI$75 -> 0.0032238331
B61: Rigid|19T - 28.5T | D61: 2430 | E61: 1940 | F61: 1310.7661 | G61: 2170 | H61: 2210 | I61: 2300 | J61: 2320 | K61: 2410 | L61: 2530 | M61: 2560 | N61: 2610 | O61: 2660 | P61: 2690 | Q61: 2560 | R61: 2690 | S61: 2770 | T61: 2770 | U61: 2800 | V61: 2800 | W61: 2830 | X61: 2830 | Y61: 2830 | Z61: 2860 | AA61: 2970 | AB61: 2910 | AC61: 2910 | AD61: 2940 | AE61: 3000 | AF61: 3060 | AG61: 3030 | AH61: 2970 | AI61: 2970 | AK61: =SUM(D61:AI61)/SUM($D$75:$AI$75)% -> 0.4495411 | AL61: =Y61/Y$75 -> 0.0040014139 | AM61: =AI61/AI$75 -> 0.0028839711
B62: Rigid|28.5T - 40T | D62: 0 | E62: 0 | F62: 0 | G62: 0 | H62: 0 | I62: 0 | J62: 0 | K62: 0 | L62: 0 | M62: 0 | N62: 0 | O62: 0 | P62: 0 | Q62: 0 | R62: 0 | S62: 0 | T62: 0 | U62: 0 | V62: 0 | W62: 0 | X62: 0 | Y62: 0 | Z62: 0 | AA62: 0 | AB62: 0 | AC62: 0 | AD62: 0 | AE62: 0 | AF62: 0 | AG62: 0 | AH62: 0 | AI62: 0 | AK62: =SUM(D62:AI62)/SUM($D$75:$AI$75)% -> 0 | AL62: =Y62/Y$75 -> 0 | AM62: =AI62/AI$75 -> 0
B63: Rigid|>40T | D63: 0 | E63: 0 | F63: 0 | G63: 0 | H63: 0 | I63: 0 | J63: 0 | K63: 0 | L63: 0 | M63: 0 | N63: 0 | O63: 0 | P63: 0 | Q63: 0 | R63: 0 | S63: 0 | T63: 0 | U63: 0 | V63: 0 | W63: 0 | X63: 0 | Y63: 0 | Z63: 0 | AA63: 0 | AB63: 0 | AC63: 0 | AD63: 0 | AE63: 0 | AF63: 0 | AG63: 0 | AH63: 0 | AI63: 0 | AK63: =SUM(D63:AI63)/SUM($D$75:$AI$75)% -> 0 | AL63: =Y63/Y$75 -> 0 | AM63: =AI63/AI$75 -> 0
B64: TT | 31T - 40T | D64: 2470 | E64: 1980 | F64: 2891.2968 | G64: 2220 | H64: 2260 | I64: 2350 | J64: 2370 | K64: 2460 | L64: 2580 | M64: 2610 | N64: 2660 | O64: 2710 | P64: 2740 | Q64: 2600 | R64: 2730 | S64: 2810 | T64: 2810 | U64: 2840 | V64: 2840 | W64: 2870 | X64: 2870 | Y64: 2870 | Z64: 2900 | AA64: 3020 | AB64: 2960 | AC64: 2960 | AD64: 2990 | AE64: 3050 | AF64: 3110 | AG64: 3080 | AH64: 3020 | AI64: 3020 | AK64: =SUM(D64:AI64)/SUM($D$75:$AI$75)% -> 0.46553052 | AL64: =Y64/Y$75 -> 0.004057971 | AM64: =AI64/AI$75 -> 0.0029325228
B65: TT | 40 T - 46T | D65: 220 | E65: 180 | F65: 120.35669 | G65: 200 | H65: 200 | I65: 210 | J65: 210 | K65: 220 | L65: 230 | M65: 230 | N65: 230 | O65: 230 | P65: 230 | Q65: 220 | R65: 230 | S65: 240 | T65: 240 | U65: 240 | V65: 240 | W65: 240 | X65: 240 | Y65: 240 | Z65: 240 | AA65: 250 | AB65: 250 | AC65: 250 | AD65: 250 | AE65: 260 | AF65: 270 | AG65: 270 | AH65: 260 | AI65: 260 | AK65: =SUM(D65:AI65)/SUM($D$75:$AI$75)% -> 0.039304517 | AL65: =Y65/Y$75 -> 0.00033934252 | AM65: =AI65/AI$75 -> 0.00025246885
B66: TT | 46T - 55T | D66: 0 | E66: 0 | F66: 0 | G66: 0 | H66: 0 | I66: 0 | J66: 0 | K66: 0 | L66: 0 | M66: 0 | N66: 0 | O66: 0 | P66: 0 | Q66: 0 | R66: 0 | S66: 0 | T66: 0 | U66: 0 | V66: 0 | W66: 0 | X66: 0 | Y66: 0 | Z66: 0 | AA66: 0 | AB66: 0 | AC66: 0 | AD66: 0 | AE66: 0 | AF66: 0 | AG66: 0 | AH66: 0 | AI66: 0 | AK66: =SUM(D66:AI66)/SUM($D$75:$AI$75)% -> 0 | AL66: =Y66/Y$75 -> 0 | AM66: =AI66/AI$75 -> 0
A67: 9 | B67: Cement Total | C67: 14811.472 | D67: =SUM(D68:D74) -> 35290 | E67: =SUM(E68:E74) -> 35640 | F67: =SUM(F68:F74) -> 36132.988 | G67: =SUM(G68:G74) -> 40800 | H67: =SUM(H68:H74) -> 41620 | I67: =SUM(I68:I74) -> 46620 | J67: =SUM(J68:J74) -> 47550 | K67: =SUM(K68:K74) -> 42790 | ... AI67: =SUM(AI68:AI74) -> 98340 | AK67: =SUM(D67:AI67)/SUM($D$75:$AI$75)% -> 10.994606 | AL67: =Y67/Y$75 -> 0.10972075 | AM67: =AI67/AI$75 -> 0.095491489
B68: Rigid|12T - 19T | D68: 2740 | E68: 2770 | F68: 5113.745 | G68: 3170 | H68: 3230 | I68: 3620 | J68: 3690 | K68: 3320 | L68: 3550 | M68: 3760 | N68: 3910 | O68: 4070 | P68: 4230 | Q68: 4310 | R68: 4480 | S68: 4750 | T68: 5080 | U68: 5280 | V68: 5490 | W68: 5710 | X68: 5880 | Y68: 6000 | Z68: 6120 | AA68: 6300 | AB68: 6360 | AC68: 6490 | AD68: 6810 | AE68: 6950 | AF68: 7090 | AG68: 7230 | AH68: 7370 | AI68: 7590 | AK68: =SUM(D68:AI68)/SUM($D$75:$AI$75)% -> 0.8628718 | AL68: =Y68/Y$75 -> 0.0084835631 | AM68: =AI68/AI$75 -> 0.0073701485
B69: Rigid|19T - 28.5T | D69: 10200 | E69: 10300 | F69: 6757.9863 | G69: 11790 | H69: 12030 | I69: 13470 | J69: 13740 | K69: 12370 | L69: 13240 | M69: 14030 | N69: 14590 | O69: 15170 | P69: 15780 | Q69: 16100 | R69: 16740 | S69: 17740 | T69: 18980 | U69: 19740 | V69: 20530 | W69: 21350 | X69: 21990 | Y69: 22430 | Z69: 22880 | AA69: 23570 | AB69: 23810 | AC69: 24290 | AD69: 25500 | AE69: 26010 | AF69: 26530 | AG69: 27060 | AH69: 27600 | AI69: 28430 | AK69: =SUM(D69:AI69)/SUM($D$75:$AI$75)% -> 3.1588048 | AL69: =Y69/Y$75 -> 0.031714387 | AM69: =AI69/AI$75 -> 0.027606498
B70: Rigid|28.5T - 40T | D70: 350 | E70: 350 | F70: 379.14733 | G70: 400 | H70: 410 | I70: 460 | J70: 470 | K70: 420 | L70: 450 | M70: 480 | N70: 500 | O70: 520 | P70: 540 | Q70: 550 | R70: 570 | S70: 600 | T70: 640 | U70: 670 | V70: 700 | W70: 730 | X70: 750 | Y70: 770 | Z70: 790 | AA70: 810 | AB70: 820 | AC70: 840 | AD70: 880 | AE70: 900 | AF70: 920 | AG70: 940 | AH70: 960 | AI70: 990 | AK70: =SUM(D70:AI70)/SUM($D$75:$AI$75)% -> 0.10919303 | AL70: =Y70/Y$75 -> 0.0010887239 | AM70: =AI70/AI$75 -> 0.00096132371
B71: Rigid|>40T | D71: 6890 | E71: 6960 | F71: 6321.2834 | G71: 7970 | H71: 8130 | I71: 9110 | J71: 9290 | K71: 8360 | L71: 8950 | M71: 9490 | N71: 9870 | O71: 10260 | P71: 10670 | Q71: 10880 | R71: 11320 | S71: 12000 | T71: 12840 | U71: 13350 | V71: 13880 | W71: 14440 | X71: 14870 | Y71: 15170 | Z71: 15470 | AA71: 15930 | AB71: 16090 | AC71: 16410 | AD71: 17230 | AE71: 17570 | AF71: 17920 | AG71: 18280 | AH71: 18650 | AI71: 19210 | AK71: =SUM(D71:AI71)/SUM($D$75:$AI$75)% -> 2.1445491 | AL71: =Y71/Y$75 -> 0.021449275 | AM71: =AI71/AI$75 -> 0.018653564
B72: TT | 31T - 40T | D72: 0 | E72: 0 | F72: 0 | G72: 0 | H72: 0 | I72: 0 | J72: 0 | K72: 0 | L72: 0 | M72: 0 | N72: 0 | O72: 0 | P72: 0 | Q72: 0 | R72: 0 | S72: 0 | T72: 0 | U72: 0 | V72: 0 | W72: 0 | X72: 0 | Y72: 0 | Z72: 0 | AA72: 0 | AB72: 0 | AC72: 0 | AD72: 0 | AE72: 0 | AF72: 0 | AG72: 0 | AH72: 0 | AI72: 0 | AK72: =SUM(D72:AI72)/SUM($D$75:$AI$75)% -> 0 | AL72: =Y72/Y$75 -> 0 | AM72: =AI72/AI$75 -> 0
B73: TT | 40 T - 46T | D73: 0 | E73: 0 | F73: 0 | G73: 0 | H73: 0 | I73: 0 | J73: 0 | K73: 0 | L73: 0 | M73: 0 | N73: 0 | O73: 0 | P73: 0 | Q73: 0 | R73: 0 | S73: 0 | T73: 0 | U73: 0 | V73: 0 | W73: 0 | X73: 0 | Y73: 0 | Z73: 0 | AA73: 0 | AB73: 0 | AC73: 0 | AD73: 0 | AE73: 0 | AF73: 0 | AG73: 0 | AH73: 0 | AI73: 0 | AK73: =SUM(D73:AI73)/SUM($D$75:$AI$75)% -> 0 | AL73: =Y73/Y$75 -> 0 | AM73: =AI73/AI$75 -> 0
B74: TT | 46T - 55T | D74: 15110 | E74: 15260 | F74: 17560.826 | G74: 17470 | H74: 17820 | I74: 19960 | J74: 20360 | K74: 18320 | L74: 19600 | M74: 20780 | N74: 21610 | O74: 22470 | P74: 23370 | Q74: 23840 | R74: 24790 | S74: 26280 | T74: 28120 | U74: 29240 | V74: 30410 | W74: 31630 | X74: 32580 | Y74: 33230 | Z74: 33890 | AA74: 34910 | AB74: 35260 | AC74: 35970 | AD74: 37770 | AE74: 38530 | AF74: 39300 | AG74: 40090 | AH74: 40890 | AI74: 42120 | AK74: =SUM(D74:AI74)/SUM($D$75:$AI$75)% -> 4.7191872 | AL74: =Y74/Y$75 -> 0.0469848 | AM74: =AI74/AI$75 -> 0.040899954
B75: Grand Total | C75: 274193.37 | D75: =SUM(D76:D82) -> 282590 | E75: =SUM(E76:E82) -> 267370 | F75: =SUM(F76:F82) -> 301119.98 | G75: =SUM(G76:G82) -> 306590 | H75: =SUM(H76:H82) -> 311550 | I75: =SUM(I76:I82) -> 340650 | J75: =SUM(J76:J82) -> 349950 | K75: =SUM(K76:K82) -> 357130 | ... AI75: =SUM(AI76:AI82) -> 1029830 | AK75: =SUM(D75:AI75)/SUM($D$75:$AI$75)% -> 100 | AL75: =Y75/Y$75 -> 1 | AM75: =AI75/AI$75 -> 1
B76: Rigid|12T - 19T | D76: =D68+D60+D52+D44+D36+D28+D20+D12+D4 -> 60940 | E76: =E68+E60+E52+E44+E36+E28+E20+E12+E4 -> 54700 | F76: =F68+F60+F52+F44+F36+F28+F20+F12+F4 -> 104824 | G76: =G68+G60+G52+G44+G36+G28+G20+G12+G4 -> 63200 | H76: =H68+H60+H52+H44+H36+H28+H20+H12+H4 -> 64080 | I76: =I68+I60+I52+I44+I36+I28+I20+I12+I4 -> 70140 | J76: =J68+J60+J52+J44+J36+J28+J20+J12+J4 -> 72400 | K76: =K68+K60+K52+K44+K36+K28+K20+K12+K4 -> 74140 | ... AI76: =AI68+AI60+AI52+AI44+AI36+AI28+AI20+AI12+AI4 -> 217490 | AK76: =SUM(D76:AI76)/SUM($D$75:$AI$75)% -> 21.394138 | AL76: =Y76/Y$75 -> 0.21177801 | AM76: =AI76/AI$75 -> 0.2111902
B77: Rigid|19T - 28.5T | D77: =D69+D61+D53+D45+D37+D29+D21+D13+D5 -> 80350 | E77: =E69+E61+E53+E45+E37+E29+E21+E13+E5 -> 76040 | F77: =F69+F61+F53+F45+F37+F29+F21+F13+F5 -> 50985 | G77: =G69+G61+G53+G45+G37+G29+G21+G13+G5 -> 86950 | H77: =H69+H61+H53+H45+H37+H29+H21+H13+H5 -> 88430 | I77: =I69+I61+I53+I45+I37+I29+I21+I13+I5 -> 96330 | J77: =J69+J61+J53+J45+J37+J29+J21+J13+J5 -> 99010 | K77: =K69+K61+K53+K45+K37+K29+K21+K13+K5 -> 100750 | ... AI77: =AI69+AI61+AI53+AI45+AI37+AI29+AI21+AI13+AI5 -> 273060 | AK77: =SUM(D77:AI77)/SUM($D$75:$AI$75)% -> 27.158564 | AL77: =Y77/Y$75 -> 0.27181336 | AM77: =AI77/AI$75 -> 0.26515056
B78: Rigid|28.5T - 40T | D78: =D70+D62+D54+D46+D38+D30+D22+D14+D6 -> 23840 | E78: =E70+E62+E54+E46+E38+E30+E22+E14+E6 -> 23650 | F78: =F70+F62+F54+F46+F38+F30+F22+F14+F6 -> 25734 | G78: =G70+G62+G54+G46+G38+G30+G22+G14+G6 -> 26980 | H78: =H70+H62+H54+H46+H38+H30+H22+H14+H6 -> 27490 | I78: =I70+I62+I54+I46+I38+I30+I22+I14+I6 -> 29620 | J78: =J70+J62+J54+J46+J38+J30+J22+J14+J6 -> 30310 | K78: =K70+K62+K54+K46+K38+K30+K22+K14+K6 -> 31640 | ... AI78: =AI70+AI62+AI54+AI46+AI38+AI30+AI22+AI14+AI6 -> 85170 | AK78: =SUM(D78:AI78)/SUM($D$75:$AI$75)% -> 8.431921 | AL78: =Y78/Y$75 -> 0.08408625 | AM78: =AI78/AI$75 -> 0.08270297
B79: Rigid|>40T | D79: =D71+D63+D55+D47+D39+D31+D23+D15+D7 -> 53880 | E79: =E71+E63+E55+E47+E39+E31+E23+E15+E7 -> 51010 | F79: =F71+F63+F55+F47+F39+F31+F23+F15+F7 -> 47430 | G79: =G71+G63+G55+G47+G39+G31+G23+G15+G7 -> 58490 | H79: =H71+H63+H55+H47+H39+H31+H23+H15+H7 -> 59460 | I79: =I71+I63+I55+I47+I39+I31+I23+I15+I7 -> 64800 | J79: =J71+J63+J55+J47+J39+J31+J23+J15+J7 -> 66580 | K79: =K71+K63+K55+K47+K39+K31+K23+K15+K7 -> 67780 | ... AI79: =AI71+AI63+AI55+AI47+AI39+AI31+AI23+AI15+AI7 -> 187160 | AK79: =SUM(D79:AI79)/SUM($D$75:$AI$75)% -> 18.57835 | AL79: =Y79/Y$75 -> 0.18624249 | AM79: =AI79/AI$75 -> 0.18173873
B80: TT | 31T - 40T | D80: =D72+D64+D56+D48+D40+D32+D24+D16+D8 -> 7060 | E80: =E72+E64+E56+E48+E40+E32+E24+E16+E8 -> 6110 | F80: =F72+F64+F56+F48+F40+F32+F24+F16+F8 -> 9154 | G80: =G72+G64+G56+G48+G40+G32+G24+G16+G8 -> 7260 | H80: =H72+H64+H56+H48+H40+H32+H24+H16+H8 -> 7400 | I80: =I72+I64+I56+I48+I40+I32+I24+I16+I8 -> 8110 | J80: =J72+J64+J56+J48+J40+J32+J24+J16+J8 -> 8360 | K80: =K72+K64+K56+K48+K40+K32+K24+K16+K8 -> 8750 | ... AI80: =AI72+AI64+AI56+AI48+AI40+AI32+AI24+AI16+AI8 -> 27580 | AK80: =SUM(D80:AI80)/SUM($D$75:$AI$75)% -> 2.6370148 | AL80: =Y80/Y$75 -> 0.026907034 | AM80: =AI80/AI$75 -> 0.026781119
B81: TT | 40 T - 46T | D81: =D73+D65+D57+D49+D41+D33+D25+D17+D9 -> 4410 | E81: =E73+E65+E57+E49+E41+E33+E25+E17+E9 -> 3930 | F81: =F73+F65+F57+F49+F41+F33+F25+F17+F9 -> 2762 | G81: =G73+G65+G57+G49+G41+G33+G25+G17+G9 -> 4730 | H81: =H73+H65+H57+H49+H41+H33+H25+H17+H9 -> 4800 | I81: =I73+I65+I57+I49+I41+I33+I25+I17+I9 -> 5340 | J81: =J73+J65+J57+J49+J41+J33+J25+J17+J9 -> 5540 | K81: =K73+K65+K57+K49+K41+K33+K25+K17+K9 -> 5800 | ... AI81: =AI73+AI65+AI57+AI49+AI41+AI33+AI25+AI17+AI9 -> 20990 | AK81: =SUM(D81:AI81)/SUM($D$75:$AI$75)% -> 1.8872801 | AL81: =Y81/Y$75 -> 0.019780841 | AM81: =AI81/AI$75 -> 0.020382005
B82: TT | 46T - 55T | D82: =D74+D66+D58+D50+D42+D34+D26+D18+D10 -> 52110 | E82: =E74+E66+E58+E50+E42+E34+E26+E18+E10 -> 51930 | F82: =F74+F66+F58+F50+F42+F34+F26+F18+F10 -> 60230.978 | G82: =G74+G66+G58+G50+G42+G34+G26+G18+G10 -> 58980 | H82: =H74+H66+H58+H50+H42+H34+H26+H18+H10 -> 59890 | I82: =I74+I66+I58+I50+I42+I34+I26+I18+I10 -> 66310 | J82: =J74+J66+J58+J50+J42+J34+J26+J18+J10 -> 67750 | K82: =K74+K66+K58+K50+K42+K34+K26+K18+K10 -> 68270 | ... AI82: =AI74+AI66+AI58+AI50+AI42+AI34+AI26+AI18+AI10 -> 218380 | AK82: =SUM(D82:AI82)/SUM($D$75:$AI$75)% -> 19.912732 | AL82: =Y82/Y$75 -> 0.19939201 | AM82: =AI82/AI$75 -> 0.21205442
B84: Rigid|12T - 19T | E84: =E76/E$75 -> 0.20458541 | F84: =F76/F$75 -> 0.34811373 | G84: =G76/G$75 -> 0.20613849 | H84: =H76/H$75 -> 0.20568127 | I84: =I76/I$75 -> 0.20590048 | J84: =J76/J$75 -> 0.2068867 | K84: =K76/K$75 -> 0.20759947 | L84: =L76/L$75 -> 0.21002514 | ... AI84: =AI76/AI$75 -> 0.2111902
B85: Rigid|19T - 28.5T | E85: =E77/E$75 -> 0.2843999 | F85: =F77/F$75 -> 0.16931789 | G85: =G77/G$75 -> 0.28360351 | H85: =H77/H$75 -> 0.28383887 | I85: =I77/I$75 -> 0.28278292 | J85: =J77/J$75 -> 0.28292613 | K85: =K77/K$75 -> 0.28211016 | L85: =L77/L$75 -> 0.28140474 | ... AI85: =AI77/AI$75 -> 0.26515056
B86: Rigid|28.5T - 40T | E86: =E78/E$75 -> 0.088454202 | F86: =F78/F$75 -> 0.085460952 | G86: =G78/G$75 -> 0.088000261 | H86: =H78/H$75 -> 0.088236238 | I86: =I78/I$75 -> 0.086951416 | J86: =J78/J$75 -> 0.086612373 | K86: =K78/K$75 -> 0.088595189 | L86: =L78/L$75 -> 0.087605698 | ... AI86: =AI78/AI$75 -> 0.08270297
B87: Rigid|>40T | E87: =E79/E$75 -> 0.19078431 | F87: =F79/F$75 -> 0.15751197 | G87: =G79/G$75 -> 0.19077595 | H87: =H79/H$75 -> 0.19085219 | I87: =I79/I$75 -> 0.19022457 | J87: =J79/J$75 -> 0.19025575 | K87: =K79/K$75 -> 0.18979083 | L87: =L79/L$75 -> 0.18943145 | ... AI87: =AI79/AI$75 -> 0.18173873
A88: 0.022941706 | B88: TT | 31T - 40T | E88: =E80/E$75 -> 0.022852227 | F88: =F80/F$75 -> 0.030399843 | G88: =G80/G$75 -> 0.023679833 | H88: =H80/H$75 -> 0.023752207 | I88: =I80/I$75 -> 0.023807427 | J88: =J80/J$75 -> 0.023889127 | K88: =K80/K$75 -> 0.024500882 | L88: =L80/L$75 -> 0.02491049 | ... AI88: =AI80/AI$75 -> 0.026781119
A89: 0.011638462 | B89: TT | 40 T - 46T | E89: =E81/E$75 -> 0.014698732 | F89: =F81/F$75 -> 0.0091724236 | G89: =G81/G$75 -> 0.01542777 | H89: =H81/H$75 -> 0.015406837 | I89: =I81/I$75 -> 0.015675914 | J89: =J81/J$75 -> 0.015830833 | K89: =K81/K$75 -> 0.016240585 | L89: =L81/L$75 -> 0.016784744 | ... AI89: =AI81/AI$75 -> 0.020382005
A90: 0.22564303 | B90: TT | 46T - 55T | E90: =E82/E$75 -> 0.19422523 | F90: =F82/F$75 -> 0.20002319 | G90: =G82/G$75 -> 0.19237418 | H90: =H82/H$75 -> 0.19223239 | I90: =I82/I$75 -> 0.19465727 | J90: =J82/J$75 -> 0.19359909 | K90: =K82/K$75 -> 0.19116288 | L90: =L82/L$75 -> 0.18983774 | ... AI90: =AI82/AI$75 -> 0.21205442
B92: =B3 -> Market Load Total | D92: =D3/D$75 -> 0.22088538 | E92: =E3/E$75 -> 0.19841418 | F92: =F3/F$75 -> 0.22436605 | G92: =G3/G$75 -> 0.20118073 | H92: =H3/H$75 -> 0.1999358 | I92: =I3/I$75 -> 0.20475561 | J92: =J3/J$75 -> 0.20725818 | K92: =K3/K$75 -> 0.20309131 | ... AI92: =AI3/AI$75 -> 0.16521173
B93: =B11 -> Parcel Load, FMCG & eCommerce | D93: =D11/D$75 -> 0.11766163 | E93: =E11/E$75 -> 0.11190485 | F93: =F11/F$75 -> 0.12590672 | G93: =G11/G$75 -> 0.1190515 | H93: =H11/H$75 -> 0.11949928 | I93: =I11/I$75 -> 0.12241303 | J93: =J11/J$75 -> 0.12396057 | K93: =K11/K$75 -> 0.12757259 | ... AI93: =AI11/AI$75 -> 0.17257217
B94: =B67 -> Cement Total | D94: =D67/D$75 -> 0.12488057 | E94: =E67/E$75 -> 0.13329843 | F94: =F67/F$75 -> 0.11999532 | G94: =G67/G$75 -> 0.13307675 | H94: =H67/H$75 -> 0.13359011 | I94: =I67/I$75 -> 0.13685601 | J94: =J67/J$75 -> 0.13587655 | K94: =K67/K$75 -> 0.11981631 | ... AI94: =AI67/AI$75 -> 0.095491489
B95: =B35 -> Steel & Metal Products Total | D95: =D35/D$75 -> 0.0699954 | E95: =E35/E$75 -> 0.074727905 | F95: =F35/F$75 -> 0.078728153 | G95: =G35/G$75 -> 0.073224828 | H95: =H35/H$75 -> 0.072765206 | I95: =I35/I$75 -> 0.074533979 | J95: =J35/J$75 -> 0.074010573 | K95: =K35/K$75 -> 0.077590793 | ... AI95: =AI35/AI$75 -> 0.11929153
B96: =B43 -> Tankers - Petroleum & CNG Total | D96: =D43/D$75 -> 0.036236243 | E96: =E43/E$75 -> 0.03564349 | F96: =F43/F$75 -> 0.032885294 | G96: =G43/G$75 -> 0.0327147 | H96: =H43/H$75 -> 0.032514845 | I96: =I43/I$75 -> 0.031234405 | J96: =J43/J$75 -> 0.03131876 | K96: =K43/K$75 -> 0.032201159 | ... AI96: =AI43/AI$75 -> 0.026004292
B97: =B51 -> Tankers - Milk, Edible Oil & Water Total | D97: =D51/D$75 -> 0.034219187 | E97: =E51/E$75 -> 0.033661219 | F97: =F51/F$75 -> 0.033164212 | G97: =G51/G$75 -> 0.032029747 | H97: =H51/H$75 -> 0.032161772 | I97: =I51/I$75 -> 0.030588581 | J97: =J51/J$75 -> 0.031004429 | K97: =K51/K$75 -> 0.031893148 | ... AI97: =AI51/AI$75 -> 0.048639096
B98: =B27 -> Constructin & Mining | D98: =D27/D$75 -> 0.30298312 | E98: =E27/E$75 -> 0.32662602 | F98: =F27/F$75 -> 0.27887542 | G98: =G27/G$75 -> 0.32300466 | H98: =H27/H$75 -> 0.32418552 | I98: =I27/I$75 -> 0.3172758 | J98: =J27/J$75 -> 0.31504501 | K98: =K27/K$75 -> 0.32416767 | ... AI98: =AI27/AI$75 -> 0.29046542
B99: =B19 -> Perishables & Fish Total | D99: =D19/D$75 -> 0.065501256 | E99: =E19/E$75 -> 0.062348057 | F99: =F19/F$75 -> 0.078148747 | G99: =G19/G$75 -> 0.06285267 | H99: =H19/H$75 -> 0.062429787 | I99: =I19/I$75 -> 0.060531337 | J99: =J19/J$75 -> 0.060094299 | K99: =K19/K$75 -> 0.061854227 | ... AI99: =AI19/AI$75 -> 0.073031471
B100: =B59 -> LPG Total | D100: =D59/D$75 -> 0.027637213 | E100: =E59/E$75 -> 0.023375846 | F100: =F59/F$75 -> 0.027930086 | G100: =G59/G$75 -> 0.022864412 | H100: =H59/H$75 -> 0.02291767 | I100: =I59/I$75 -> 0.021811243 | J100: =J59/J$75 -> 0.021431633 | K100: =K59/K$75 -> 0.021812785 | ... AI100: =AI59/AI$75 -> 0.0092927959
B102: Grand Total (Rounded off) | C102: =ROUND(C75/100,0)*100 -> 274200 | D102: =ROUND(D75/100,0)*100 -> 282600 | E102: =ROUND(E75/100,0)*100 -> 267400 | F102: =ROUND(F75/100,0)*100 -> 301100 | G102: =ROUND(G75/100,0)*100 -> 306600 | H102: =ROUND(H75/100,0)*100 -> 311600 | I102: =ROUND(I75/100,0)*100 -> 340700 | J102: =ROUND(J75/100,0)*100 -> 350000 | ... AI102: =ROUND(AI75/100,0)*100 -> 1029800
A104: Year | B104: {=TRANSPOSE(B75:AI75)} -> Grand Total
...

Sheet Buckets
A1: Buckets | H1: Potential TIV 2035 | M1: Potential TIV 2040 | R1: Potential TIV 2045 | W1: Potential TIV 2050 | AB1: TIV 2055 | AE1: TCO Parity with Diesel | AH1: TCO Parity with Diesel Scenario 1
A2: Sl. No. | B2: Bucket No. | C2: Usecase | D2: Model | E2: 2025 Volume | F2: Share of TIV | H2: Total | I2: Share of TIV | J2: Rigid | K2: TT | M2: Total | N2: Share of TIV | O2: Rigid | P2: TT | R2: Total | S2: Share of TIV | T2: Rigid | U2: TT | W2: Total | X2: Share of TIV | Y2: Rigid | Z2: TT | AB2: Total | AC2: Share of TIV | AE2: BET Vs Diesel | AF2: H2 ICE Vs Diesel | AG2: H2 FCET Vs Diesel | AH2: BET Vs Diesel | AI2: H2 ICE Vs Diesel | AJ2: H2 FCET Vs Diesel
A3: 1 | B3: B1 | C3: Market Load | D3: 19T Rigid | E3: ='AnnualSalesSummary Revised'!E4 -> 19240 | F3: =E3/$E$18 -> 0.071960205 | H3: ='AnnualSalesSummary Revised'!O4 -> 36690 | I3: =H3/H$18 -> 0.079851136 | J3: =H3 -> 36690 | K3: =H3-J3 -> 0 | M3: ='AnnualSalesSummary Revised'!T4 -> 40490 | N3: =M3/M$18 -> 0.070967855 | O3: =M3 -> 40490 | P3: =M3-O3 -> 0 | R3: ='AnnualSalesSummary Revised'!Y4 -> 46470 | S3: =R3/R$18 -> 0.065705196 | T3: =R3 -> 46470 | U3: =R3-T3 -> 0 | W3: ='AnnualSalesSummary Revised'!AD4 -> 54310 | X3: =W3/W$18 -> 0.063631358 | Y3: =W3 -> 54310 | Z3: =W3-Y3 -> 0 | AB3: ='AnnualSalesSummary Revised'!AI4 -> 61710 | AC3: =AB3/AB$18 -> 0.059922511 | AE3: {=IFERROR(INDEX('B1 - TCO ML 19T'!$C$182:$AG$182,MATCH(1,('B1 - TCO ML 19T'!$C$168:$AG$168<='B1 - TCO ML 19T'!$C$165:$AG$165)*1,0)),"No Parity")} -> 2031 | AF3: {=IFERROR(INDEX('B1 - TCO ML 19T'!$C$182:$AG$182,MATCH(1,('B1 - TCO ML 19T'!$C$169:$AG$169<='B1 - TCO ML 19T'!$C$165:$AG$165)*1,0)),"No Parity")} -> 2046 | AG3: {=IFERROR(INDEX('B1 - TCO ML 19T'!$C$182:$AG$182,MATCH(1,('B1 - TCO ML 19T'!$C$170:$AG$170<='B1 - TCO ML 19T'!$C$165:$AG$165)*1,0)),"No Parity")} -> 2046 | AH3: {=IFERROR(INDEX('B1 - TCO ML 19T'!$C$182:$AG$182,MATCH(1,('B1 - TCO ML 19T'!$C$168:$AG$168<='B1 - TCO ML 19T'!$C$165:$AG$165)*1,0)),"No Parity")} -> 2031 | AI3: {=IFERROR(INDEX('B1 - TCO ML 19T'!$C$182:$AG$182,MATCH(1,('B1 - TCO ML 19T'!$C$169:$AG$169<='B1 - TCO ML 19T'!$C$165:$AG$165)*1,0)),"No Parity")} -> 2046 | AJ3: {=IFERROR(INDEX('B1 - TCO ML 19T'!$C$182:$AG$182,MATCH(1,('B1 - TCO ML 19T'!$C$170:$AG$170<='B1 - TCO ML 19T'!$C$165:$AG$165)*1,0)),"No Parity")} -> 2046
A4: 2 | B4: B2 | C4: Market Load | D4: 28T Rigid | E4: ='AnnualSalesSummary Revised'!E5 -> 16400 | F4: =E4/$E$18 -> 0.06133822 | H4: ='AnnualSalesSummary Revised'!O5+'AnnualSalesSummary Revised'!O6 -> 34680 | I4: =H4/H$18 -> 0.075476626 | J4: =H4 -> 34680 | K4: =H4-J4 -> 0 | M4: ='AnnualSalesSummary Revised'!T5+'AnnualSalesSummary Revised'!T6 -> 38280 | N4: =M4/M$18 -> 0.067094332 | O4: =M4 -> 38280 | P4: =M4-O4 -> 0 | R4: ='AnnualSalesSummary Revised'!Y5+'AnnualSalesSummary Revised'!Y6 -> 43950 | S4: =R4/R$18 -> 0.0621421 | T4: =R4 -> 43950 | U4: =R4-T4 -> 0 | W4: ='AnnualSalesSummary Revised'!AD5+'AnnualSalesSummary Revised'!AD6 -> 51350 | X4: =W4/W$18 -> 0.060163326 | Y4: =W4 -> 51350 | Z4: =W4-Y4 -> 0 | AB4: ='AnnualSalesSummary Revised'!AI5+'AnnualSalesSummary Revised'!AI6 -> 58330 | AC4: =AB4/AB$18 -> 0.056640416 | AE4: {=IFERROR(INDEX('B2 - TCO ML 28T'!$C$182:$AG$182,MATCH(1,('B2 - TCO ML 28T'!$C$168:$AG$168<='B2 - TCO ML 28T'!$C$165:$AG$165)*1,0)),"No Parity")} -> 2032 | AF4: {=IFERROR(INDEX('B2 - TCO ML 28T'!$C$182:$AG$182,MATCH(1,('B2 - TCO ML 28T'!$C$169:$AG$169<='B2 - TCO ML 28T'!$C$165:$AG$165)*1,0)),"No Parity")} -> 2046 | AG4: {=IFERROR(INDEX('B2 - TCO ML 28T'!$C$182:$AG$182,MATCH(1,('B2 - TCO ML 28T'!$C$170:$AG$170<='B2 - TCO ML 28T'!$C$165:$AG$165)*1,0)),"No Parity")} -> 2046 | AH4: {=IFERROR(INDEX('B2 - TCO ML 28T'!$C$182:$AG$182,MATCH(1,('B2 - TCO ML 28T'!$C$168:$AG$168<='B2 - TCO ML 28T'!$C$165:$AG$165)*1,0)),"No Parity")} -> 2032 | AI4: {=IFERROR(INDEX('B2 - TCO ML 28T'!$C$182:$AG$182,MATCH(1,('B2 - TCO ML 28T'!$C$169:$AG$169<='B2 - TCO ML 28T'!$C$165:$AG$165)*1,0)),"No Parity")} -> 2046 | AJ4: {=IFERROR(INDEX('B2 - TCO ML 28T'!$C$182:$AG$182,MATCH(1,('B2 - TCO ML 28T'!$C$170:$AG$170<='B2 - TCO ML 28T'!$C$165:$AG$165)*1,0)),"No Parity")} -> 2046
A5: 3 | B5: B3 | C5: Market Load | D5: 48T Rigid | E5: ='AnnualSalesSummary Revised'!E7 -> 10810 | F5: =E5/$E$18 -> 0.040430864 | H5: =SUM('AnnualSalesSummary Revised'!O7:O10) -> 29780 | I5: =H5/H$18 -> 0.064812397 | J5: =SUM('AnnualSalesSummary Revised'!O7) -> 20630 | K5: =H5-J5 -> 9150 | M5: =SUM('AnnualSalesSummary Revised'!T7:T10) -> 32870 | N5: =M5/M$18 -> 0.057612087 | O5: =SUM('AnnualSalesSummary Revised'!T7) -> 22770 | P5: =M5-O5 -> 10100 | R5: =SUM('AnnualSalesSummary Revised'!Y7:Y10) -> 37730 | S5: =R5/R$18 -> 0.053347473 | T5: =SUM('AnnualSalesSummary Revised'!Y7) -> 26130 | U5: =R5-T5 -> 11600 | W5: =SUM('AnnualSalesSummary Revised'!AD7:AD10) -> 44100 | X5: =W5/W$18 -> 0.05166899 | Y5: =SUM('AnnualSalesSummary Revised'!AD7) -> 30530 | Z5: =W5-Y5 -> 13570 | AB5: =SUM('AnnualSalesSummary Revised'!AI7:AI10) -> 50100 | AC5: =AB5/AB$18 -> 0.048648806 | AE5: {=IFERROR(INDEX('B3 - TCO ML 48T '!$C$182:$AG$182,MATCH(1,('B3 - TCO ML 48T '!$C$168:$AG$168<='B3 - TCO ML 48T '!$C$165:$AG$165)*1,0)),"No Parity")} -> 2028 | AF5: {=IFERROR(INDEX('B3 - TCO ML 48T '!$C$182:$AG$182,MATCH(1,('B3 - TCO ML 48T '!$C$169:$AG$169<='B3 - TCO ML 48T '!$C$165:$AG$165)*1,0)),"No Parity")} -> 2045 | AG5: {=IFERROR(INDEX('B3 - TCO ML 48T '!$C$182:$AG$182,MATCH(1,('B3 - TCO ML 48T '!$C$170:$AG$170<='B3 - TCO ML 48T '!$C$165:$AG$165)*1,0)),"No Parity")} -> 2045 | AH5: {=IFERROR(INDEX('B3 - TCO ML 48T '!$C$182:$AG$182,MATCH(1,('B3 - TCO ML 48T '!$C$168:$AG$168<='B3 - TCO ML 48T '!$C$165:$AG$165)*1,0)),"No Parity")} -> 2028 | AI5: {=IFERROR(INDEX('B3 - TCO ML 48T '!$C$182:$AG$182,MATCH(1,('B3 - TCO ML 48T '!$C$169:$AG$169<='B3 - TCO ML 48T '!$C$165:$AG$165)*1,0)),"No Parity")} -> 2045 | AJ5: {=IFERROR(INDEX('B3 - TCO ML 48T '!$C$182:$AG$182,MATCH(1,('B3 - TCO ML 48T '!$C$170:$AG$170<='B3 - TCO ML 48T '!$C$165:$AG$165)*1,0)),"No Parity")} -> 2045
A6: 4 | B6: B4 | C6: Parcel Load and FMCG | D6: 19T Rigid | E6: ='AnnualSalesSummary Revised'!E12 -> 9140 | F6: =E6/$E$18 -> 0.034184837 | H6: ='AnnualSalesSummary Revised'!O12 -> 19210 | I6: =H6/H$18 -> 0.041808131 | J6: =H6 -> 19210 | K6: =H6-J6 -> 0 | M6: ='AnnualSalesSummary Revised'!T12 -> 26920 | N6: =M6/M$18 -> 0.04718337 | O6: =M6 -> 26920 | P6: =M6-O6 -> 0 | R6: ='AnnualSalesSummary Revised'!Y12 -> 35660 | S6: =R6/R$18 -> 0.050420643 | T6: =R6 -> 35660 | U6: =R6-T6 -> 0 | W6: ='AnnualSalesSummary Revised'!AD12 -> 45000 | X6: =W6/W$18 -> 0.05272346 | Y6: =W6 -> 45000 | Z6: =W6-Y6 -> 0 | AB6: ='AnnualSalesSummary Revised'!AI12 -> 54190 | AC6: =AB6/AB$18 -> 0.052620335 | AE6: {=IFERROR(INDEX('B4 - TCO PL&FMCG 19T '!$C$182:$AG$182,MATCH(1,('B4 - TCO PL&FMCG 19T '!$C$168:$AG$168<='B4 - TCO PL&FMCG 19T '!$C$165:$AG$165)*1,0)),"No Parity")} -> 2030 | AF6: {=IFERROR(INDEX('B4 - TCO PL&FMCG 19T '!$C$182:$AG$182,MATCH(1,('B4 - TCO PL&FMCG 19T '!$C$169:$AG$169<='B4 - TCO PL&FMCG 19T '!$C$165:$AG$165)*1,0)),"No Parity")} -> 2046 | AG6: {=IFERROR(INDEX('B4 - TCO PL&FMCG 19T '!$C$182:$AG$182,MATCH(1,('B4 - TCO PL&FMCG 19T '!$C$170:$AG$170<='B4 - TCO PL&FMCG 19T '!$C$165:$AG$165)*1,0)),"No Parity")} -> 2046 | AH6: {=IFERROR(INDEX('B4 - TCO PL&FMCG 19T '!$C$182:$AG$182,MATCH(1,('B4 - TCO PL&FMCG 19T '!$C$168:$AG$168<='B4 - TCO PL&FMCG 19T '!$C$165:$AG$165)*1,0)),"No Parity")} -> 2030 | AI6: {=IFERROR(INDEX('B4 - TCO PL&FMCG 19T '!$C$182:$AG$182,MATCH(1,('B4 - TCO PL&FMCG 19T '!$C$169:$AG$169<='B4 - TCO PL&FMCG 19T '!$C$165:$AG$165)*1,0)),"No Parity")} -> 2046 | AJ6: {=IFERROR(INDEX('B4 - TCO PL&FMCG 19T '!$C$182:$AG$182,MATCH(1,('B4 - TCO PL&FMCG 19T '!$C$170:$AG$170<='B4 - TCO PL&FMCG 19T '!$C$165:$AG$165)*1,0)),"No Parity")} -> 2046
A7: 5 | B7: B5 | C7: Parcel Load and FMCG | D7: 28T Rigid | E7: ='AnnualSalesSummary Revised'!E13 -> 7310 | F7: =E7/$E$18 -> 0.02734039 | H7: =SUM('AnnualSalesSummary Revised'!O13:O18) -> 43730 | I7: =H7/H$18 -> 0.095172804 | J7: =SUM('AnnualSalesSummary Revised'!O13:O15) -> 28760 | K7: =H7-J7 -> 14970 | M7: =SUM('AnnualSalesSummary Revised'!T13:T18) -> 61330 | N7: =M7/M$18 -> 0.10749465 | O7: =SUM('AnnualSalesSummary Revised'!T13:T15) -> 40330 | P7: =M7-O7 -> 21000 | R7: =SUM('AnnualSalesSummary Revised'!Y13:Y18) -> 81270 | S7: =R7/R$18 -> 0.11490986 | T7: =SUM('AnnualSalesSummary Revised'!Y13:Y15) -> 53450 | U7: =R7-T7 -> 27820 | W7: =SUM('AnnualSalesSummary Revised'!AD13:AD18) -> 102560 | X7: =W7/W$18 -> 0.12016262 | Y7: =SUM('AnnualSalesSummary Revised'!AD13:AD15) -> 67450 | Z7: =W7-Y7 -> 35110 | AB7: =SUM('AnnualSalesSummary Revised'!AI13:AI18) -> 123530 | AC7: =AB7/AB$18 -> 0.11995184 | AE7: {=IFERROR(INDEX('B5 - TCO PL&FMCG 28T '!$C$182:$AG$182,MATCH(1,('B5 - TCO PL&FMCG 28T '!$C$168:$AG$168<='B5 - TCO PL&FMCG 28T '!$C$165:$AG$165)*1,0)),"No Parity")} -> 2031 | AF7: {=IFERROR(INDEX('B5 - TCO PL&FMCG 28T '!$C$182:$AG$182,MATCH(1,('B5 - TCO PL&FMCG 28T '!$C$169:$AG$169<='B5 - TCO PL&FMCG 28T '!$C$165:$AG$165)*1,0)),"No Parity")} -> 2045 | AG7: {=IFERROR(INDEX('B5 - TCO PL&FMCG 28T '!$C$182:$AG$182,MATCH(1,('B5 - TCO PL&FMCG 28T '!$C$170:$AG$170<='B5 - TCO PL&FMCG 28T '!$C$165:$AG$165)*1,0)),"No Parity")} -> 2046 | AH7: {=IFERROR(INDEX('B5 - TCO PL&FMCG 28T '!$C$182:$AG$182,MATCH(1,('B5 - TCO PL&FMCG 28T '!$C$168:$AG$168<='B5 - TCO PL&FMCG 28T '!$C$165:$AG$165)*1,0)),"No Parity")} -> 2031 | AI7: {=IFERROR(INDEX('B5 - TCO PL&FMCG 28T '!$C$182:$AG$182,MATCH(1,('B5 - TCO PL&FMCG 28T '!$C$169:$AG$169<='B5 - TCO PL&FMCG 28T '!$C$165:$AG$165)*1,0)),"No Parity")} -> 2045 | AJ7: {=IFERROR(INDEX('B5 - TCO PL&FMCG 28T '!$C$182:$AG$182,MATCH(1,('B5 - TCO PL&FMCG 28T '!$C$170:$AG$170<='B5 - TCO PL&FMCG 28T '!$C$165:$AG$165)*1,0)),"No Parity")} -> 2046
A8: 6 | B8: B6 | C8: Perishables | D8: 15T Rigid | E8: ='AnnualSalesSummary Revised'!E20 -> 8870 | F8: =E8/$E$18 -> 0.033175001 | H8: ='AnnualSalesSummary Revised'!O19 -> 27900 | I8: =H8/H$18 -> 0.060720815 | J8: =SUM('AnnualSalesSummary Revised'!O20:O23) -> 27230 | K8: =H8-J8 -> 670 | M8: ='AnnualSalesSummary Revised'!T19 -> 36630 | N8: =M8/M$18 -> 0.064202335 | O8: =SUM('AnnualSalesSummary Revised'!T20:T23) -> 35750 | P8: =M8-O8 -> 880 | R8: ='AnnualSalesSummary Revised'!Y19 -> 49420 | S8: =R8/R$18 -> 0.069876281 | T8: =SUM('AnnualSalesSummary Revised'!Y20:Y23) -> 48230 | U8: =R8-T8 -> 1190 | W8: ='AnnualSalesSummary Revised'!AD19 -> 61240 | X8: =W8/W$18 -> 0.07175077 | Y8: =SUM('AnnualSalesSummary Revised'!AD20:AD23) -> 59770 | Z8: =W8-Y8 -> 1470 | AB8: ='AnnualSalesSummary Revised'!AI19 -> 75210 | AC8: =AB8/AB$18 -> 0.073031471 | AE8: {=IFERROR(INDEX('B6 Perishables 15T'!$C$182:$AG$182,MATCH(1,('B6 Perishables 15T'!$C$168:$AG$168<='B6 Perishables 15T'!$C$165:$AG$165)*1,0)),"No Parity")} -> 2031 | AF8: {=IFERROR(INDEX('B6 Perishables 15T'!$C$182:$AG$182,MATCH(1,('B6 Perishables 15T'!$C$169:$AG$169<='B6 Perishables 15T'!$C$165:$AG$165)*1,0)),"No Parity")} -> 2046 | AG8: {=IFERROR(INDEX('B6 Perishables 15T'!$C$182:$AG$182,MATCH(1,('B6 Perishables 15T'!$C$170:$AG$170<='B6 Perishables 15T'!$C$165:$AG$165)*1,0)),"No Parity")} -> 2046 | AH8: {=IFERROR(INDEX('B6 Perishables 15T'!$C$182:$AG$182,MATCH(1,('B6 Perishables 15T'!$C$168:$AG$168<='B6 Perishables 15T'!$C$165:$AG$165)*1,0)),"No Parity")} -> 2031 | AI8: {=IFERROR(INDEX('B6 Perishables 15T'!$C$182:$AG$182,MATCH(1,('B6 Perishables 15T'!$C$169:$AG$169<='B6 Perishables 15T'!$C$165:$AG$165)*1,0)),"No Parity")} -> 2046 | AJ8: {=IFERROR(INDEX('B6 Perishables 15T'!$C$182:$AG$182,MATCH(1,('B6 Perishables 15T'!$C$170:$AG$170<='B6 Perishables 15T'!$C$165:$AG$165)*1,0)),"No Parity")} -> 2046
A9: 7 | B9: B7 | C9: Construction & Mining | D9: 28T Tip | E9: ='AnnualSalesSummary Revised'!E29 -> 30170 | F9: =E9/$E$18 -> 0.11283988 | H9: ='AnnualSalesSummary Revised'!O29+'AnnualSalesSummary Revised'!O28 -> 57980 | I9: =H9/H$18 -> 0.12618612 | J9: =H9 -> 57980 | K9: =H9-J9 -> 0 | M9: ='AnnualSalesSummary Revised'!T29+'AnnualSalesSummary Revised'!T28 -> 69860 | N9: =M9/M$18 -> 0.1224454 | O9: =M9 -> 69860 | P9: =M9-O9 -> 0 | R9: ='AnnualSalesSummary Revised'!Y29+'AnnualSalesSummary Revised'!Y28 -> 85820 | S9: =R9/R$18 -> 0.12134323 | T9: =R9 -> 85820 | U9: =R9-T9 -> 0 | W9: ='AnnualSalesSummary Revised'!AD29+'AnnualSalesSummary Revised'!AD28 -> 101390 | X9: =W9/W$18 -> 0.11879181 | Y9: =W9 -> 101390 | Z9: =W9-Y9 -> 0 | AB9: ='AnnualSalesSummary Revised'!AI29+'AnnualSalesSummary Revised'!AI28 -> 122150 | AC9: =AB9/AB$18 -> 0.11861181 | AE9: {=IFERROR(INDEX('B7 C&M 28Tip'!$C$182:$AG$182,MATCH(1,('B7 C&M 28Tip'!$C$168:$AG$168<='B7 C&M 28Tip'!$C$165:$AG$165)*1,0)),"No Parity")} -> 2032 | AF9: {=IFERROR(INDEX('B7 C&M 28Tip'!$C$182:$AG$182,MATCH(1,('B7 C&M 28Tip'!$C$169:$AG$169<='B7 C&M 28Tip'!$C$165:$AG$165)*1,0)),"No Parity")} -> 2046 | AG9: {=IFERROR(INDEX('B7 C&M 28Tip'!$C$182:$AG$182,MATCH(1,('B7 C&M 28Tip'!$C$170:$AG$170<='B7 C&M 28Tip'!$C$165:$AG$165)*1,0)),"No Parity")} -> 2046 | AH9: {=IFERROR(INDEX('B7 C&M 28Tip'!$C$182:$AG$182,MATCH(1,('B7 C&M 28Tip'!$C$168:$AG$168<='B7 C&M 28Tip'!$C$165:$AG$165)*1,0)),"No Parity")} -> 2032 | AI9: {=IFERROR(INDEX('B7 C&M 28Tip'!$C$182:$AG$182,MATCH(1,('B7 C&M 28Tip'!$C$169:$AG$169<='B7 C&M 28Tip'!$C$165:$AG$165)*1,0)),"No Parity")} -> 2046 | AJ9: {=IFERROR(INDEX('B7 C&M 28Tip'!$C$182:$AG$182,MATCH(1,('B7 C&M 28Tip'!$C$170:$AG$170<='B7 C&M 28Tip'!$C$165:$AG$165)*1,0)),"No Parity")} -> 2046
A10: 8 | B10: B8 | C10: Construction & Mining | D10: 35T Tip | E10: ='AnnualSalesSummary Revised'!E30 -> 19090 | F10: =E10/$E$18 -> 0.071399185 | H10: =SUM('AnnualSalesSummary Revised'!O30:O34) -> 84000 | I10: =H10/H$18 -> 0.18281536 | J10: =SUM('AnnualSalesSummary Revised'!O30:O31) -> 62390 | K10: =H10-J10 -> 21610 | M10: =SUM('AnnualSalesSummary Revised'!T30:T34) -> 101210 | N10: =M10/M$18 -> 0.17739335 | O10: =SUM('AnnualSalesSummary Revised'!T30:T31) -> 75170 | P10: =M10-O10 -> 26040 | R10: =SUM('AnnualSalesSummary Revised'!Y30:Y34) -> 124320 | S10: =R10/R$18 -> 0.17577943 | T10: =SUM('AnnualSalesSummary Revised'!Y30:Y31) -> 92340 | U10: =R10-T10 -> 31980 | W10: =SUM('AnnualSalesSummary Revised'!AD30:AD34) -> 146890 | X10: =W10/W$18 -> 0.17210109 | Y10: =SUM('AnnualSalesSummary Revised'!AD30:AD31) -> 109100 | Z10: =W10-Y10 -> 37790 | AB10: =SUM('AnnualSalesSummary Revised'!AI30:AI34) -> 176980 | AC10: =AB10/AB$18 -> 0.17185361 | AE10: {=IFERROR(INDEX('B8 C&M 35Tip'!$C$182:$AG$182,MATCH(1,('B8 C&M 35Tip'!$C$168:$AG$168<='B8 C&M 35Tip'!$C$165:$AG$165)*1,0)),"No Parity")} -> 2030 | AF10: {=IFERROR(INDEX('B8 C&M 35Tip'!$C$182:$AG$182,MATCH(1,('B8 C&M 35Tip'!$C$169:$AG$169<='B8 C&M 35Tip'!$C$165:$AG$165)*1,0)),"No Parity")} -> 2045 | AG10: {=IFERROR(INDEX('B8 C&M 35Tip'!$C$182:$AG$182,MATCH(1,('B8 C&M 35Tip'!$C$170:$AG$170<='B8 C&M 35Tip'!$C$165:$AG$165)*1,0)),"No Parity")} -> 2045 | AH10: {=IFERROR(INDEX('B8 C&M 35Tip'!$C$182:$AG$182,MATCH(1,('B8 C&M 35Tip'!$C$168:$AG$168<='B8 C&M 35Tip'!$C$165:$AG$165)*1,0)),"No Parity")} -> 2030 | AI10: {=IFERROR(INDEX('B8 C&M 35Tip'!$C$182:$AG$182,MATCH(1,('B8 C&M 35Tip'!$C$169:$AG$169<='B8 C&M 35Tip'!$C$165:$AG$165)*1,0)),"No Parity")} -> 2045 | AJ10: {=IFERROR(INDEX('B8 C&M 35Tip'!$C$182:$AG$182,MATCH(1,('B8 C&M 35Tip'!$C$170:$AG$170<='B8 C&M 35Tip'!$C$165:$AG$165)*1,0)),"No Parity")} -> 2045
A11: 9 | B11: B9 | C11: Cement (Bulkers & Bagged) | D11: 48T Rigid | E11: ='AnnualSalesSummary Revised'!E71 -> 6960 | F11: =E11/$E$18 -> 0.026031342 | H11: =SUM('AnnualSalesSummary Revised'!O68:O71) -> 30020 | I11: =H11/H$18 -> 0.065334726 | J11: =H11 -> 30020 | K11: =H11-J11 -> 0 | M11: =SUM('AnnualSalesSummary Revised'!T68:T71) -> 37540 | N11: =M11/M$18 -> 0.065797315 | O11: =M11 -> 37540 | P11: =M11-O11 -> 0 | R11: =SUM('AnnualSalesSummary Revised'!Y68:Y71) -> 44370 | S11: =R11/R$18 -> 0.062735949 | T11: =R11 -> 44370 | U11: =R11-T11 -> 0 | W11: =SUM('AnnualSalesSummary Revised'!AD68:AD71) -> 50420 | X11: =W11/W$18 -> 0.059073707 | Y11: =W11 -> 50420 | Z11: =W11-Y11 -> 0 | AB11: =SUM('AnnualSalesSummary Revised'!AI68:AI71) -> 56220 | AC11: =AB11/AB$18 -> 0.054591535 | AE11: {=IFERROR(INDEX('B9 Cement 48T Rigid '!$C$182:$AG$182,MATCH(1,('B9 Cement 48T Rigid '!$C$168:$AG$168<='B9 Cement 48T Rigid '!$C$165:$AG$165)*1,0)),"No Parity")} -> 2027 | AF11: {=IFERROR(INDEX('B9 Cement 48T Rigid '!$C$182:$AG$182,MATCH(1,('B9 Cement 48T Rigid '!$C$169:$AG$169<='B9 Cement 48T Rigid '!$C$165:$AG$165)*1,0)),"No Parity")} -> 2045 | AG11: {=IFERROR(INDEX('B9 Cement 48T Rigid '!$C$182:$AG$182,MATCH(1,('B9 Cement 48T Rigid '!$C$170:$AG$170<='B9 Cement 48T Rigid '!$C$165:$AG$165)*1,0)),"No Parity")} -> 2045 | AH11: {=IFERROR(INDEX('B9 Cement 48T Rigid '!$C$182:$AG$182,MATCH(1,('B9 Cement 48T Rigid '!$C$168:$AG$168<='B9 Cement 48T Rigid '!$C$165:$AG$165)*1,0)),"No Parity")} -> 2027 | AI11: {=IFERROR(INDEX('B9 Cement 48T Rigid '!$C$182:$AG$182,MATCH(1,('B9 Cement 48T Rigid '!$C$169:$AG$169<='B9 Cement 48T Rigid '!$C$165:$AG$165)*1,0)),"No Parity")} -> 2045 | AJ11: {=IFERROR(INDEX('B9 Cement 48T Rigid '!$C$182:$AG$182,MATCH(1,('B9 Cement 48T Rigid '!$C$170:$AG$170<='B9 Cement 48T Rigid '!$C$165:$AG$165)*1,0)),"No Parity")} -> 2045
A12: 10 | B12: B10 | C12: Cement (Bulkers & Bagged) | D12: 55T Tractor | E12: ='AnnualSalesSummary Revised'!E74 -> 15260 | F12: =E12/$E$18 -> 0.057074466 | H12: =SUM('AnnualSalesSummary Revised'!O72:O74) -> 22470 | I12: =H12/H$18 -> 0.048903108 | J12: 0 | K12: =H12-J12 -> 22470 | M12: =SUM('AnnualSalesSummary Revised'!T72:T74) -> 28120 | N12: =M12/M$18 -> 0.049286641 | O12: 0 | P12: =M12-O12 -> 28120 | R12: =SUM('AnnualSalesSummary Revised'!Y72:Y74) -> 33230 | S12: =R12/R$18 -> 0.0469848 | T12: 0 | U12: =R12-T12 -> 33230 | W12: =SUM('AnnualSalesSummary Revised'!AD72:AD74) -> 37770 | X12: =W12/W$18 -> 0.044252557 | Y12: 0 | Z12: =W12-Y12 -> 37770 | AB12: =SUM('AnnualSalesSummary Revised'!AI72:AI74) -> 42120 | AC12: =AB12/AB$18 -> 0.040899954 | AE12: {=IFERROR(INDEX('B10 Cement 55 Tractor '!$C$182:$AG$182,MATCH(1,('B10 Cement 55 Tractor '!$C$168:$AG$168<='B10 Cement 55 Tractor '!$C$165:$AG$165)*1,0)),"No Parity")} -> 2026 | AF12: {=IFERROR(INDEX('B10 Cement 55 Tractor '!$C$182:$AG$182,MATCH(1,('B10 Cement 55 Tractor '!$C$169:$AG$169<='B10 Cement 55 Tractor '!$C$165:$AG$165)*1,0)),"No Parity")} -> 2045 | AG12: {=IFERROR(INDEX('B10 Cement 55 Tractor '!$C$182:$AG$182,MATCH(1,('B10 Cement 55 Tractor '!$C$170:$AG$170<='B10 Cement 55 Tractor '!$C$165:$AG$165)*1,0)),"No Parity")} -> 2045 | AH12: {=IFERROR(INDEX('B10 Cement 55 Tractor '!$C$182:$AG$182,MATCH(1,('B10 Cement 55 Tractor '!$C$168:$AG$168<='B10 Cement 55 Tractor '!$C$165:$AG$165)*1,0)),"No Parity")} -> 2026 | AI12: {=IFERROR(INDEX('B10 Cement 55 Tractor '!$C$182:$AG$182,MATCH(1,('B10 Cement 55 Tractor '!$C$169:$AG$169<='B10 Cement 55 Tractor '!$C$165:$AG$165)*1,0)),"No Parity")} -> 2045 | AJ12: {=IFERROR(INDEX('B10 Cement 55 Tractor '!$C$182:$AG$182,MATCH(1,('B10 Cement 55 Tractor '!$C$170:$AG$170<='B10 Cement 55 Tractor '!$C$165:$AG$165)*1,0)),"No Parity")} -> 2045
A13: 11 | B13: B11 | C13: Steel & metal products | D13: 55T Tractor | E13: ='AnnualSalesSummary Revised'!E42 -> 18950 | F13: =E13/$E$18 -> 0.070875566 | H13: ='AnnualSalesSummary Revised'!O35 -> 35940 | I13: =H13/H$18 -> 0.078218856 | J13: ='AnnualSalesSummary Revised'!O36 -> 1860 | K13: =H13-J13 -> 34080 | M13: ='AnnualSalesSummary Revised'!T35 -> 51820 | N13: =M13/M$18 -> 0.090826235 | O13: ='AnnualSalesSummary Revised'!T36 -> 2680 | P13: =M13-O13 -> 49140 | R13: ='AnnualSalesSummary Revised'!Y35 -> 68660 | S13: =R13/R$18 -> 0.09708024 | T13: ='AnnualSalesSummary Revised'!Y36 -> 3550 | U13: =R13-T13 -> 65110 | W13: ='AnnualSalesSummary Revised'!AD35 -> 90100 | X13: =W13/W$18 -> 0.10556408 | Y13: ='AnnualSalesSummary Revised'!AD36 -> 4650 | Z13: =W13-Y13 -> 85450 | AB13: ='AnnualSalesSummary Revised'!AI35 -> 122850 | AC13: =AB13/AB$18 -> 0.11929153 | AE13: {=IFERROR(INDEX('B11 S&M 55Tractor'!$C$182:$AG$182,MATCH(1,('B11 S&M 55Tractor'!$C$168:$AG$168<='B11 S&M 55Tractor'!$C$165:$AG$165)*1,0)),"No Parity")} -> 2026 | AF13: {=IFERROR(INDEX('B11 S&M 55Tractor'!$C$182:$AG$182,MATCH(1,('B11 S&M 55Tractor'!$C$169:$AG$169<='B11 S&M 55Tractor'!$C$165:$AG$165)*1,0)),"No Parity")} -> 2045 | AG13: {=IFERROR(INDEX('B11 S&M 55Tractor'!$C$182:$AG$182,MATCH(1,('B11 S&M 55Tractor'!$C$170:$AG$170<='B11 S&M 55Tractor'!$C$165:$AG$165)*1,0)),"No Parity")} -> 2046 | AH13: {=IFERROR(INDEX('B11 S&M 55Tractor'!$C$182:$AG$182,MATCH(1,('B11 S&M 55Tractor'!$C$168:$AG$168<='B11 S&M 55Tractor'!$C$165:$AG$165)*1,0)),"No Parity")} -> 2026 | AI13: {=IFERROR(INDEX('B11 S&M 55Tractor'!$C$182:$AG$182,MATCH(1,('B11 S&M 55Tractor'!$C$169:$AG$169<='B11 S&M 55Tractor'!$C$165:$AG$165)*1,0)),"No Parity")} -> 2045 | AJ13: {=IFERROR(INDEX('B11 S&M 55Tractor'!$C$182:$AG$182,MATCH(1,('B11 S&M 55Tractor'!$C$170:$AG$170<='B11 S&M 55Tractor'!$C$165:$AG$165)*1,0)),"No Parity")} -> 2046
A14: 12 | B14: B12 | C14: Tankers - POL & CNG cascades | D14: 28T Rigid | E14: ='AnnualSalesSummary Revised'!E45 -> 3900 | F14: =E14/$E$18 -> 0.014586528 | H14: ='AnnualSalesSummary Revised'!O43 -> 14390 | I14: =H14/H$18 -> 0.031318012 | J14: =H14 -> 14390 | K14: =H14-J14 -> 0 | M14: ='AnnualSalesSummary Revised'!T43 -> 18030 | N14: =M14/M$18 -> 0.031601641 | O14: =M14 -> 18030 | P14: =M14-O14 -> 0 | R14: ='AnnualSalesSummary Revised'!Y43 -> 21520 | S14: =R14/R$18 -> 0.030427713 | T14: =R14 -> 21520 | U14: =R14-T14 -> 0 | W14: ='AnnualSalesSummary Revised'!AD43 -> 23550 | X14: =W14/W$18 -> 0.027591944 | Y14: =W14 -> 23550 | Z14: =W14-Y14 -> 0 | AB14: ='AnnualSalesSummary Revised'!AI43 -> 26780 | AC14: =AB14/AB$18 -> 0.026004292 | AE14: {=IFERROR(INDEX('B12 POL&CNG Tankers 28T'!$C$182:$AG$182,MATCH(1,('B12 POL&CNG Tankers 28T'!$C$168:$AG$168<='B12 POL&CNG Tankers 28T'!$C$165:$AG$165)*1,0)),"No Parity")} -> 2034 | AF14: {=IFERROR(INDEX('B12 POL&CNG Tankers 28T'!$C$182:$AG$182,MATCH(1,('B12 POL&CNG Tankers 28T'!$C$169:$AG$169<='B12 POL&CNG Tankers 28T'!$C$165:$AG$165)*1,0)),"No Parity")} -> 2046 | AG14: {=IFERROR(INDEX('B12 POL&CNG Tankers 28T'!$C$182:$AG$182,MATCH(1,('B12 POL&CNG Tankers 28T'!$C$170:$AG$170<='B12 POL&CNG Tankers 28T'!$C$165:$AG$165)*1,0)),"No Parity")} -> 2048 | AH14: {=IFERROR(INDEX('B12 POL&CNG Tankers 28T'!$C$182:$AG$182,MATCH(1,('B12 POL&CNG Tankers 28T'!$C$168:$AG$168<='B12 POL&CNG Tankers 28T'!$C$165:$AG$165)*1,0)),"No Parity")} -> 2034 | AI14: {=IFERROR(INDEX('B12 POL&CNG Tankers 28T'!$C$182:$AG$182,MATCH(1,('B12 POL&CNG Tankers 28T'!$C$169:$AG$169<='B12 POL&CNG Tankers 28T'!$C$165:$AG$165)*1,0)),"No Parity")} -> 2046 | AJ14: {=IFERROR(INDEX('B12 POL&CNG Tankers 28T'!$C$182:$AG$182,MATCH(1,('B12 POL&CNG Tankers 28T'!$C$170:$AG$170<='B12 POL&CNG Tankers 28T'!$C$165:$AG$165)*1,0)),"No Parity")} -> 2048
A15: 13 | B15: B13 | C15: Tankers - Non POL | D15: 28T Rigid | E15: ='AnnualSalesSummary Revised'!E53 -> 4030 | F15: =E15/$E$18 -> 0.015072746 | H15: ='AnnualSalesSummary Revised'!O51 -> 14100 | I15: =H15/H$18 -> 0.030686863 | J15: =H15 -> 14100 | K15: =H15-J15 -> 0 | M15: ='AnnualSalesSummary Revised'!T51 -> 18520 | N15: =M15/M$18 -> 0.032460476 | O15: =M15 -> 18520 | P15: =M15-O15 -> 0 | R15: ='AnnualSalesSummary Revised'!Y51 -> 25730 | S15: =R15/R$18 -> 0.036380346 | T15: =R15 -> 25730 | U15: =R15-T15 -> 0 | W15: ='AnnualSalesSummary Revised'!AD51 -> 35370 | X15: =W15/W$18 -> 0.041440639 | Y15: =W15 -> 35370 | Z15: =W15-Y15 -> 0 | AB15: ='AnnualSalesSummary Revised'!AI51 -> 50090 | AC15: =AB15/AB$18 -> 0.048639096 | AE15: {=IFERROR(INDEX('B13 Non POL Tankers 28T'!$C$182:$AG$182,MATCH(1,('B13 Non POL Tankers 28T'!$C$168:$AG$168<='B13 Non POL Tankers 28T'!$C$165:$AG$165)*1,0)),"No Parity")} -> 2032 | AF15: {=IFERROR(INDEX('B13 Non POL Tankers 28T'!$C$182:$AG$182,MATCH(1,('B13 Non POL Tankers 28T'!$C$169:$AG$169<='B13 Non POL Tankers 28T'!$C$165:$AG$165)*1,0)),"No Parity")} -> 2046 | AG15: {=IFERROR(INDEX('B13 Non POL Tankers 28T'!$C$182:$AG$182,MATCH(1,('B13 Non POL Tankers 28T'!$C$170:$AG$170<='B13 Non POL Tankers 28T'!$C$165:$AG$165)*1,0)),"No Parity")} -> 2046 | AH15: {=IFERROR(INDEX('B13 Non POL Tankers 28T'!$C$182:$AG$182,MATCH(1,('B13 Non POL Tankers 28T'!$C$168:$AG$168<='B13 Non POL Tankers 28T'!$C$165:$AG$165)*1,0)),"No Parity")} -> 2032 | AI15: {=IFERROR(INDEX('B13 Non POL Tankers 28T'!$C$182:$AG$182,MATCH(1,('B13 Non POL Tankers 28T'!$C$169:$AG$169<='B13 Non POL Tankers 28T'!$C$165:$AG$165)*1,0)),"No Parity")} -> 2046 | AJ15: {=IFERROR(INDEX('B13 Non POL Tankers 28T'!$C$182:$AG$182,MATCH(1,('B13 Non POL Tankers 28T'!$C$170:$AG$170<='B13 Non POL Tankers 28T'!$C$165:$AG$165)*1,0)),"No Parity")} -> 2046
A16: 14 | B16: B14 | C16: LPG bullet tankers | D16: 40T Tractor | E16: ='AnnualSalesSummary Revised'!E64 -> 1980 | F16: =E16/$E$18 -> 0.0074054681 | H16: ='AnnualSalesSummary Revised'!O59 -> 8590 | I16: =H16/H$18 -> 0.018695047 | J16: =SUM('AnnualSalesSummary Revised'!O60:O63) -> 5650 | K16: =H16-J16 -> 2940 | M16: ='AnnualSalesSummary Revised'!T59 -> 8920 | N16: =M16/M$18 -> 0.015634311 | O16: =SUM('AnnualSalesSummary Revised'!T60:T63) -> 5870 | P16: =M16-O16 -> 3050 | R16: ='AnnualSalesSummary Revised'!Y59 -> 9100 | S16: =R16/R$18 -> 0.012866737 | T16: =SUM('AnnualSalesSummary Revised'!Y60:Y63) -> 5990 | U16: =R16-T16 -> 3110 | W16: ='AnnualSalesSummary Revised'!AD59 -> 9460 | X16: =W16/W$18 -> 0.011083643 | Y16: =SUM('AnnualSalesSummary Revised'!AD60:AD63) -> 6220 | Z16: =W16-Y16 -> 3240 | AB16: ='AnnualSalesSummary Revised'!AI59 -> 9570 | AC16: =AB16/AB$18 -> 0.0092927959 | AE16: {=IFERROR(INDEX('B14 LPG Tankers 40T'!$C$182:$AG$182,MATCH(1,('B14 LPG Tankers 40T'!$C$168:$AG$168<='B14 LPG Tankers 40T'!$C$165:$AG$165)*1,0)),"No Parity")} -> 2035 | AF16: {=IFERROR(INDEX('B14 LPG Tankers 40T'!$C$182:$AG$182,MATCH(1,('B14 LPG Tankers 40T'!$C$169:$AG$169<='B14 LPG Tankers 40T'!$C$165:$AG$165)*1,0)),"No Parity")} -> 2046 | AG16: {=IFERROR(INDEX('B14 LPG Tankers 40T'!$C$182:$AG$182,MATCH(1,('B14 LPG Tankers 40T'!$C$170:$AG$170<='B14 LPG Tankers 40T'!$C$165:$AG$165)*1,0)),"No Parity")} -> 2048 | AH16: {=IFERROR(INDEX('B14 LPG Tankers 40T'!$C$182:$AG$182,MATCH(1,('B14 LPG Tankers 40T'!$C$168:$AG$168<='B14 LPG Tankers 40T'!$C$165:$AG$165)*1,0)),"No Parity")} -> 2035 | AI16: {=IFERROR(INDEX('B14 LPG Tankers 40T'!$C$182:$AG$182,MATCH(1,('B14 LPG Tankers 40T'!$C$169:$AG$169<='B14 LPG Tankers 40T'!$C$165:$AG$165)*1,0)),"No Parity")} -> 2046 | AJ16: {=IFERROR(INDEX('B14 LPG Tankers 40T'!$C$182:$AG$182,MATCH(1,('B14 LPG Tankers 40T'!$C$170:$AG$170<='B14 LPG Tankers 40T'!$C$165:$AG$165)*1,0)),"No Parity")} -> 2048
D17: Total | E17: =SUM(E3:E16) -> 172110 | F17: =E17/$E$18 -> 0.6437147 | H17: =SUM(H3:H16) -> 459480 | I17: =H17/H$18 -> 1 | J17: =SUM(J3:J16) -> 353590 | K17: =SUM(K3:K16) -> 105890 | M17: =SUM(M3:M16) -> 570540 | N17: =M17/M$18 -> 1 | O17: =SUM(O3:O16) -> 432210 | P17: =SUM(P3:P16) -> 138330 | R17: =SUM(R3:R16) -> 707250 | S17: =R17/R$18 -> 1 | T17: =SUM(T3:T16) -> 533210 | U17: =SUM(U3:U16) -> 174040 | W17: =SUM(W3:W16) -> 853510 | X17: =W17/W$18 -> 1 | Y17: =SUM(Y3:Y16) -> 639110 | Z17: =SUM(Z3:Z16) -> 214400 | AB17: =SUM(AB3:AB16) -> 1029830 | AC17: =AB17/AB$18 -> 1 | AE17: =(AE3*$E$3+AE4*$E$4+AE5*$E$5+AE6*$E$6+AE7*$E$7+AE8*$E$8+$E$9*AE9+AE10*$E$10+$E$11*AE11+AE12*$E$12+$E$13*AE13+AE14*$E$14+$E$15*AE15+AE16*$E$16)/$E$17 -> 2029.8999 | AF17: =(AF3*$E$3+AF4*$E$4+AF5*$E$5+AF6*$E$6+AF7*$E$7+AF8*$E$8+$E$9*AF9+AF10*$E$10+$E$11*AF11+AF12*$E$12+$E$13*AF13+AF14*$E$14+$E$15*AF15+AF16*$E$16)/$E$17 -> 2045.5446 | AG17: =(AG3*$E$3+AG4*$E$4+AG5*$E$5+AG6*$E$6+AG7*$E$7+AG8*$E$8+$E$9*AG9+AG10*$E$10+$E$11*AG11+AG12*$E$12+$E$13*AG13+AG14*$E$14+$E$15*AG15+AG16*$E$16)/$E$17 -> 2045.7655 | AH17: =(AH3*$E$3+AH4*$E$4+AH5*$E$5+AH6*$E$6+AH7*$E$7+AH8*$E$8+$E$9*AH9+AH10*$E$10+$E$11*AH11+AH12*$E$12+$E$13*AH13+AH14*$E$14+$E$15*AH15+AH16*$E$16)/$E$17 -> 2029.8999 | AI17: =(AI3*$E$3+AI4*$E$4+AI5*$E$5+AI6*$E$6+AI7*$E$7+AI8*$E$8+$E$9*AI9+AI10*$E$10+$E$11*AI11+AI12*$E$12+$E$13*AI13+AI14*$E$14+$E$15*AI15+AI16*$E$16)/$E$17 -> 2045.5446 | AJ17: =(AJ3*$E$3+AJ4*$E$4+AJ5*$E$5+AJ6*$E$6+AJ7*$E$7+AJ8*$E$8+$E$9*AJ9+AJ10*$E$10+$E$11*AJ11+AJ12*$E$12+$E$13*AJ13+AJ14*$E$14+$E$15*AJ15+AJ16*$E$16)/$E$17 -> 2045.7655
D18: 2025 TIV: | E18: ='AnnualSalesSummary Revised'!E75 -> 267370 | H18: ='AnnualSalesSummary Revised'!O75 -> 459480 | M18: ='AnnualSalesSummary Revised'!T75 -> 570540 | O18: =M17/M18% -> 100 | R18: ='AnnualSalesSummary Revised'!Y75 -> 707250 | T18: =R17/R18% -> 100 | W18: ='AnnualSalesSummary Revised'!AD75 -> 853510 | Y18: =W17/W18% -> 100 | AB18: ='AnnualSalesSummary Revised'!AI75 -> 1029830 | AC18: Inflection Point (3%): | AE18: =ROUND((AE17+1),0) -> 2031 | AF18: =ROUND((AF17+5),0) -> 2051 | AG18: =ROUND((AG17+5),0) -> 2051 | AH18: =AH17+5 -> 2034.8999 | AI18: =AI17+5 -> 2050.5446 | AJ18: =AJ17+5 -> 2050.7655
H19: 2035 TIV | M19: 2040 TIV | R19: 2045 TIV | W19: 2050 TIV | AB19: 2050 TIV

Sheet Changing with year
A1: Year | C1: 2025 | D1: 2026 | E1: 2027 | F1: 2028 | G1: 2029 | H1: 2030 | I1: 2031 | J1: 2032 | K1: 2033 | L1: 2034 | M1: 2035 | N1: 2036 | O1: 2037 | P1: 2038 | Q1: 2039 | R1: 2040 | S1: 2041 | T1: 2042 | U1: 2043 | V1: 2044 | W1: 2045 | X1: 2046 | Y1: 2047 | Z1: 2048 | AA1: 2049 | AB1: 2050 | AC1: 2051 | AD1: 2052 | AE1: 2053 | AF1: 2054 | AG1: 2055 | AH1: % Change 2026-30 | AI1: % Change 2031-40 | AJ1: % Change 2041-50 | AK1: % Change in 2051-55
C2: 2025 | D2: 2026 | E2: 2027 | F2: 2028 | G2: 2029 | H2: 2030 | I2: 2031 | J2: 2032 | K2: 2033 | L2: 2034 | M2: 2035 | N2: 2036 | O2: 2037 | P2: 2038 | Q2: 2039 | R2: 2040 | S2: 2041 | T2: 2042 | U2: 2043 | V2: 2044 | W2: 2045 | X2: 2046 | Y2: 2047 | Z2: 2048 | AA2: 2049 | AB2: 2050 | AC2: 2051 | AD2: 2052 | AE2: 2053 | AF2: 2054 | AG2: 2055
A3: Diesel Price per litre | C3: 88.926296 | D3: 99 | E3: =D3*(1+$AH$3) -> 100.98 | F3: =E3*(1+$AH$3) -> 102.9996 | G3: =F3*(1+$AH$3) -> 105.05959 | H3: =G3*(1+$AH$3) -> 107.16078 | I3: =H3*(1+$AH$3) -> 109.304 | J3: =I3*(1+$AH$3) -> 111.49008 | K3: =J3*(1+$AH$3) -> 113.71988 | L3: =K3*(1+$AH$3) -> 115.99428 | ... AG3: =AF3*(1+$AH$3) -> 175.80862 | AH3: 0.02
A4: Adblue Price | C4: 55 | D4: =C4*(1+$AH4) -> 56.375 | E4: =D4*(1+$AH4) -> 57.784375 | F4: =E4*(1+$AH4) -> 59.228984 | G4: =F4*(1+$AH4) -> 60.709709 | H4: =G4*(1+$AH4) -> 62.227452 | I4: =H4*(1+$AI4) -> 63.783138 | J4: =I4*(1+$AI4) -> 65.377716 | K4: =J4*(1+$AI4) -> 67.012159 | L4: =K4*(1+$AI4) -> 68.687463 | M4: =L4*(1+$AI4) -> 70.40465 | N4: =M4*(1+$AI4) -> 72.164766 | O4: =N4*(1+$AI4) -> 73.968885 | P4: =O4*(1+$AI4) -> 75.818107 | ... R4: =Q4*(1+$AI4) -> 79.656399 | S4: =R4*(1+$AJ4) -> 81.647809 | T4: =S4*(1+$AJ4) -> 83.689004 | U4: =T4*(1+$AJ4) -> 85.781229 | V4: =U4*(1+$AJ4) -> 87.92576 | W4: =V4*(1+$AJ4) -> 90.123904 | X4: =W4*(1+$AJ4) -> 92.377002 | Y4: =X4*(1+$AJ4) -> 94.686427 | Z4: =Y4*(1+$AJ4) -> 97.053588 | ... AB4: =AA4*(1+$AJ4) -> 101.96693 | AC4: =AB4*(1+$AK4) -> 104.5161 | AD4: =AC4*(1+$AK4) -> 107.129 | AE4: =AD4*(1+$AK4) -> 109.80723 | AF4: =AE4*(1+$AK4) -> 112.55241 | AG4: =AF4*(1+$AK4) -> 115.36622 | AH4: 0.025 | AI4: 0.025 | AJ4: 0.025 | AK4: 0.025
A5: CNG Price per kg | C5: 87 | D5: 91.5 | E5: =D5*(1+$AH5) -> 94.245 | F5: =E5*(1+$AH5) -> 97.07235 | G5: =F5*(1+$AH5) -> 99.984521 | H5: =G5*(1+$AH5) -> 102.98406 | I5: =H5*(1+$AI5) -> 106.07358 | J5: =I5*(1+$AI5) -> 109.25579 | K5: =J5*(1+$AI5) -> 112.53346 | L5: =K5*(1+$AI5) -> 115.90946 | M5: =L5*(1+$AI5) -> 119.38675 | N5: =M5*(1+$AI5) -> 122.96835 | O5: =N5*(1+$AI5) -> 126.6574 | P5: =O5*(1+$AI5) -> 130.45712 | ... R5: =Q5*(1+$AI5) -> 138.40196 | S5: =R5*(1+$AJ5) -> 142.55402 | T5: =S5*(1+$AJ5) -> 146.83064 | U5: =T5*(1+$AJ5) -> 151.23556 | V5: =U5*(1+$AJ5) -> 155.77263 | W5: =V5*(1+$AJ5) -> 160.4458 | X5: =W5*(1+$AJ5) -> 165.25918 | Y5: =X5*(1+$AJ5) -> 170.21695 | Z5: =Y5*(1+$AJ5) -> 175.32346 | ... AB5: =AA5*(1+$AJ5) -> 186.00066 | AC5: =AB5*(1+$AK5) -> 191.58068 | AD5: =AC5*(1+$AK5) -> 197.3281 | AE5: =AD5*(1+$AK5) -> 203.24794 | AF5: =AE5*(1+$AK5) -> 209.34538 | AG5: =AF5*(1+$AK5) -> 215.62574 | AH5: 0.03 | AI5: 0.03 | AJ5: 0.03 | AK5: 0.03
A6: LNG Price per kg | C6: 83 | D6: 86 | E6: =D6*(1+$AH6) -> 88.58 | F6: =E6*(1+$AH6) -> 91.2374 | G6: =F6*(1+$AH6) -> 93.974522 | H6: =G6*(1+$AH6) -> 96.793758 | I6: =H6*(1+$AI6) -> 99.69757 | J6: =I6*(1+$AI6) -> 102.6885 | K6: =J6*(1+$AI6) -> 105.76915 | L6: =K6*(1+$AI6) -> 108.94223 | M6: =L6*(1+$AI6) -> 112.21049 | N6: =M6*(1+$AI6) -> 115.57681 | O6: =N6*(1+$AI6) -> 119.04411 | P6: =O6*(1+$AI6) -> 122.61544 | ... R6: =Q6*(1+$AI6) -> 130.08272 | S6: =R6*(1+$AJ6) -> 133.9852 | T6: =S6*(1+$AJ6) -> 138.00475 | U6: =T6*(1+$AJ6) -> 142.1449 | V6: =U6*(1+$AJ6) -> 146.40924 | W6: =V6*(1+$AJ6) -> 150.80152 | X6: =W6*(1+$AJ6) -> 155.32557 | Y6: =X6*(1+$AJ6) -> 159.98533 | Z6: =Y6*(1+$AJ6) -> 164.78489 | ... AB6: =AA6*(1+$AJ6) -> 174.82029 | AC6: =AB6*(1+$AK6) -> 180.0649 | AD6: =AC6*(1+$AK6) -> 185.46685 | AE6: =AD6*(1+$AK6) -> 191.03085 | AF6: =AE6*(1+$AK6) -> 196.76178 | AG6: =AF6*(1+$AK6) -> 202.66463 | AH6: 0.03 | AI6: 0.03 | AJ6: 0.03 | AK6: 0.03
A7: Cost of Electricity for Green H2 Prodn. | B7: Rs./kg | C7: =(C15-$AH7)*$AH8 -> 291.5 | D7: =(D15-$AH7)*$AH8 -> 299.45 | E7: =(E15-$AH7)*$AH8 -> 307.559 | F7: =(F15-$AH7)*$AH8 -> 315.83018 | G7: =(G15-$AH7)*$AH8 -> 324.26678 | H7: =(H15-$AH7)*$AH8 -> 332.87212 | I7: =(I15-$AI7)*$AI8 -> 305.7497 | J7: =(J15-$AI7)*$AI8 -> 297.6347 | K7: =(K15-$AI7)*$AI8 -> 289.68201 | L7: =(L15-$AI7)*$AI8 -> 281.88837 | M7: =(M15-$AI7)*$AI8 -> 274.2506 | N7: =(N15-$AI7)*$AI8 -> 266.76559 | O7: =(O15-$AI7)*$AI8 -> 259.43028 | P7: =(P15-$AI7)*$AI8 -> 252.24167 | ... R7: =(R15-$AI7)*$AI8 -> 238.2929 | S7: =(S15-$AJ7)*$AJ8 -> 211.41897 | T7: =(T15-$AJ7)*$AJ8 -> 208.40478 | U7: =(U15-$AJ7)*$AJ8 -> 205.42074 | V7: =(V15-$AJ7)*$AJ8 -> 202.46653 | W7: =(W15-$AJ7)*$AJ8 -> 199.54186 | X7: =(X15-$AJ7)*$AJ8 -> 196.64645 | Y7: =(Y15-$AJ7)*$AJ8 -> 193.77998 | Z7: =(Z15-$AJ7)*$AJ8 -> 190.94218 | ... AB7: =(AB15-$AJ7)*$AJ8 -> 185.35143 | AC7: =(AC15-$AK7)*$AK8 -> 179.41954 | AD7: =(AD15-$AK7)*$AK8 -> 186.00502 | AE7: =(AE15-$AK7)*$AK8 -> 192.75515 | AF7: =(AF15-$AK7)*$AK8 -> 199.67403 | AG7: =(AG15-$AK7)*$AK8 -> 206.76588 | AH7: 2 | AI7: 2 | AJ7: 2 | AK7: 2 | AL7: Reduction in general power tariff
AH8: 53 | AI8: 50 | AJ8: 45 | AK8: 42 | AL8: kWh per kg of H2 Prodn.
A9: Capex (@$1.25/kg. as per RIL) | B9: Rs./kg | C9: 115 | D9: =C9*(1+$AH9) -> 111.55 | E9: =D9*(1+$AH9) -> 108.2035 | F9: =E9*(1+$AH9) -> 104.95739 | G9: =F9*(1+$AH9) -> 101.80867 | H9: =G9*(1+$AH9) -> 98.754413 | I9: =H9*(1+$AI9) -> 94.804236 | J9: =I9*(1+$AI9) -> 91.012067 | K9: =J9*(1+$AI9) -> 87.371584 | L9: =K9*(1+$AI9) -> 83.876721 | M9: =L9*(1+$AI9) -> 80.521652 | N9: =M9*(1+$AI9) -> 77.300786 | O9: =N9*(1+$AI9) -> 74.208755 | P9: =O9*(1+$AI9) -> 71.240404 | ... R9: =Q9*(1+$AI9) -> 65.655157 | S9: =R9*(1+$AJ9) -> 62.372399 | T9: =S9*(1+$AJ9) -> 59.253779 | U9: =T9*(1+$AJ9) -> 56.29109 | V9: =U9*(1+$AJ9) -> 53.476535 | W9: =V9*(1+$AJ9) -> 50.802709 | X9: =W9*(1+$AJ9) -> 48.262573 | Y9: =X9*(1+$AJ9) -> 45.849445 | Z9: =Y9*(1+$AJ9) -> 43.556972 | ... AB9: =AA9*(1+$AJ9) -> 39.310168 | AC9: =AB9*(1+$AK9) -> 37.344659 | AD9: =AC9*(1+$AK9) -> 35.477426 | AE9: =AD9*(1+$AK9) -> 33.703555 | AF9: =AE9*(1+$AK9) -> 32.018377 | AG9: =AF9*(1+$AK9) -> 30.417458 | AH9: -0.03 | AI9: -0.04 | AJ9: -0.05 | AK9: -0.05
A10: Opex & margin | B10: Rs./kg | C10: 140 | D10: =C10*(1+$AH10) -> 135.8 | E10: =D10*(1+$AH10) -> 131.726 | F10: =E10*(1+$AH10) -> 127.77422 | G10: =F10*(1+$AH10) -> 123.94099 | H10: =G10*(1+$AH10) -> 120.22276 | I10: =H10*(1+$AI10) -> 114.21163 | J10: =I10*(1+$AI10) -> 108.50104 | K10: =J10*(1+$AI10) -> 103.07599 | L10: =K10*(1+$AI10) -> 97.922192 | M10: =L10*(1+$AI10) -> 93.026083 | N10: =M10*(1+$AI10) -> 88.374779 | O10: =N10*(1+$AI10) -> 83.95604 | P10: =O10*(1+$AI10) -> 79.758238 | ... R10: =Q10*(1+$AI10) -> 71.98181 | S10: =R10*(1+$AJ10) -> 68.382719 | T10: =S10*(1+$AJ10) -> 64.963583 | U10: =T10*(1+$AJ10) -> 61.715404 | V10: =U10*(1+$AJ10) -> 58.629634 | W10: =V10*(1+$AJ10) -> 55.698152 | X10: =W10*(1+$AJ10) -> 52.913244 | Y10: =X10*(1+$AJ10) -> 50.267582 | Z10: =Y10*(1+$AJ10) -> 47.754203 | ... AB10: =AA10*(1+$AJ10) -> 43.098168 | AC10: =AB10*(1+$AK10) -> 40.94326 | AD10: =AC10*(1+$AK10) -> 38.896097 | AE10: =AD10*(1+$AK10) -> 36.951292 | AF10: =AE10*(1+$AK10) -> 35.103727 | AG10: =AF10*(1+$AK10) -> 33.348541 | AH10: -0.03 | AI10: -0.05 | AJ10: -0.05 | AK10: -0.05
A11: Green H2 Prodn cost/kg | C11: =SUM(C7:C10) -> 546.5 | D11: =SUM(D7:D10) -> 546.8 | E11: =SUM(E7:E10) -> 547.4885 | F11: =SUM(F7:F10) -> 548.5618 | G11: =SUM(G7:G10) -> 550.01645 | H11: =SUM(H7:H10) -> 551.8493 | I11: =SUM(I7:I10) -> 514.76556 | J11: =SUM(J7:J10) -> 497.14781 | ... AG11: =SUM(AG7:AG10) -> 270.53188 | AM11: For 220: | AN11: -0.04 | AO11: -0.035 | AP11: -0.03 | AQ11: -0.03 | AS11: For 330: | AT11: -0.04 | AU11: -0.03 | AV11: -0.01 | AW11: 0 | AY11: For 170: | AZ11: -0.04 | BA11: -0.03 | BB11: -0.05 | BC11: -0.05
A12: Grey H2 Prodn cost/kg | C12: 250 | D12: =C12*(1+$AH12) -> 255 | E12: =D12*(1+$AH12) -> 260.1 | F12: =E12*(1+$AH12) -> 265.302 | G12: =F12*(1+$AH12) -> 270.60804 | H12: =G12*(1+$AH12) -> 276.0202 | I12: =H12*(1+$AI12) -> 281.5406 | J12: =I12*(1+$AI12) -> 287.17142 | K12: =J12*(1+$AI12) -> 292.91485 | L12: =K12*(1+$AI12) -> 298.77314 | M12: =L12*(1+$AI12) -> 304.7486 | N12: =M12*(1+$AI12) -> 310.84358 | O12: =N12*(1+$AI12) -> 317.06045 | P12: =O12*(1+$AI12) -> 323.40166 | ... R12: =Q12*(1+$AI12) -> 336.46708 | S12: =R12*(1+$AJ12) -> 343.19643 | T12: =S12*(1+$AJ12) -> 350.06035 | U12: =T12*(1+$AJ12) -> 357.06156 | V12: =U12*(1+$AJ12) -> 364.20279 | W12: =V12*(1+$AJ12) -> 371.48685 | X12: =W12*(1+$AJ12) -> 378.91659 | Y12: =X12*(1+$AJ12) -> 386.49492 | Z12: =Y12*(1+$AJ12) -> 394.22482 | ... AB12: =AA12*(1+$AJ12) -> 410.1515 | AC12: =AB12*(1+$AK12) -> 418.35453 | AD12: =AC12*(1+$AK12) -> 426.72162 | AE12: =AD12*(1+$AK12) -> 435.25605 | AF12: =AE12*(1+$AK12) -> 443.96117 | AG12: =AF12*(1+$AK12) -> 452.8404 | AH12: 0.02 | AI12: 0.02 | AJ12: 0.02 | AK12: 0.02
A13: Grey H2 in Blend | C13: =$AH13 -> 0 | D13: =$AH13 -> 0 | E13: =$AH13 -> 0 | F13: =$AH13 -> 0 | G13: =$AH13 -> 0 | H13: =$AH13 -> 0 | I13: =$AI13 -> 0 | J13: =$AI13 -> 0 | K13: =$AI13 -> 0 | L13: =$AI13 -> 0 | M13: =$AI13 -> 0 | N13: =$AI13 -> 0 | O13: =$AI13 -> 0 | P13: =$AI13 -> 0 | ... R13: =$AI13 -> 0 | S13: =$AJ13 -> 0 | T13: =$AJ13 -> 0 | U13: =$AJ13 -> 0 | V13: =$AJ13 -> 0 | W13: =$AJ13 -> 0 | X13: =$AJ13 -> 0 | Y13: =$AJ13 -> 0 | Z13: =$AJ13 -> 0 | ... AB13: =$AJ13 -> 0 | AC13: =$AK13 -> 0 | AD13: =$AK13 -> 0 | AE13: =$AK13 -> 0 | AF13: =$AK13 -> 0 | AG13: =$AK13 -> 0 | AH13: 0 | AI13: 0 | AJ13: 0 | AK13: 0
A14: H2 Compression, storage & transmission cost/kg | C14: 175 | D14: =C14*(1+$AH14) -> 168 | E14: =D14*(1+$AH14) -> 161.28 | F14: =E14*(1+$AH14) -> 154.8288 | G14: =F14*(1+$AH14) -> 148.63565 | H14: =G14*(1+$AH14) -> 142.69022 | I14: =H14*(1+$AI14) -> 138.40952 | J14: =I14*(1+$AI14) -> 134.25723 | K14: =J14*(1+$AI14) -> 130.22951 | L14: =K14*(1+$AI14) -> 126.32263 | M14: =L14*(1+$AI14) -> 122.53295 | N14: =M14*(1+$AI14) -> 118.85696 | O14: =N14*(1+$AI14) -> 115.29125 | P14: =O14*(1+$AI14) -> 111.83251 | ... R14: =Q14*(1+$AI14) -> 105.22321 | S14: =R14*(1+$AJ14) -> 102.06652 | T14: =S14*(1+$AJ14) -> 99.004521 | U14: =T14*(1+$AJ14) -> 96.034385 | V14: =U14*(1+$AJ14) -> 93.153353 | W14: =V14*(1+$AJ14) -> 90.358753 | X14: =W14*(1+$AJ14) -> 87.64799 | Y14: =X14*(1+$AJ14) -> 85.018551 | Z14: =Y14*(1+$AJ14) -> 82.467994 | ... AB14: =AA14*(1+$AJ14) -> 77.594136 | AC14: =AB14*(1+$AK14) -> 76.042253 | AD14: =AC14*(1+$AK14) -> 74.521408 | AE14: =AD14*(1+$AK14) -> 73.03098 | AF14: =AE14*(1+$AK14) -> 71.57036 | AG14: =AF14*(1+$AK14) -> 70.138953 | AH14: -0.04 | AI14: -0.03 | AJ14: -0.03 | AK14: -0.02 | AM14: For 70: | AN14: -0.04 | AO14: -0.03 | AP14: -0.03 | AQ14: -0.02 | AS14: For 100: | AT14: -0.03 | AU14: -0.02 | AV14: -0.02 | AW14: 0 | AY14: For 70: | AZ14: -0.04 | BA14: -0.03 | BB14: -0.03 | BC14: -0.02
A15: Cost of electricity from DISCOM Rs./kWh | B15: Rs./kWh | C15: 7.5 | D15: =C15*(1+$AH15) -> 7.65 | E15: =D15*(1+$AH15) -> 7.803 | F15: =E15*(1+$AH15) -> 7.95906 | G15: =F15*(1+$AH15) -> 8.1182412 | H15: =G15*(1+$AH15) -> 8.280606 | I15: =H15*(1+$AI15) -> 8.1149939 | J15: =I15*(1+$AI15) -> 7.952694 | K15: =J15*(1+$AI15) -> 7.7936401 | L15: =K15*(1+$AI15) -> 7.6377673 | M15: =L15*(1+$AI15) -> 7.485012 | N15: =M15*(1+$AI15) -> 7.3353118 | O15: =N15*(1+$AI15) -> 7.1886055 | P15: =O15*(1+$AI15) -> 7.0448334 | ... R15: =Q15*(1+$AI15) -> 6.765858 | S15: =R15*(1+$AJ15) -> 6.6981994 | T15: =S15*(1+$AJ15) -> 6.6312174 | U15: =T15*(1+$AJ15) -> 6.5649053 | V15: =U15*(1+$AJ15) -> 6.4992562 | W15: =V15*(1+$AJ15) -> 6.4342636 | X15: =W15*(1+$AJ15) -> 6.369921 | Y15: =X15*(1+$AJ15) -> 6.3062218 | Z15: =Y15*(1+$AJ15) -> 6.2431596 | ... AB15: =AA15*(1+$AJ15) -> 6.1189207 | AC15: =AB15*(1+$AK15) -> 6.2718937 | AD15: =AC15*(1+$AK15) -> 6.4286911 | AE15: =AD15*(1+$AK15) -> 6.5894083 | AF15: =AE15*(1+$AK15) -> 6.7541435 | AG15: =AF15*(1+$AK15) -> 6.9229971 | AH15: 0.02 | AI15: -0.02 | AJ15: -0.01 | AK15: 0.025
A16: Fixed/Demand Charges | B16: Rs./kWh | C16: 2.3964286 | D16: 2.3964286 | E16: 2.175805 | F16: 1.9432857 | G16: 1.6728316 | H16: 1.5104762 | I16: 1.4005102 | J16: 1.3080321 | K16: 1.123965 | L16: 0.98613703 | M16: 0.88921283 | N16: 0.88921283 | O16: 0.88921283 | P16: 0.87142857 | Q16: 0.87142857 | R16: 0.88921283 | S16: 0.88921283 | T16: 0.90344023 | U16: 0.90344023 | V16: 0.90344023 | W16: 0.90344023 | X16: 0.90344023 | Y16: 0.90344023 | Z16: 0.90344023 | AA16: 0.90344023 | AB16: 0.90344023 | AC16: 0.88921283 | AD16: 0.88921283 | AE16: 0.88921283 | AF16: 0.88921283 | AG16: 0.88921283 | AM16: Increasing capacity utilisation will bring down costs initially
A17: Charging infra - Land, Capex+Opex incl Margin | B17: Rs./kWh | C17: 2.0334192 | D17: 2.0334192 | E17: 2.1642995 | F17: 2.2359561 | G17: 2.2380733 | H17: 2.3266148 | I17: 0.99733671 | J17: 0.99064315 | K17: 0.89495066 | L17: 0.81859666 | M17: 0.77649244 | N17: 0.82556219 | O17: 0.87789832 | P17: 0.91897893 | Q17: 0.97750497 | R17: 1.0615692 | S17: 1.1337624 | T17: 1.2312109 | U17: 1.3132588 | V17: 1.4007941 | W17: 1.4948746 | X17: 1.5952661 | Y17: 1.7016853 | Z17: 1.8152751 | AA17: 1.9372954 | AB17: 2.0667734 | AC17: 2.1709014 | AD17: 2.3121547 | AE17: 2.4604122 | AF17: 2.6196598 | AG17: 2.791612
A18: Electricity incl CAAS | C18: =C17+C16+C15 -> 11.929848 | D18: =D17+D16+D15 -> 12.079848 | E18: =E17+E16+E15 -> 12.143104 | F18: =F17+F16+F15 -> 12.138302 | G18: =G17+G16+G15 -> 12.029146 | H18: =H17+H16+H15 -> 12.117697 | I18: =I17+I16+I15 -> 10.512841 | J18: =J17+J16+J15 -> 10.251369 | ... AG18: =AG17+AG16+AG15 -> 10.603822 | AL18: 0 | AM18: Energy Subsidy per kWh till 2040 | AN18: 2056 | AO18: 2057 | AP18: 2058 | AQ18: 2059 | AR18: 2060 | AS18: 2061 | AT18: 2062 | AU18: 2063 | AV18: 2064 | AW18: 2065
A19: Battery cost per kwh | C19: 9900 | D19: =C19*(1+$AH19) -> 9751.5 | E19: =D19*(1+$AH19) -> 9605.2275 | F19: =E19*(1+$AH19) -> 9461.1491 | G19: =F19*(1+$AH19) -> 9319.2319 | H19: =G19*(1+$AH19) -> 9179.4434 | I19: =H19*(1+$AI19) -> 8949.9573 | J19: =I19*(1+$AI19) -> 8726.2084 | K19: =J19*(1+$AI19) -> 8508.0531 | L19: =K19*(1+$AI19) -> 8295.3518 | M19: =L19*(1+$AI19) -> 8087.968 | N19: =M19*(1+$AI19) -> 7885.7688 | O19: =N19*(1+$AI19) -> 7688.6246 | P19: =O19*(1+$AI19) -> 7496.409 | ... R19: =Q19*(1+$AI19) -> 7126.2738 | S19: =R19*(1+$AJ19) -> 7055.0111 | T19: =S19*(1+$AJ19) -> 6984.4609 | U19: =T19*(1+$AJ19) -> 6914.6163 | V19: =U19*(1+$AJ19) -> 6845.4702 | W19: =V19*(1+$AJ19) -> 6777.0155 | X19: =W19*(1+$AJ19) -> 6709.2453 | Y19: =X19*(1+$AJ19) -> 6642.1529 | Z19: =Y19*(1+$AJ19) -> 6575.7313 | ... AB19: =AA19*(1+$AJ19) -> 6444.8743 | AC19: =AB19*(1+$AK19) -> 6509.323 | AD19: =AC19*(1+$AK19) -> 6574.4163 | AE19: =AD19*(1+$AK19) -> 6640.1604 | AF19: =AE19*(1+$AK19) -> 6706.562 | AG19: =AF19*(1+$AK19) -> 6773.6276 | AH19: -0.015 | AI19: -0.025 | AJ19: -0.01 | AK19: 0.01 | AN19: =AG19*(1+$AK19) -> 6841.3639 | AO19: =AN19*(1+$AK19) -> 6909.7776 | AP19: =AO19*(1+$AK19) -> 6978.8753 | AQ19: =AP19*(1+$AK19) -> 7048.6641 | AR19: =AQ19*(1+$AK19) -> 7119.1507 | AS19: =AR19*(1+$AK19) -> 7190.3422 | AT19: =AS19*(1+$AK19) -> 7262.2457 | AU19: =AT19*(1+$AK19) -> 7334.8681 | AV19: =AU19*(1+$AK19) -> 7408.2168 | AW19: =AV19*(1+$AK19) -> 7482.299
A20: Fuel Cell cost per kW | C20: 36000 | D20: =C20*(1+$AH20) -> 34920 | E20: =D20*(1+$AH20) -> 33872.4 | F20: =E20*(1+$AH20) -> 32856.228 | G20: =F20*(1+$AH20) -> 31870.541 | H20: =G20*(1+$AH20) -> 30914.425 | I20: =H20*(1+$AI20) -> 29986.992 | J20: =I20*(1+$AI20) -> 29087.382 | K20: =J20*(1+$AI20) -> 28214.761 | L20: =K20*(1+$AI20) -> 27368.318 | M20: =L20*(1+$AI20) -> 26547.269 | N20: =M20*(1+$AI20) -> 25750.851 | O20: =N20*(1+$AI20) -> 24978.325 | P20: =O20*(1+$AI20) -> 24228.975 | ... R20: =Q20*(1+$AI20) -> 22797.043 | S20: =R20*(1+$AJ20) -> 22341.102 | T20: =S20*(1+$AJ20) -> 21894.28 | U20: =T20*(1+$AJ20) -> 21456.394 | V20: =U20*(1+$AJ20) -> 21027.266 | W20: =V20*(1+$AJ20) -> 20606.721 | X20: =W20*(1+$AJ20) -> 20194.587 | Y20: =X20*(1+$AJ20) -> 19790.695 | Z20: =Y20*(1+$AJ20) -> 19394.881 | ... AB20: =AA20*(1+$AJ20) -> 18626.844 | AC20: =AB20*(1+$AK20) -> 18813.112 | AD20: =AC20*(1+$AK20) -> 19001.243 | AE20: =AD20*(1+$AK20) -> 19191.256 | AF20: =AE20*(1+$AK20) -> 19383.168 | AG20: =AF20*(1+$AK20) -> 19577 | AH20: -0.03 | AI20: -0.03 | AJ20: -0.02 | AK20: 0.01 | AN20: =AG20*(1+$AK20) -> 19772.77 | AO20: =AN20*(1+$AK20) -> 19970.498 | AP20: =AO20*(1+$AK20) -> 20170.203 | AQ20: =AP20*(1+$AK20) -> 20371.905 | AR20: =AQ20*(1+$AK20) -> 20575.624 | AS20: =AR20*(1+$AK20) -> 20781.38 | AT20: =AS20*(1+$AK20) -> 20989.194 | AU20: =AT20*(1+$AK20) -> 21199.086 | AV20: =AU20*(1+$AK20) -> 21411.077 | AW20: =AV20*(1+$AK20) -> 21625.187
A21: LNG Tank cost/kg of LNG | C21: 3050 | D21: =C21*(1+$AH21) -> 3080.5 | E21: =D21*(1+$AH21) -> 3111.305 | F21: =E21*(1+$AH21) -> 3142.418 | G21: =F21*(1+$AH21) -> 3173.8422 | H21: =G21*(1+$AH21) -> 3205.5807 | I21: =H21*(1+$AI21) -> 3237.6365 | J21: =I21*(1+$AI21) -> 3270.0128 | K21: =J21*(1+$AI21) -> 3302.713 | L21: =K21*(1+$AI21) -> 3335.7401 | M21: =L21*(1+$AI21) -> 3369.0975 | N21: =M21*(1+$AI21) -> 3402.7885 | O21: =N21*(1+$AI21) -> 3436.8163 | P21: =O21*(1+$AI21) -> 3471.1845 | ... R21: =Q21*(1+$AI21) -> 3540.9553 | S21: =R21*(1+$AJ21) -> 3576.3649 | T21: =S21*(1+$AJ21) -> 3612.1285 | U21: =T21*(1+$AJ21) -> 3648.2498 | V21: =U21*(1+$AJ21) -> 3684.7323 | W21: =V21*(1+$AJ21) -> 3721.5796 | X21: =W21*(1+$AJ21) -> 3758.7954 | Y21: =X21*(1+$AJ21) -> 3796.3834 | Z21: =Y21*(1+$AJ21) -> 3834.3472 | ... AB21: =AA21*(1+$AJ21) -> 3911.4176 | AC21: =AB21*(1+$AK21) -> 3950.5318 | AD21: =AC21*(1+$AK21) -> 3990.0371 | AE21: =AD21*(1+$AK21) -> 4029.9374 | AF21: =AE21*(1+$AK21) -> 4070.2368 | AG21: =AF21*(1+$AK21) -> 4110.9392 | AH21: 0.01 | AI21: 0.01 | AJ21: 0.01 | AK21: 0.01
A22: LNG Valves & Piping cost/vehicle | C22: 100000 | D22: =C22*(1+$AH22) -> 101000 | E22: =D22*(1+$AH22) -> 102010 | F22: =E22*(1+$AH22) -> 103030.1 | G22: =F22*(1+$AH22) -> 104060.4 | H22: =G22*(1+$AH22) -> 105101.01 | I22: =H22*(1+$AI22) -> 106152.02 | J22: =I22*(1+$AI22) -> 107213.54 | K22: =J22*(1+$AI22) -> 108285.67 | L22: =K22*(1+$AI22) -> 109368.53 | M22: =L22*(1+$AI22) -> 110462.21 | N22: =M22*(1+$AI22) -> 111566.83 | O22: =N22*(1+$AI22) -> 112682.5 | P22: =O22*(1+$AI22) -> 113809.33 | ... R22: =Q22*(1+$AI22) -> 116096.9 | S22: =R22*(1+$AJ22) -> 117257.86 | T22: =S22*(1+$AJ22) -> 118430.44 | U22: =T22*(1+$AJ22) -> 119614.75 | V22: =U22*(1+$AJ22) -> 120810.9 | W22: =V22*(1+$AJ22) -> 122019 | X22: =W22*(1+$AJ22) -> 123239.19 | Y22: =X22*(1+$AJ22) -> 124471.59 | Z22: =Y22*(1+$AJ22) -> 125716.3 | ... AB22: =AA22*(1+$AJ22) -> 128243.2 | AC22: =AB22*(1+$AK22) -> 129525.63 | AD22: =AC22*(1+$AK22) -> 130820.89 | AE22: =AD22*(1+$AK22) -> 132129.1 | AF22: =AE22*(1+$AK22) -> 133450.39 | AG22: =AF22*(1+$AK22) -> 134784.89 | AH22: 0.01 | AI22: 0.01 | AJ22: 0.01 | AK22: 0.01
A23: H2 Tank cost/kg of H2 | C23: 56000 | D23: =C23*(1+$AH23) -> 53200 | E23: =D23*(1+$AH23) -> 50540 | F23: =E23*(1+$AH23) -> 48013 | G23: =F23*(1+$AH23) -> 45612.35 | H23: =G23*(1+$AH23) -> 43331.732 | I23: =H23*(1+$AI23) -> 41598.463 | J23: =I23*(1+$AI23) -> 39934.525 | K23: =J23*(1+$AI23) -> 38337.144 | L23: =K23*(1+$AI23) -> 36803.658 | M23: =L23*(1+$AI23) -> 35331.512 | N23: =M23*(1+$AI23) -> 33918.251 | O23: =N23*(1+$AI23) -> 32561.521 | P23: =O23*(1+$AI23) -> 31259.06 | ... R23: =Q23*(1+$AI23) -> 28808.35 | S23: =R23*(1+$AJ23) -> 29096.433 | T23: =S23*(1+$AJ23) -> 29387.398 | U23: =T23*(1+$AJ23) -> 29681.272 | V23: =U23*(1+$AJ23) -> 29978.084 | W23: =V23*(1+$AJ23) -> 30277.865 | X23: =W23*(1+$AJ23) -> 30580.644 | Y23: =X23*(1+$AJ23) -> 30886.45 | Z23: =Y23*(1+$AJ23) -> 31195.315 | ... AB23: =AA23*(1+$AJ23) -> 31822.341 | AC23: =AB23*(1+$AK23) -> 32140.564 | AD23: =AC23*(1+$AK23) -> 32461.97 | AE23: =AD23*(1+$AK23) -> 32786.589 | AF23: =AE23*(1+$AK23) -> 33114.455 | AG23: =AF23*(1+$AK23) -> 33445.6 | AH23: -0.05 | AI23: -0.04 | AJ23: 0.01 | AK23: 0.01
A25: Cost of engine and transmission | C25: 2025 | D25: 2026 | E25: 2027 | F25: 2028 | G25: 2029 | H25: 2030 | I25: 2031 | J25: 2032 | K25: 2033 | L25: 2034 | M25: 2035 | N25: 2036 | O25: 2037 | P25: 2038 | Q25: 2039 | R25: 2040 | S25: 2041 | T25: 2042 | U25: 2043 | V25: 2044 | W25: 2045 | X25: 2046 | Y25: 2047 | Z25: 2048 | AA25: 2049 | AB25: 2050 | AC25: 2051 | AD25: 2052 | AE25: 2053 | AF25: 2054 | AG25: 2055
